Workbook

Sheet DATA ENTRY FORM2
D3: SOUTHVILLE INTERNATIONAL SCHOOL AND COLLEGES
D4: SUPPLIER EVALUATION FORM
C7: Evaluation Date: | D7: 44498
C9: Company Name: | D9: Atlas Super Flags | H9: PRF No.: | I9: 102099 | M9: Requisitioner Details
C11: Address: | H11: PO Number: | I11: PO29704 | M11: Requisitioner Name:
C13: Item/s Delivered: | D13: =IFERROR(__xludf.DUMMYFUNCTION("IFERROR(FILTER('PRF Details'!D3:D48, 'PRF Details'!A3:A48 = I9))"),"INTERNATIONAL FLAGS ") -> INTERNATIONAL FLAGS | H13: Remarks: | M13: Email Address:
C17: CRITERIA | F17: Purchasing | G17: Requisitioner | H17: AMD | I17: REMARKS (Kindly put reasons for item below 4)
C18: A. Accurate Delivery/quality | F18: 5 | G18: 5 | H18: 5
C19: B. Competitive Price | F19: 5 | G19: 5 | H19: 5
C20: C. Timeliness of Delivery | F20: 5 | G20: 5 | H20: 5
C21: D. After Sales Service | F21: 5 | G21: 5 | H21: 5
C22: E. Compliance with Regulatory Requirements and School Policies | F22: 5 | G22: N/A | H22: N/A
E24: AVERAGE | F24: =IFERROR(AVERAGE(F18:F22),"") -> 5 | G24: =IFERROR(AVERAGE(G18:G21),"") -> 5 | H24: =IFERROR(AVERAGE(H18:H21),"") -> 5
E26: FINAL RATING | F26: =IFERROR(AVERAGE(F24:H24),"") -> 5
C28: RUBRIC | I28: RECOMMENDATIONS
C29: 5 EXCELLENT - Supplier conformed to all requirements, accurate delivery, good quality, competitive price, timeliness of delivery, after sales, compliance to regulatory requirements. | I29: 4.5 - 5.0 || Strongly Recommended
C30: 4 VERY GOOD - Supplier conformed to all requirements, accurate delivery, good quality, competitive price, timeliness of delivery, after sales, compliance to regulatory requirements. | I30: 4.0 - 4.49 || Recommended
C31: 3 GOOD - Supplier conformed to all requirements, accurate delivery, good quality, competitive price, timeliness of delivery, after sales, compliance to regulatory requirements (1-2 deviations). | I31: 3.5 - 3.99 || Acceptable
C32: 2 FAIR - Supplier conformed to requirements, specifications and standards of good with 3-4 non-conformance issues. | I32: 3.0 - 3.49 || Acceptable w/ some Reservation
C33: 1 POOR - Supplier conformed to few requirements, specifications and standards of good workmanship with 6 or more non-conformance. | I33: Below 3.0 || Not Recommended
C35: Note: This form is used after the delivery of item/s. This will be done per transaction w/ supplier
C37: CONFORMED BY
C39: SUPPLIER
C41: EVALUATOR | E41: NOTED BY | H41: APPROVED BY
I42: Dr. Jocelyn P. Tizon
C43: Name & Signature | F43: Next Level Head/Manager | I43: President

Sheet July 2024
B1: March | C1: 2024 | D1: Average: | E1: =AVERAGE(E9:E103) -> 4.6614236 | H1: Company | I1: Month Start | J1: Month End | K1: Year
H2: Amazon | I2: July | J2: December | K2: 2024
A4: Supplier Evalution Report for the Month of July 2024
D7: Average: | E7: =AVERAGE(E9:E15) -> 4.3792857
A8: # | B8: PRF# | C8: PO# | D8: DATE | E8: AVERAGE | G8: # | H8: PRF# | I8: PO# | J8: DATE | K8: SUPPLIER | L8: AVERAGE
A9: 1 | B9: =IFERROR(__xludf.DUMMYFUNCTION("IFERROR(FILTER(DATABASE!A:B, TEXT(DATABASE!D:D, ""MMMM"")=B1, YEAR(DATABASE!D:D)=C1), ""No Data Found"")"),104215.0) -> 104215 | C9: =IFERROR(__xludf.DUMMYFUNCTION("""COMPUTED_VALUE"""),"PO31159") -> PO31159 | D9: =IFERROR(__xludf.DUMMYFUNCTION("FILTER(DATABASE!D:D, TEXT(DATABASE!D:D, ""MMMM"")=B1, YEAR(DATABASE!D:D)=C1)"),45352.0) -> 45352 | E9: =IFERROR(__xludf.DUMMYFUNCTION("FILTER(DATABASE!AC:AC, TEXT(DATABASE!D:D, ""MMMM"")=B1, YEAR(DATABASE!D:D)=C1)"),5.0) -> 5 | G9: 1
A10: 2 | B10: =IFERROR(__xludf.DUMMYFUNCTION("""COMPUTED_VALUE"""),104053.0) -> 104053 | C10: =IFERROR(__xludf.DUMMYFUNCTION("""COMPUTED_VALUE"""),"PO31185") -> PO31185 | D10: =IFERROR(__xludf.DUMMYFUNCTION("""COMPUTED_VALUE"""),45353.0) -> 45353 | E10: =IFERROR(__xludf.DUMMYFUNCTION("""COMPUTED_VALUE"""),4.575) -> 4.575 | G10: 2
A11: 3 | B11: =IFERROR(__xludf.DUMMYFUNCTION("""COMPUTED_VALUE"""),104230.0) -> 104230 | C11: =IFERROR(__xludf.DUMMYFUNCTION("""COMPUTED_VALUE"""),"PO31193") -> PO31193 | D11: =IFERROR(__xludf.DUMMYFUNCTION("""COMPUTED_VALUE"""),45355.0) -> 45355 | E11: =IFERROR(__xludf.DUMMYFUNCTION("""COMPUTED_VALUE"""),4.75) -> 4.75 | G11: 3
A12: 4 | B12: =IFERROR(__xludf.DUMMYFUNCTION("""COMPUTED_VALUE"""),104248.0) -> 104248 | C12: =IFERROR(__xludf.DUMMYFUNCTION("""COMPUTED_VALUE"""),"PO31178") -> PO31178 | D12: =IFERROR(__xludf.DUMMYFUNCTION("""COMPUTED_VALUE"""),45356.0) -> 45356 | E12: =IFERROR(__xludf.DUMMYFUNCTION("""COMPUTED_VALUE"""),4.5) -> 4.5 | G12: 4
A13: 5 | B13: =IFERROR(__xludf.DUMMYFUNCTION("""COMPUTED_VALUE"""),104186.0) -> 104186 | C13: =IFERROR(__xludf.DUMMYFUNCTION("""COMPUTED_VALUE"""),"PO31179") -> PO31179 | D13: =IFERROR(__xludf.DUMMYFUNCTION("""COMPUTED_VALUE"""),45356.0) -> 45356 | E13: =IFERROR(__xludf.DUMMYFUNCTION("""COMPUTED_VALUE"""),4.496666666666667) -> 4.4966667 | G13: 5
A14: 6 | B14: =IFERROR(__xludf.DUMMYFUNCTION("""COMPUTED_VALUE"""),104102.0) -> 104102 | C14: =IFERROR(__xludf.DUMMYFUNCTION("""COMPUTED_VALUE"""),"PO31146") -> PO31146 | D14: =IFERROR(__xludf.DUMMYFUNCTION("""COMPUTED_VALUE"""),45356.0) -> 45356 | E14: =IFERROR(__xludf.DUMMYFUNCTION("""COMPUTED_VALUE"""),3.6666666666666665) -> 3.6666667 | G14: 6
A15: 7 | B15: =IFERROR(__xludf.DUMMYFUNCTION("""COMPUTED_VALUE"""),104102.0) -> 104102 | C15: =IFERROR(__xludf.DUMMYFUNCTION("""COMPUTED_VALUE"""),"PO31147") -> PO31147 | D15: =IFERROR(__xludf.DUMMYFUNCTION("""COMPUTED_VALUE"""),45356.0) -> 45356 | E15: =IFERROR(__xludf.DUMMYFUNCTION("""COMPUTED_VALUE"""),3.6666666666666665) -> 3.6666667 | G15: 7
A16: 8 | B16: =IFERROR(__xludf.DUMMYFUNCTION("""COMPUTED_VALUE"""),104179.0) -> 104179 | C16: =IFERROR(__xludf.DUMMYFUNCTION("""COMPUTED_VALUE"""),"PO31191") -> PO31191 | D16: =IFERROR(__xludf.DUMMYFUNCTION("""COMPUTED_VALUE"""),45357.0) -> 45357 | E16: =IFERROR(__xludf.DUMMYFUNCTION("""COMPUTED_VALUE"""),4.496666666666667) -> 4.4966667 | G16: 8
A17: 9 | B17: =IFERROR(__xludf.DUMMYFUNCTION("""COMPUTED_VALUE"""),104208.0) -> 104208 | C17: =IFERROR(__xludf.DUMMYFUNCTION("""COMPUTED_VALUE"""),"PO31190") -> PO31190 | D17: =IFERROR(__xludf.DUMMYFUNCTION("""COMPUTED_VALUE"""),45357.0) -> 45357 | E17: =IFERROR(__xludf.DUMMYFUNCTION("""COMPUTED_VALUE"""),4.5) -> 4.5 | G17: 9
A18: 10 | B18: =IFERROR(__xludf.DUMMYFUNCTION("""COMPUTED_VALUE"""),104176.0) -> 104176 | C18: =IFERROR(__xludf.DUMMYFUNCTION("""COMPUTED_VALUE"""),"PO31155") -> PO31155 | D18: =IFERROR(__xludf.DUMMYFUNCTION("""COMPUTED_VALUE"""),45358.0) -> 45358 | E18: =IFERROR(__xludf.DUMMYFUNCTION("""COMPUTED_VALUE"""),5.0) -> 5 | G18: 10
A19: 11 | B19: =IFERROR(__xludf.DUMMYFUNCTION("""COMPUTED_VALUE"""),104199.0) -> 104199 | C19: =IFERROR(__xludf.DUMMYFUNCTION("""COMPUTED_VALUE"""),"PO31173") -> PO31173 | D19: =IFERROR(__xludf.DUMMYFUNCTION("""COMPUTED_VALUE"""),45359.0) -> 45359 | E19: =IFERROR(__xludf.DUMMYFUNCTION("""COMPUTED_VALUE"""),4.5) -> 4.5 | G19: 11
A20: 12 | B20: =IFERROR(__xludf.DUMMYFUNCTION("""COMPUTED_VALUE"""),104178.0) -> 104178 | C20: =IFERROR(__xludf.DUMMYFUNCTION("""COMPUTED_VALUE"""),"PO31174") -> PO31174 | D20: =IFERROR(__xludf.DUMMYFUNCTION("""COMPUTED_VALUE"""),45359.0) -> 45359 | E20: =IFERROR(__xludf.DUMMYFUNCTION("""COMPUTED_VALUE"""),4.496666666666667) -> 4.4966667
A21: 13 | B21: =IFERROR(__xludf.DUMMYFUNCTION("""COMPUTED_VALUE"""),104300.0) -> 104300 | C21: =IFERROR(__xludf.DUMMYFUNCTION("""COMPUTED_VALUE"""),"PO31203") -> PO31203 | D21: =IFERROR(__xludf.DUMMYFUNCTION("""COMPUTED_VALUE"""),45360.0) -> 45360 | E21: =IFERROR(__xludf.DUMMYFUNCTION("""COMPUTED_VALUE"""),4.833333333333333) -> 4.8333333
A22: 14 | B22: =IFERROR(__xludf.DUMMYFUNCTION("""COMPUTED_VALUE"""),104261.0) -> 104261 | C22: =IFERROR(__xludf.DUMMYFUNCTION("""COMPUTED_VALUE"""),"PO31199") -> PO31199 | D22: =IFERROR(__xludf.DUMMYFUNCTION("""COMPUTED_VALUE"""),45360.0) -> 45360 | E22: =IFERROR(__xludf.DUMMYFUNCTION("""COMPUTED_VALUE"""),5.0) -> 5
A23: 15 | B23: =IFERROR(__xludf.DUMMYFUNCTION("""COMPUTED_VALUE"""),104270.0) -> 104270 | C23: =IFERROR(__xludf.DUMMYFUNCTION("""COMPUTED_VALUE"""),"PO31211") -> PO31211 | D23: =IFERROR(__xludf.DUMMYFUNCTION("""COMPUTED_VALUE"""),45360.0) -> 45360 | E23: =IFERROR(__xludf.DUMMYFUNCTION("""COMPUTED_VALUE"""),4.75) -> 4.75
A24: 16 | B24: =IFERROR(__xludf.DUMMYFUNCTION("""COMPUTED_VALUE"""),104233.0) -> 104233 | C24: =IFERROR(__xludf.DUMMYFUNCTION("""COMPUTED_VALUE"""),"PO31192") -> PO31192 | D24: =IFERROR(__xludf.DUMMYFUNCTION("""COMPUTED_VALUE"""),45362.0) -> 45362 | E24: =IFERROR(__xludf.DUMMYFUNCTION("""COMPUTED_VALUE"""),4.75) -> 4.75
A25: 17 | B25: =IFERROR(__xludf.DUMMYFUNCTION("""COMPUTED_VALUE"""),104234.0) -> 104234 | D25: =IFERROR(__xludf.DUMMYFUNCTION("""COMPUTED_VALUE"""),45362.0) -> 45362 | E25: =IFERROR(__xludf.DUMMYFUNCTION("""COMPUTED_VALUE"""),4.75) -> 4.75
A26: 18 | B26: =IFERROR(__xludf.DUMMYFUNCTION("""COMPUTED_VALUE"""),103963.0) -> 103963 | C26: =IFERROR(__xludf.DUMMYFUNCTION("""COMPUTED_VALUE"""),"PO31181") -> PO31181 | D26: =IFERROR(__xludf.DUMMYFUNCTION("""COMPUTED_VALUE"""),45363.0) -> 45363 | E26: =IFERROR(__xludf.DUMMYFUNCTION("""COMPUTED_VALUE"""),4.666666666666667) -> 4.6666667
A27: 19 | B27: =IFERROR(__xludf.DUMMYFUNCTION("""COMPUTED_VALUE"""),104061.0) -> 104061 | C27: =IFERROR(__xludf.DUMMYFUNCTION("""COMPUTED_VALUE"""),"PO31131") -> PO31131 | D27: =IFERROR(__xludf.DUMMYFUNCTION("""COMPUTED_VALUE"""),45365.0) -> 45365 | E27: =IFERROR(__xludf.DUMMYFUNCTION("""COMPUTED_VALUE"""),4.833333333333333) -> 4.8333333
A28: 20 | B28: =IFERROR(__xludf.DUMMYFUNCTION("""COMPUTED_VALUE"""),104269.0) -> 104269 | C28: =IFERROR(__xludf.DUMMYFUNCTION("""COMPUTED_VALUE"""),"PO31200") -> PO31200 | D28: =IFERROR(__xludf.DUMMYFUNCTION("""COMPUTED_VALUE"""),45365.0) -> 45365 | E28: =IFERROR(__xludf.DUMMYFUNCTION("""COMPUTED_VALUE"""),4.75) -> 4.75
A29: 21 | B29: =IFERROR(__xludf.DUMMYFUNCTION("""COMPUTED_VALUE"""),104346.0) -> 104346 | C29: =IFERROR(__xludf.DUMMYFUNCTION("""COMPUTED_VALUE"""),"PO31230") -> PO31230 | D29: =IFERROR(__xludf.DUMMYFUNCTION("""COMPUTED_VALUE"""),45366.0) -> 45366 | E29: =IFERROR(__xludf.DUMMYFUNCTION("""COMPUTED_VALUE"""),5.0) -> 5
A30: 22 | B30: =IFERROR(__xludf.DUMMYFUNCTION("""COMPUTED_VALUE"""),104271.0) -> 104271 | C30: =IFERROR(__xludf.DUMMYFUNCTION("""COMPUTED_VALUE"""),"PO31212") -> PO31212 | D30: =IFERROR(__xludf.DUMMYFUNCTION("""COMPUTED_VALUE"""),45366.0) -> 45366 | E30: =IFERROR(__xludf.DUMMYFUNCTION("""COMPUTED_VALUE"""),4.75) -> 4.75
A31: 23 | B31: =IFERROR(__xludf.DUMMYFUNCTION("""COMPUTED_VALUE"""),104272.0) -> 104272 | C31: =IFERROR(__xludf.DUMMYFUNCTION("""COMPUTED_VALUE"""),"PO31213") -> PO31213 | D31: =IFERROR(__xludf.DUMMYFUNCTION("""COMPUTED_VALUE"""),45366.0) -> 45366 | E31: =IFERROR(__xludf.DUMMYFUNCTION("""COMPUTED_VALUE"""),4.75) -> 4.75
A32: 24 | B32: =IFERROR(__xludf.DUMMYFUNCTION("""COMPUTED_VALUE"""),104283.0) -> 104283 | C32: =IFERROR(__xludf.DUMMYFUNCTION("""COMPUTED_VALUE"""),"PO31217") -> PO31217 | D32: =IFERROR(__xludf.DUMMYFUNCTION("""COMPUTED_VALUE"""),45367.0) -> 45367 | E32: =IFERROR(__xludf.DUMMYFUNCTION("""COMPUTED_VALUE"""),4.0) -> 4
A33: 25 | B33: =IFERROR(__xludf.DUMMYFUNCTION("""COMPUTED_VALUE"""),104202.0) -> 104202 | C33: =IFERROR(__xludf.DUMMYFUNCTION("""COMPUTED_VALUE"""),"PO31241") -> PO31241 | D33: =IFERROR(__xludf.DUMMYFUNCTION("""COMPUTED_VALUE"""),45367.0) -> 45367 | E33: =IFERROR(__xludf.DUMMYFUNCTION("""COMPUTED_VALUE"""),5.0) -> 5
A34: 26 | B34: =IFERROR(__xludf.DUMMYFUNCTION("""COMPUTED_VALUE"""),104280.0) -> 104280 | C34: =IFERROR(__xludf.DUMMYFUNCTION("""COMPUTED_VALUE"""),"PO31204") -> PO31204 | D34: =IFERROR(__xludf.DUMMYFUNCTION("""COMPUTED_VALUE"""),45367.0) -> 45367 | E34: =IFERROR(__xludf.DUMMYFUNCTION("""COMPUTED_VALUE"""),4.75) -> 4.75
A35: 27 | B35: =IFERROR(__xludf.DUMMYFUNCTION("""COMPUTED_VALUE"""),104320.0) -> 104320 | C35: =IFERROR(__xludf.DUMMYFUNCTION("""COMPUTED_VALUE"""),"PO#0681") -> PO#0681 | D35: =IFERROR(__xludf.DUMMYFUNCTION("""COMPUTED_VALUE"""),45370.0) -> 45370 | E35: =IFERROR(__xludf.DUMMYFUNCTION("""COMPUTED_VALUE"""),4.3999999999999995) -> 4.4
A36: 28 | B36: =IFERROR(__xludf.DUMMYFUNCTION("""COMPUTED_VALUE"""),104299.0) -> 104299 | C36: =IFERROR(__xludf.DUMMYFUNCTION("""COMPUTED_VALUE"""),"PO31222") -> PO31222 | D36: =IFERROR(__xludf.DUMMYFUNCTION("""COMPUTED_VALUE"""),45370.0) -> 45370 | E36: =IFERROR(__xludf.DUMMYFUNCTION("""COMPUTED_VALUE"""),4.833333333333333) -> 4.8333333
A37: 29 | B37: =IFERROR(__xludf.DUMMYFUNCTION("""COMPUTED_VALUE"""),104263.0) -> 104263 | C37: =IFERROR(__xludf.DUMMYFUNCTION("""COMPUTED_VALUE"""),"PO31221") -> PO31221 | D37: =IFERROR(__xludf.DUMMYFUNCTION("""COMPUTED_VALUE"""),45370.0) -> 45370 | E37: =IFERROR(__xludf.DUMMYFUNCTION("""COMPUTED_VALUE"""),4.325) -> 4.325
A38: 30 | B38: =IFERROR(__xludf.DUMMYFUNCTION("""COMPUTED_VALUE"""),104335.0) -> 104335 | C38: =IFERROR(__xludf.DUMMYFUNCTION("""COMPUTED_VALUE"""),"PO31228") -> PO31228 | D38: =IFERROR(__xludf.DUMMYFUNCTION("""COMPUTED_VALUE"""),45370.0) -> 45370 | E38: =IFERROR(__xludf.DUMMYFUNCTION("""COMPUTED_VALUE"""),4.75) -> 4.75
A39: 31 | B39: =IFERROR(__xludf.DUMMYFUNCTION("""COMPUTED_VALUE"""),104274.0) -> 104274 | C39: =IFERROR(__xludf.DUMMYFUNCTION("""COMPUTED_VALUE"""),"PO31219") -> PO31219 | D39: =IFERROR(__xludf.DUMMYFUNCTION("""COMPUTED_VALUE"""),45373.0) -> 45373 | E39: =IFERROR(__xludf.DUMMYFUNCTION("""COMPUTED_VALUE"""),4.166666666666667) -> 4.1666667
A40: 32 | B40: =IFERROR(__xludf.DUMMYFUNCTION("""COMPUTED_VALUE"""),104266.0) -> 104266 | C40: =IFERROR(__xludf.DUMMYFUNCTION("""COMPUTED_VALUE"""),"PO31220") -> PO31220 | D40: =IFERROR(__xludf.DUMMYFUNCTION("""COMPUTED_VALUE"""),45373.0) -> 45373 | E40: =IFERROR(__xludf.DUMMYFUNCTION("""COMPUTED_VALUE"""),4.0) -> 4
A41: 33 | B41: =IFERROR(__xludf.DUMMYFUNCTION("""COMPUTED_VALUE"""),104293.0) -> 104293 | C41: =IFERROR(__xludf.DUMMYFUNCTION("""COMPUTED_VALUE"""),"PO#0680") -> PO#0680 | D41: =IFERROR(__xludf.DUMMYFUNCTION("""COMPUTED_VALUE"""),45373.0) -> 45373 | E41: =IFERROR(__xludf.DUMMYFUNCTION("""COMPUTED_VALUE"""),4.833333333333333) -> 4.8333333
A42: 34 | B42: =IFERROR(__xludf.DUMMYFUNCTION("""COMPUTED_VALUE"""),104332.0) -> 104332 | C42: =IFERROR(__xludf.DUMMYFUNCTION("""COMPUTED_VALUE"""),"PO31229") -> PO31229 | D42: =IFERROR(__xludf.DUMMYFUNCTION("""COMPUTED_VALUE"""),45373.0) -> 45373 | E42: =IFERROR(__xludf.DUMMYFUNCTION("""COMPUTED_VALUE"""),4.75) -> 4.75
A43: 35 | B43: =IFERROR(__xludf.DUMMYFUNCTION("""COMPUTED_VALUE"""),104313.0) -> 104313 | C43: =IFERROR(__xludf.DUMMYFUNCTION("""COMPUTED_VALUE"""),"PO31245") -> PO31245 | D43: =IFERROR(__xludf.DUMMYFUNCTION("""COMPUTED_VALUE"""),45374.0) -> 45374 | E43: =IFERROR(__xludf.DUMMYFUNCTION("""COMPUTED_VALUE"""),4.3999999999999995) -> 4.4
A44: 36 | B44: =IFERROR(__xludf.DUMMYFUNCTION("""COMPUTED_VALUE"""),104308.0) -> 104308 | C44: =IFERROR(__xludf.DUMMYFUNCTION("""COMPUTED_VALUE"""),"PO31244") -> PO31244 | D44: =IFERROR(__xludf.DUMMYFUNCTION("""COMPUTED_VALUE"""),45374.0) -> 45374 | E44: =IFERROR(__xludf.DUMMYFUNCTION("""COMPUTED_VALUE"""),4.5) -> 4.5
A45: 37 | B45: =IFERROR(__xludf.DUMMYFUNCTION("""COMPUTED_VALUE"""),104308.0) -> 104308 | C45: =IFERROR(__xludf.DUMMYFUNCTION("""COMPUTED_VALUE"""),"PO31243") -> PO31243 | D45: =IFERROR(__xludf.DUMMYFUNCTION("""COMPUTED_VALUE"""),45376.0) -> 45376 | E45: =IFERROR(__xludf.DUMMYFUNCTION("""COMPUTED_VALUE"""),4.833333333333333) -> 4.8333333
A46: 38 | B46: =IFERROR(__xludf.DUMMYFUNCTION("""COMPUTED_VALUE"""),104357.0) -> 104357 | C46: =IFERROR(__xludf.DUMMYFUNCTION("""COMPUTED_VALUE"""),"PO#0687") -> PO#0687 | D46: =IFERROR(__xludf.DUMMYFUNCTION("""COMPUTED_VALUE"""),45377.0) -> 45377 | E46: =IFERROR(__xludf.DUMMYFUNCTION("""COMPUTED_VALUE"""),4.475) -> 4.475
A47: 39 | B47: =IFERROR(__xludf.DUMMYFUNCTION("""COMPUTED_VALUE"""),104369.0) -> 104369 | C47: =IFERROR(__xludf.DUMMYFUNCTION("""COMPUTED_VALUE"""),"PO#0685") -> PO#0685 | D47: =IFERROR(__xludf.DUMMYFUNCTION("""COMPUTED_VALUE"""),45377.0) -> 45377 | E47: =IFERROR(__xludf.DUMMYFUNCTION("""COMPUTED_VALUE"""),4.833333333333333) -> 4.8333333
A48: 40 | B48: =IFERROR(__xludf.DUMMYFUNCTION("""COMPUTED_VALUE"""),104331.0) -> 104331 | C48: =IFERROR(__xludf.DUMMYFUNCTION("""COMPUTED_VALUE"""),"PO31242") -> PO31242 | D48: =IFERROR(__xludf.DUMMYFUNCTION("""COMPUTED_VALUE"""),45377.0) -> 45377 | E48: =IFERROR(__xludf.DUMMYFUNCTION("""COMPUTED_VALUE"""),4.75) -> 4.75
A49: 41 | B49: =IFERROR(__xludf.DUMMYFUNCTION("""COMPUTED_VALUE"""),104373.0) -> 104373 | C49: =IFERROR(__xludf.DUMMYFUNCTION("""COMPUTED_VALUE"""),"PO#0686") -> PO#0686 | D49: =IFERROR(__xludf.DUMMYFUNCTION("""COMPUTED_VALUE"""),45377.0) -> 45377 | E49: =IFERROR(__xludf.DUMMYFUNCTION("""COMPUTED_VALUE"""),4.833333333333333) -> 4.8333333
A50: 42 | B50: =IFERROR(__xludf.DUMMYFUNCTION("""COMPUTED_VALUE"""),104295.0) -> 104295 | C50: =IFERROR(__xludf.DUMMYFUNCTION("""COMPUTED_VALUE"""),"PO31207") -> PO31207 | D50: =IFERROR(__xludf.DUMMYFUNCTION("""COMPUTED_VALUE"""),45379.0) -> 45379 | E50: =IFERROR(__xludf.DUMMYFUNCTION("""COMPUTED_VALUE"""),4.833333333333333) -> 4.8333333
A51: 43 | B51: =IFERROR(__xludf.DUMMYFUNCTION("""COMPUTED_VALUE"""),104157.0) -> 104157 | D51: =IFERROR(__xludf.DUMMYFUNCTION("""COMPUTED_VALUE"""),45380.0) -> 45380 | E51: =IFERROR(__xludf.DUMMYFUNCTION("""COMPUTED_VALUE"""),5.0) -> 5
A52: 44 | B52: =IFERROR(__xludf.DUMMYFUNCTION("""COMPUTED_VALUE"""),104157.0) -> 104157 | C52: =IFERROR(__xludf.DUMMYFUNCTION("""COMPUTED_VALUE"""),"PO31214") -> PO31214 | D52: =IFERROR(__xludf.DUMMYFUNCTION("""COMPUTED_VALUE"""),45380.0) -> 45380 | E52: =IFERROR(__xludf.DUMMYFUNCTION("""COMPUTED_VALUE"""),5.0) -> 5
A53: 45 | B53: =IFERROR(__xludf.DUMMYFUNCTION("""COMPUTED_VALUE"""),104044.0) -> 104044 | C53: =IFERROR(__xludf.DUMMYFUNCTION("""COMPUTED_VALUE"""),"PO31150") -> PO31150 | D53: =IFERROR(__xludf.DUMMYFUNCTION("""COMPUTED_VALUE"""),45352.0) -> 45352 | E53: =IFERROR(__xludf.DUMMYFUNCTION("""COMPUTED_VALUE"""),5.0) -> 5
A54: 46 | B54: =IFERROR(__xludf.DUMMYFUNCTION("""COMPUTED_VALUE"""),104255.0) -> 104255 | C54: =IFERROR(__xludf.DUMMYFUNCTION("""COMPUTED_VALUE"""),"PO31216") -> PO31216 | D54: =IFERROR(__xludf.DUMMYFUNCTION("""COMPUTED_VALUE"""),45366.0) -> 45366 | E54: =IFERROR(__xludf.DUMMYFUNCTION("""COMPUTED_VALUE"""),5.0) -> 5
A55: 47 | B55: =IFERROR(__xludf.DUMMYFUNCTION("""COMPUTED_VALUE"""),104255.0) -> 104255 | C55: =IFERROR(__xludf.DUMMYFUNCTION("""COMPUTED_VALUE"""),"PO31216") -> PO31216 | D55: =IFERROR(__xludf.DUMMYFUNCTION("""COMPUTED_VALUE"""),45366.0) -> 45366 | E55: =IFERROR(__xludf.DUMMYFUNCTION("""COMPUTED_VALUE"""),5.0) -> 5
A56: 48 | B56: =IFERROR(__xludf.DUMMYFUNCTION("""COMPUTED_VALUE"""),104258.0) -> 104258 | C56: =IFERROR(__xludf.DUMMYFUNCTION("""COMPUTED_VALUE"""),"PO31206") -> PO31206 | D56: =IFERROR(__xludf.DUMMYFUNCTION("""COMPUTED_VALUE"""),45366.0) -> 45366 | E56: =IFERROR(__xludf.DUMMYFUNCTION("""COMPUTED_VALUE"""),5.0) -> 5
A57: 49
A58: 50

Sheet raw report
A3: 2024-2025 | E3: 2023-2024 | I3: 2022-2023 | M3: 2022-2023 | Q3: 2023-2024 | U3: 2024-2025 | Y3: 2022-2023 | AB3: 2023-2024 | AE3: 2024-2025
C4: Averagt Ratings | G4: Averagt Ratings | K4: Averagt Ratings | Y4: =IFERROR(__xludf.DUMMYFUNCTION("QUERY(M:N, ""select M, AVG(N) where M is not null group by M label AVG(N) 'Average Rating'"", 0)"),"") | Z4: =IFERROR(__xludf.DUMMYFUNCTION("""COMPUTED_VALUE"""),"Average Rating") -> Average Rating | AB4: =IFERROR(__xludf.DUMMYFUNCTION("QUERY(Q:R, ""select Q, AVG(R) where Q is not null group by Q label AVG(R) 'Average Rating'"", 0)"),"") | AC4: =IFERROR(__xludf.DUMMYFUNCTION("""COMPUTED_VALUE"""),"Average Rating") -> Average Rating | AE4: =IFERROR(__xludf.DUMMYFUNCTION("QUERY(U:V, ""select U, AVG(V) where U is not null group by U label AVG(V) 'Average Rating'"", 0)"),"") | AF4: =IFERROR(__xludf.DUMMYFUNCTION("""COMPUTED_VALUE"""),"Average Rating") -> Average Rating
B5: Company Name | F5: Company Name | I5: COMPANY | K5: =average(K6:K9) -> 4.7751923 | M5: =IFERROR(__xludf.DUMMYFUNCTION("FILTER( {DATABASE!E2:E1099, DATABASE!AC2:AC1099, DATABASE!D2:D1099}, (DATABASE!D2:D1099 >= DATE(2022,7,1)) * (DATABASE!D2:D1099 <= DATE(2023,6,30)) )"),"EIG Metal Engravers") -> EIG Metal Engravers | N5: =IFERROR(__xludf.DUMMYFUNCTION("""COMPUTED_VALUE"""),4.0) -> 4 | O5: =IFERROR(__xludf.DUMMYFUNCTION("""COMPUTED_VALUE"""),44746.0) -> 44746 | Q5: =IFERROR(__xludf.DUMMYFUNCTION("FILTER( {DATABASE!E2:E1099, DATABASE!AC2:AC1099, DATABASE!D2:D1099}, (DATABASE!D2:D1099 >= DATE(2023,7,1)) * (DATABASE!D2:D1099 <= DATE(2024,6,30)) )"),"Leonard Prints Inc.") -> Leonard Prints Inc. | R5: =IFERROR(__xludf.DUMMYFUNCTION("""COMPUTED_VALUE"""),4.833333333333333) -> 4.8333333 | S5: =IFERROR(__xludf.DUMMYFUNCTION("""COMPUTED_VALUE"""),45110.0) -> 45110 | U5: =IFERROR(__xludf.DUMMYFUNCTION("FILTER( {DATABASE!E2:E1099, DATABASE!AC2:AC1099, DATABASE!D2:D1099}, (DATABASE!D2:D1099 >= DATE(2024,7,1)) * (DATABASE!D2:D1099 <= DATE(2025,6,30)) )"),"Creative Juice Digital Printing") -> Creative Juice Digital Printing | V5: =IFERROR(__xludf.DUMMYFUNCTION("""COMPUTED_VALUE"""),4.833333333333333) -> 4.8333333 | W5: =IFERROR(__xludf.DUMMYFUNCTION("""COMPUTED_VALUE"""),45476.0) -> 45476 | Y5: =IFERROR(__xludf.DUMMYFUNCTION("""COMPUTED_VALUE"""),"2022-2023") -> 2022-2023 | AB5: =IFERROR(__xludf.DUMMYFUNCTION("""COMPUTED_VALUE"""),"2023-2024") -> 2023-2024 | AE5: =IFERROR(__xludf.DUMMYFUNCTION("""COMPUTED_VALUE"""),"2024-2025") -> 2024-2025
A6: Books | C6: =average(C7:C12) -> #DIV/0! | E6: Books | G6: =average(G7:G12) -> 4.83125 | I6: Advertisement Printing | M6: =IFERROR(__xludf.DUMMYFUNCTION("""COMPUTED_VALUE"""),"Atlas Superflags") -> Atlas Superflags | N6: =IFERROR(__xludf.DUMMYFUNCTION("""COMPUTED_VALUE"""),5.0) -> 5 | O6: =IFERROR(__xludf.DUMMYFUNCTION("""COMPUTED_VALUE"""),44750.0) -> 44750 | Q6: =IFERROR(__xludf.DUMMYFUNCTION("""COMPUTED_VALUE"""),"Leonard Prints Inc.") -> Leonard Prints Inc. | R6: =IFERROR(__xludf.DUMMYFUNCTION("""COMPUTED_VALUE"""),4.833333333333333) -> 4.8333333 | S6: =IFERROR(__xludf.DUMMYFUNCTION("""COMPUTED_VALUE"""),45110.0) -> 45110 | U6: =IFERROR(__xludf.DUMMYFUNCTION("""COMPUTED_VALUE"""),"Arkin Hardware") -> Arkin Hardware | V6: =IFERROR(__xludf.DUMMYFUNCTION("""COMPUTED_VALUE"""),4.625) -> 4.625 | W6: =IFERROR(__xludf.DUMMYFUNCTION("""COMPUTED_VALUE"""),45477.0) -> 45477 | Y6: =IFERROR(__xludf.DUMMYFUNCTION("""COMPUTED_VALUE"""),"Abenson Ventures, Inc.") -> Abenson Ventures, Inc. | Z6: =IFERROR(__xludf.DUMMYFUNCTION("""COMPUTED_VALUE"""),4.916666666666666) -> 4.9166667 | AB6: =IFERROR(__xludf.DUMMYFUNCTION("""COMPUTED_VALUE"""),"ADBM Lightning Equipment Trading") -> ADBM Lightning Equipment Trading | AC6: =IFERROR(__xludf.DUMMYFUNCTION("""COMPUTED_VALUE"""),5.0) -> 5 | AE6: =IFERROR(__xludf.DUMMYFUNCTION("""COMPUTED_VALUE"""),"4David's Book Trading") -> 4David's Book Trading | AF6: =IFERROR(__xludf.DUMMYFUNCTION("""COMPUTED_VALUE"""),4.803333333333333) -> 4.8033333
A7: 1 | B7: REX Book Store | E7: 1 | F7: REX Book Store | G7: 4.8333333 | I7: 1 | J7: Creative Juice Digital Printing | K7: 4.7751923 | M7: =IFERROR(__xludf.DUMMYFUNCTION("""COMPUTED_VALUE"""),"Atlas Superflags") -> Atlas Superflags | N7: =IFERROR(__xludf.DUMMYFUNCTION("""COMPUTED_VALUE"""),4.066666666666666) -> 4.0666667 | O7: =IFERROR(__xludf.DUMMYFUNCTION("""COMPUTED_VALUE"""),44750.0) -> 44750 | Q7: =IFERROR(__xludf.DUMMYFUNCTION("""COMPUTED_VALUE"""),"Net Ad IT Solutions") -> Net Ad IT Solutions | R7: =IFERROR(__xludf.DUMMYFUNCTION("""COMPUTED_VALUE"""),4.733333333333333) -> 4.7333333 | S7: =IFERROR(__xludf.DUMMYFUNCTION("""COMPUTED_VALUE"""),45127.0) -> 45127 | U7: =IFERROR(__xludf.DUMMYFUNCTION("""COMPUTED_VALUE"""),"EIG Metal Engravers") -> EIG Metal Engravers | V7: =IFERROR(__xludf.DUMMYFUNCTION("""COMPUTED_VALUE"""),5.0) -> 5 | W7: =IFERROR(__xludf.DUMMYFUNCTION("""COMPUTED_VALUE"""),45478.0) -> 45478 | Y7: =IFERROR(__xludf.DUMMYFUNCTION("""COMPUTED_VALUE"""),"Ahrcel's Gift Shop") -> Ahrcel's Gift Shop | Z7: =IFERROR(__xludf.DUMMYFUNCTION("""COMPUTED_VALUE"""),5.0) -> 5 | AB7: =IFERROR(__xludf.DUMMYFUNCTION("""COMPUTED_VALUE"""),"Abacus Book & Card Corp.") -> Abacus Book & Card Corp. | AC7: =IFERROR(__xludf.DUMMYFUNCTION("""COMPUTED_VALUE"""),4.845897435897436) -> 4.8458974 | AE7: =IFERROR(__xludf.DUMMYFUNCTION("""COMPUTED_VALUE"""),"888 Tile Phil Corp") -> 888 Tile Phil Corp | AF7: =IFERROR(__xludf.DUMMYFUNCTION("""COMPUTED_VALUE"""),4.416666666666667) -> 4.4166667
A8: 2 | B8: BELVIEW CO., INC. | E8: 2 | F8: BELVIEW CO., INC. | G8: 4.7583333 | I8: 2 | J8: Luneta Advertisement Inc. | M8: =IFERROR(__xludf.DUMMYFUNCTION("""COMPUTED_VALUE"""),"Marguerita Maria Nina I. Kanapi") -> Marguerita Maria Nina I. Kanapi | N8: =IFERROR(__xludf.DUMMYFUNCTION("""COMPUTED_VALUE"""),5.0) -> 5 | O8: =IFERROR(__xludf.DUMMYFUNCTION("""COMPUTED_VALUE"""),44756.0) -> 44756 | Q8: =IFERROR(__xludf.DUMMYFUNCTION("""COMPUTED_VALUE"""),"Forefront Book Co., Inc.") -> Forefront Book Co., Inc. | R8: =IFERROR(__xludf.DUMMYFUNCTION("""COMPUTED_VALUE"""),4.733333333333333) -> 4.7333333 | S8: =IFERROR(__xludf.DUMMYFUNCTION("""COMPUTED_VALUE"""),45128.0) -> 45128 | U8: =IFERROR(__xludf.DUMMYFUNCTION("""COMPUTED_VALUE"""),"Arkin Hardware") -> Arkin Hardware | V8: =IFERROR(__xludf.DUMMYFUNCTION("""COMPUTED_VALUE"""),4.625) -> 4.625 | W8: =IFERROR(__xludf.DUMMYFUNCTION("""COMPUTED_VALUE"""),45481.0) -> 45481 | Y8: =IFERROR(__xludf.DUMMYFUNCTION("""COMPUTED_VALUE"""),"Alpha-Cored Technology Systems, Inc.") -> Alpha-Cored Technology Systems, Inc. | Z8: =IFERROR(__xludf.DUMMYFUNCTION("""COMPUTED_VALUE"""),5.0) -> 5 | AB8: =IFERROR(__xludf.DUMMYFUNCTION("""COMPUTED_VALUE"""),"Abenson Ventures, Inc.") -> Abenson Ventures, Inc. | AC8: =IFERROR(__xludf.DUMMYFUNCTION("""COMPUTED_VALUE"""),4.608333333333333) -> 4.6083333 | AE8: =IFERROR(__xludf.DUMMYFUNCTION("""COMPUTED_VALUE"""),"Abacus Book & Card Corp.") -> Abacus Book & Card Corp. | AF8: =IFERROR(__xludf.DUMMYFUNCTION("""COMPUTED_VALUE"""),4.805555555555555) -> 4.8055556
A9: 3 | B9: CD Books International, Inc. | E9: 3 | F9: CD Books International, Inc. | I9: 3 | J9: Doo Graphic Services | M9: =IFERROR(__xludf.DUMMYFUNCTION("""COMPUTED_VALUE"""),"Hospeco Philippines, Inc.") -> Hospeco Philippines, Inc. | N9: =IFERROR(__xludf.DUMMYFUNCTION("""COMPUTED_VALUE"""),4.533333333333333) -> 4.5333333 | O9: =IFERROR(__xludf.DUMMYFUNCTION("""COMPUTED_VALUE"""),44757.0) -> 44757 | Q9: =IFERROR(__xludf.DUMMYFUNCTION("""COMPUTED_VALUE"""),"Contrade Integrated Depot") -> Contrade Integrated Depot | R9: =IFERROR(__xludf.DUMMYFUNCTION("""COMPUTED_VALUE"""),4.680000000000001) -> 4.68 | S9: =IFERROR(__xludf.DUMMYFUNCTION("""COMPUTED_VALUE"""),45131.0) -> 45131 | U9: =IFERROR(__xludf.DUMMYFUNCTION("""COMPUTED_VALUE"""),"Abiva Publishing House, Inc.") -> Abiva Publishing House, Inc. | V9: =IFERROR(__xludf.DUMMYFUNCTION("""COMPUTED_VALUE"""),4.833333333333333) -> 4.8333333 | W9: =IFERROR(__xludf.DUMMYFUNCTION("""COMPUTED_VALUE"""),45484.0) -> 45484 | Y9: =IFERROR(__xludf.DUMMYFUNCTION("""COMPUTED_VALUE"""),"Amalgamated Specialties Corporation") -> Amalgamated Specialties Corporation | Z9: =IFERROR(__xludf.DUMMYFUNCTION("""COMPUTED_VALUE"""),4.333333333333333) -> 4.3333333 | AB9: =IFERROR(__xludf.DUMMYFUNCTION("""COMPUTED_VALUE"""),"Ahrcel's Gift Shop") -> Ahrcel's Gift Shop | AC9: =IFERROR(__xludf.DUMMYFUNCTION("""COMPUTED_VALUE"""),4.836111111111111) -> 4.8361111 | AE9: =IFERROR(__xludf.DUMMYFUNCTION("""COMPUTED_VALUE"""),"Abenson Ventures, Inc.") -> Abenson Ventures, Inc. | AF9: =IFERROR(__xludf.DUMMYFUNCTION("""COMPUTED_VALUE"""),4.8973958333333325) -> 4.8973958
A10: 4 | B10: Forefront Book Co | E10: 4 | F10: Forefront Book Co | G10: 4.7333333 | I10: Audio Visual and Equipment | K10: =average(K11:K14) -> #DIV/0! | M10: =IFERROR(__xludf.DUMMYFUNCTION("""COMPUTED_VALUE"""),"Oray Copier Solutions") -> Oray Copier Solutions | N10: =IFERROR(__xludf.DUMMYFUNCTION("""COMPUTED_VALUE"""),5.0) -> 5 | O10: =IFERROR(__xludf.DUMMYFUNCTION("""COMPUTED_VALUE"""),44757.0) -> 44757 | Q10: =IFERROR(__xludf.DUMMYFUNCTION("""COMPUTED_VALUE"""),"Alpha-Cored Technology Systems, Inc.") -> Alpha-Cored Technology Systems, Inc. | R10: =IFERROR(__xludf.DUMMYFUNCTION("""COMPUTED_VALUE"""),5.0) -> 5 | S10: =IFERROR(__xludf.DUMMYFUNCTION("""COMPUTED_VALUE"""),45134.0) -> 45134 | U10: =IFERROR(__xludf.DUMMYFUNCTION("""COMPUTED_VALUE"""),"Mostaco Printing") -> Mostaco Printing | V10: =IFERROR(__xludf.DUMMYFUNCTION("""COMPUTED_VALUE"""),4.833333333333333) -> 4.8333333 | W10: =IFERROR(__xludf.DUMMYFUNCTION("""COMPUTED_VALUE"""),45492.0) -> 45492 | Y10: =IFERROR(__xludf.DUMMYFUNCTION("""COMPUTED_VALUE"""),"Amazon") -> Amazon | Z10: =IFERROR(__xludf.DUMMYFUNCTION("""COMPUTED_VALUE"""),4.708) -> 4.708 | AB10: =IFERROR(__xludf.DUMMYFUNCTION("""COMPUTED_VALUE"""),"Alpha Steel Office and Home Furnishing Company") -> Alpha Steel Office and Home Furnishing Company | AC10: =IFERROR(__xludf.DUMMYFUNCTION("""COMPUTED_VALUE"""),5.0) -> 5 | AE10: =IFERROR(__xludf.DUMMYFUNCTION("""COMPUTED_VALUE"""),"Abiva Publishing House, Inc.") -> Abiva Publishing House, Inc. | AF10: =IFERROR(__xludf.DUMMYFUNCTION("""COMPUTED_VALUE"""),4.833333333333333) -> 4.8333333
A11: 5 | B11: Phoenix Publishing House | E11: 5 | F11: Phoenix Publishing House | I11: 4 | J11: Lovell de Mesa | M11: =IFERROR(__xludf.DUMMYFUNCTION("""COMPUTED_VALUE"""),"Amazon") -> Amazon | N11: =IFERROR(__xludf.DUMMYFUNCTION("""COMPUTED_VALUE"""),4.3116666666666665) -> 4.3116667 | O11: =IFERROR(__xludf.DUMMYFUNCTION("""COMPUTED_VALUE"""),44762.0) -> 44762 | Q11: =IFERROR(__xludf.DUMMYFUNCTION("""COMPUTED_VALUE"""),"Tropical Palms Fashion House, Inc.") -> Tropical Palms Fashion House, Inc. | R11: =IFERROR(__xludf.DUMMYFUNCTION("""COMPUTED_VALUE"""),4.608333333333333) -> 4.6083333 | S11: =IFERROR(__xludf.DUMMYFUNCTION("""COMPUTED_VALUE"""),45140.0) -> 45140 | U11: =IFERROR(__xludf.DUMMYFUNCTION("""COMPUTED_VALUE"""),"CD Books International, Inc.") -> CD Books International, Inc. | V11: =IFERROR(__xludf.DUMMYFUNCTION("""COMPUTED_VALUE"""),4.833333333333333) -> 4.8333333 | W11: =IFERROR(__xludf.DUMMYFUNCTION("""COMPUTED_VALUE"""),45492.0) -> 45492 | Y11: =IFERROR(__xludf.DUMMYFUNCTION("""COMPUTED_VALUE"""),"Arkwood Plus Fine Furniture") -> Arkwood Plus Fine Furniture | Z11: =IFERROR(__xludf.DUMMYFUNCTION("""COMPUTED_VALUE"""),4.0) -> 4 | AB11: =IFERROR(__xludf.DUMMYFUNCTION("""COMPUTED_VALUE"""),"Alpha-Cored Technology Systems, Inc.") -> Alpha-Cored Technology Systems, Inc. | AC11: =IFERROR(__xludf.DUMMYFUNCTION("""COMPUTED_VALUE"""),5.0) -> 5 | AE11: =IFERROR(__xludf.DUMMYFUNCTION("""COMPUTED_VALUE"""),"Ace Hardware") -> Ace Hardware | AF11: =IFERROR(__xludf.DUMMYFUNCTION("""COMPUTED_VALUE"""),4.791666666666667) -> 4.7916667
A12: 6 | B12: Booktrends Enterprises | E12: 6 | F12: Booktrends Enterprises | G12: 5 | I12: Books | K12: =average(K13:K21) -> #DIV/0! | M12: =IFERROR(__xludf.DUMMYFUNCTION("""COMPUTED_VALUE"""),"Contrade Integrated Depot") -> Contrade Integrated Depot | N12: =IFERROR(__xludf.DUMMYFUNCTION("""COMPUTED_VALUE"""),3.9166666666666665) -> 3.9166667 | O12: =IFERROR(__xludf.DUMMYFUNCTION("""COMPUTED_VALUE"""),44763.0) -> 44763 | Q12: =IFERROR(__xludf.DUMMYFUNCTION("""COMPUTED_VALUE"""),"Awardextremes, Inc.") -> Awardextremes, Inc. | R12: =IFERROR(__xludf.DUMMYFUNCTION("""COMPUTED_VALUE"""),4.566666666666666) -> 4.5666667 | S12: =IFERROR(__xludf.DUMMYFUNCTION("""COMPUTED_VALUE"""),45141.0) -> 45141 | U12: =IFERROR(__xludf.DUMMYFUNCTION("""COMPUTED_VALUE"""),"Belview Co., Inc.") -> Belview Co., Inc. | V12: =IFERROR(__xludf.DUMMYFUNCTION("""COMPUTED_VALUE"""),4.833333333333333) -> 4.8333333 | W12: =IFERROR(__xludf.DUMMYFUNCTION("""COMPUTED_VALUE"""),45492.0) -> 45492 | Y12: =IFERROR(__xludf.DUMMYFUNCTION("""COMPUTED_VALUE"""),"Atlas Superflags") -> Atlas Superflags | Z12: =IFERROR(__xludf.DUMMYFUNCTION("""COMPUTED_VALUE"""),4.766666666666667) -> 4.7666667 | AB12: =IFERROR(__xludf.DUMMYFUNCTION("""COMPUTED_VALUE"""),"Amalgamated Specialties Corporation") -> Amalgamated Specialties Corporation | AC12: =IFERROR(__xludf.DUMMYFUNCTION("""COMPUTED_VALUE"""),5.0) -> 5 | AE12: =IFERROR(__xludf.DUMMYFUNCTION("""COMPUTED_VALUE"""),"Alpha Steel Office and Home Furnishing Company") -> Alpha Steel Office and Home Furnishing Company | AF12: =IFERROR(__xludf.DUMMYFUNCTION("""COMPUTED_VALUE"""),4.833333333333333) -> 4.8333333
A13: Cleaning Materials | C13: =average(C14:C15) -> 4.6809896 | E13: School/Office Supplies | G13: =average(G14:G21) -> 4.7778378 | I13: 5 | J13: C & E Publishing Inc | M13: =IFERROR(__xludf.DUMMYFUNCTION("""COMPUTED_VALUE"""),"Rivchem Enterprises") -> Rivchem Enterprises | N13: =IFERROR(__xludf.DUMMYFUNCTION("""COMPUTED_VALUE"""),4.833333333333333) -> 4.8333333 | O13: =IFERROR(__xludf.DUMMYFUNCTION("""COMPUTED_VALUE"""),44763.0) -> 44763 | Q13: =IFERROR(__xludf.DUMMYFUNCTION("""COMPUTED_VALUE"""),"Contrade Integrated Depot") -> Contrade Integrated Depot | R13: =IFERROR(__xludf.DUMMYFUNCTION("""COMPUTED_VALUE"""),4.566666666666666) -> 4.5666667 | S13: =IFERROR(__xludf.DUMMYFUNCTION("""COMPUTED_VALUE"""),45142.0) -> 45142 | U13: =IFERROR(__xludf.DUMMYFUNCTION("""COMPUTED_VALUE"""),"Belview Co., Inc.") -> Belview Co., Inc. | V13: =IFERROR(__xludf.DUMMYFUNCTION("""COMPUTED_VALUE"""),4.833333333333333) -> 4.8333333 | W13: =IFERROR(__xludf.DUMMYFUNCTION("""COMPUTED_VALUE"""),45492.0) -> 45492 | Y13: =IFERROR(__xludf.DUMMYFUNCTION("""COMPUTED_VALUE"""),"Awardextremes, Inc.") -> Awardextremes, Inc. | Z13: =IFERROR(__xludf.DUMMYFUNCTION("""COMPUTED_VALUE"""),4.666666666666667) -> 4.6666667 | AB13: =IFERROR(__xludf.DUMMYFUNCTION("""COMPUTED_VALUE"""),"Arkin Hardware") -> Arkin Hardware | AC13: =IFERROR(__xludf.DUMMYFUNCTION("""COMPUTED_VALUE"""),4.4714285714285715) -> 4.4714286 | AE13: =IFERROR(__xludf.DUMMYFUNCTION("""COMPUTED_VALUE"""),"Alpha-Cored Technology Systems, Inc.") -> Alpha-Cored Technology Systems, Inc. | AF13: =IFERROR(__xludf.DUMMYFUNCTION("""COMPUTED_VALUE"""),4.925925925925926) -> 4.9259259
A14: 7 | B14: Rivchem Enterprises | C14: 4.7161458 | E14: 7 | F14: Abacus Book and Card Corporation | G14: 4.8458974 | I14: 6 | J14: National Book Store, Inc | M14: =IFERROR(__xludf.DUMMYFUNCTION("""COMPUTED_VALUE"""),"Belview Co., Inc.") -> Belview Co., Inc. | N14: =IFERROR(__xludf.DUMMYFUNCTION("""COMPUTED_VALUE"""),5.0) -> 5 | O14: =IFERROR(__xludf.DUMMYFUNCTION("""COMPUTED_VALUE"""),44764.0) -> 44764 | Q14: =IFERROR(__xludf.DUMMYFUNCTION("""COMPUTED_VALUE"""),"Lordfel Marketing") -> Lordfel Marketing | R14: =IFERROR(__xludf.DUMMYFUNCTION("""COMPUTED_VALUE"""),4.0) -> 4 | S14: =IFERROR(__xludf.DUMMYFUNCTION("""COMPUTED_VALUE"""),45142.0) -> 45142 | U14: =IFERROR(__xludf.DUMMYFUNCTION("""COMPUTED_VALUE"""),"Contrade Integrated Depot") -> Contrade Integrated Depot | V14: =IFERROR(__xludf.DUMMYFUNCTION("""COMPUTED_VALUE"""),4.583333333333333) -> 4.5833333 | W14: =IFERROR(__xludf.DUMMYFUNCTION("""COMPUTED_VALUE"""),45493.0) -> 45493 | Y14: =IFERROR(__xludf.DUMMYFUNCTION("""COMPUTED_VALUE"""),"Belview Co., Inc.") -> Belview Co., Inc. | Z14: =IFERROR(__xludf.DUMMYFUNCTION("""COMPUTED_VALUE"""),5.0) -> 5 | AB14: =IFERROR(__xludf.DUMMYFUNCTION("""COMPUTED_VALUE"""),"Atlas Superflags") -> Atlas Superflags | AC14: =IFERROR(__xludf.DUMMYFUNCTION("""COMPUTED_VALUE"""),4.0) -> 4 | AE14: =IFERROR(__xludf.DUMMYFUNCTION("""COMPUTED_VALUE"""),"Arkin Hardware") -> Arkin Hardware | AF14: =IFERROR(__xludf.DUMMYFUNCTION("""COMPUTED_VALUE"""),4.867222222222223) -> 4.8672222
A15: 8 | B15: Chemtrust Global Market | C15: 4.6458333 | E15: 8 | F15: Contrade Integrated Depot, Inc, | G15: 4.6089167 | I15: 7 | J15: Rex Bookstore | M15: =IFERROR(__xludf.DUMMYFUNCTION("""COMPUTED_VALUE"""),"Belview Co., Inc.") -> Belview Co., Inc. | N15: =IFERROR(__xludf.DUMMYFUNCTION("""COMPUTED_VALUE"""),5.0) -> 5 | O15: =IFERROR(__xludf.DUMMYFUNCTION("""COMPUTED_VALUE"""),44764.0) -> 44764 | Q15: =IFERROR(__xludf.DUMMYFUNCTION("""COMPUTED_VALUE"""),"Rivchem Enterprises") -> Rivchem Enterprises | R15: =IFERROR(__xludf.DUMMYFUNCTION("""COMPUTED_VALUE"""),4.6) -> 4.6 | S15: =IFERROR(__xludf.DUMMYFUNCTION("""COMPUTED_VALUE"""),45145.0) -> 45145 | U15: =IFERROR(__xludf.DUMMYFUNCTION("""COMPUTED_VALUE"""),"Javammp Printing Services") -> Javammp Printing Services | V15: =IFERROR(__xludf.DUMMYFUNCTION("""COMPUTED_VALUE"""),3.9166666666666665) -> 3.9166667 | W15: =IFERROR(__xludf.DUMMYFUNCTION("""COMPUTED_VALUE"""),45495.0) -> 45495 | Y15: =IFERROR(__xludf.DUMMYFUNCTION("""COMPUTED_VALUE"""),"Brown Movement for Cultural Advancement, Inc.") -> Brown Movement for Cultural Advancement, Inc. | Z15: =IFERROR(__xludf.DUMMYFUNCTION("""COMPUTED_VALUE"""),5.0) -> 5 | AB15: =IFERROR(__xludf.DUMMYFUNCTION("""COMPUTED_VALUE"""),"Awardextremes, Inc.") -> Awardextremes, Inc. | AC15: =IFERROR(__xludf.DUMMYFUNCTION("""COMPUTED_VALUE"""),4.566666666666666) -> 4.5666667 | AE15: =IFERROR(__xludf.DUMMYFUNCTION("""COMPUTED_VALUE"""),"Asahl Design Centre Inc.") -> Asahl Design Centre Inc. | AF15: =IFERROR(__xludf.DUMMYFUNCTION("""COMPUTED_VALUE"""),4.858333333333333) -> 4.8583333
A16: School/Office Supplies | C16: =average(C17:C26) -> 4.7827932 | E16: 9 | F16: Times Trading Co., Inc. | G16: 4.6860417 | I16: 8 | J16: Phoenix Publishing House | M16: =IFERROR(__xludf.DUMMYFUNCTION("""COMPUTED_VALUE"""),"Amalgamated Specialties Corporation") -> Amalgamated Specialties Corporation | N16: =IFERROR(__xludf.DUMMYFUNCTION("""COMPUTED_VALUE"""),4.333333333333333) -> 4.3333333 | O16: =IFERROR(__xludf.DUMMYFUNCTION("""COMPUTED_VALUE"""),44767.0) -> 44767 | Q16: =IFERROR(__xludf.DUMMYFUNCTION("""COMPUTED_VALUE"""),"Rivchem Enterprises") -> Rivchem Enterprises | R16: =IFERROR(__xludf.DUMMYFUNCTION("""COMPUTED_VALUE"""),4.6) -> 4.6 | S16: =IFERROR(__xludf.DUMMYFUNCTION("""COMPUTED_VALUE"""),45146.0) -> 45146 | U16: =IFERROR(__xludf.DUMMYFUNCTION("""COMPUTED_VALUE"""),"BIG LEAGUE SPORTS WEAR SHOP. INC.") -> BIG LEAGUE SPORTS WEAR SHOP. INC. | V16: =IFERROR(__xludf.DUMMYFUNCTION("""COMPUTED_VALUE"""),4.0) -> 4 | W16: =IFERROR(__xludf.DUMMYFUNCTION("""COMPUTED_VALUE"""),45503.0) -> 45503 | Y16: =IFERROR(__xludf.DUMMYFUNCTION("""COMPUTED_VALUE"""),"Chemtrust Global Market, Inc.") -> Chemtrust Global Market, Inc. | Z16: =IFERROR(__xludf.DUMMYFUNCTION("""COMPUTED_VALUE"""),4.066666666666666) -> 4.0666667 | AB16: =IFERROR(__xludf.DUMMYFUNCTION("""COMPUTED_VALUE"""),"Belview Co., Inc.") -> Belview Co., Inc. | AC16: =IFERROR(__xludf.DUMMYFUNCTION("""COMPUTED_VALUE"""),4.753333333333333) -> 4.7533333 | AE16: =IFERROR(__xludf.DUMMYFUNCTION("""COMPUTED_VALUE"""),"Atlas Superflags") -> Atlas Superflags | AF16: =IFERROR(__xludf.DUMMYFUNCTION("""COMPUTED_VALUE"""),4.7444444444444445) -> 4.7444444
A17: 9 | B17: Abacus Book and Card Corporation | C17: 4.7222222 | E17: 10 | F17: Paper Tree Marketing Group, Inc. | I17: 9 | J17: F & J De Jesus, Inc | M17: =IFERROR(__xludf.DUMMYFUNCTION("""COMPUTED_VALUE"""),"Contrade Integrated Depot") -> Contrade Integrated Depot | N17: =IFERROR(__xludf.DUMMYFUNCTION("""COMPUTED_VALUE"""),3.6) -> 3.6 | O17: =IFERROR(__xludf.DUMMYFUNCTION("""COMPUTED_VALUE"""),44767.0) -> 44767 | Q17: =IFERROR(__xludf.DUMMYFUNCTION("""COMPUTED_VALUE"""),"Lordfel Marketing") -> Lordfel Marketing | R17: =IFERROR(__xludf.DUMMYFUNCTION("""COMPUTED_VALUE"""),5.0) -> 5 | S17: =IFERROR(__xludf.DUMMYFUNCTION("""COMPUTED_VALUE"""),45149.0) -> 45149 | U17: =IFERROR(__xludf.DUMMYFUNCTION("""COMPUTED_VALUE"""),"Printing Shop PrintPilipinas.com") -> Printing Shop PrintPilipinas.com | V17: =IFERROR(__xludf.DUMMYFUNCTION("""COMPUTED_VALUE"""),4.833333333333333) -> 4.8333333 | W17: =IFERROR(__xludf.DUMMYFUNCTION("""COMPUTED_VALUE"""),45505.0) -> 45505 | Y17: =IFERROR(__xludf.DUMMYFUNCTION("""COMPUTED_VALUE"""),"Columbia Technologies, Inc.") -> Columbia Technologies, Inc. | Z17: =IFERROR(__xludf.DUMMYFUNCTION("""COMPUTED_VALUE"""),4.958333333333333) -> 4.9583333 | AB17: =IFERROR(__xludf.DUMMYFUNCTION("""COMPUTED_VALUE"""),"Beyond Global Multiales Corp.") -> Beyond Global Multiales Corp. | AC17: =IFERROR(__xludf.DUMMYFUNCTION("""COMPUTED_VALUE"""),4.833333333333333) -> 4.8333333 | AE17: =IFERROR(__xludf.DUMMYFUNCTION("""COMPUTED_VALUE"""),"BIG LEAGUE SPORTS WEAR SHOP. INC.") -> BIG LEAGUE SPORTS WEAR SHOP. INC. | AF17: =IFERROR(__xludf.DUMMYFUNCTION("""COMPUTED_VALUE"""),4.0) -> 4
A18: 10 | B18: Contrade Integrated Depot, Inc, | C18: 4.7083333 | E18: 11 | F18: EA Intertrade General Merchandising, Inc. | G18: 5 | I18: 10 | J18: BOOK TRENDS ENTERPRISES | M18: =IFERROR(__xludf.DUMMYFUNCTION("""COMPUTED_VALUE"""),"Gift Republic, Inc.") -> Gift Republic, Inc. | N18: =IFERROR(__xludf.DUMMYFUNCTION("""COMPUTED_VALUE"""),2.0) -> 2 | O18: =IFERROR(__xludf.DUMMYFUNCTION("""COMPUTED_VALUE"""),44774.0) -> 44774 | Q18: =IFERROR(__xludf.DUMMYFUNCTION("""COMPUTED_VALUE"""),"Lordfel Marketing") -> Lordfel Marketing | R18: =IFERROR(__xludf.DUMMYFUNCTION("""COMPUTED_VALUE"""),4.0) -> 4 | S18: =IFERROR(__xludf.DUMMYFUNCTION("""COMPUTED_VALUE"""),45149.0) -> 45149 | U18: =IFERROR(__xludf.DUMMYFUNCTION("""COMPUTED_VALUE"""),"Mostaco Printing") -> Mostaco Printing | V18: =IFERROR(__xludf.DUMMYFUNCTION("""COMPUTED_VALUE"""),4.75) -> 4.75 | W18: =IFERROR(__xludf.DUMMYFUNCTION("""COMPUTED_VALUE"""),45509.0) -> 45509 | Y18: =IFERROR(__xludf.DUMMYFUNCTION("""COMPUTED_VALUE"""),"Contrade Integrated Depot") -> Contrade Integrated Depot | Z18: =IFERROR(__xludf.DUMMYFUNCTION("""COMPUTED_VALUE"""),4.325444444444444) -> 4.3254444 | AB18: =IFERROR(__xludf.DUMMYFUNCTION("""COMPUTED_VALUE"""),"Booktrens Enterprises") -> Booktrens Enterprises | AC18: =IFERROR(__xludf.DUMMYFUNCTION("""COMPUTED_VALUE"""),5.0) -> 5 | AE18: =IFERROR(__xludf.DUMMYFUNCTION("""COMPUTED_VALUE"""),"Barcaman Couture Corporation") -> Barcaman Couture Corporation | AF18: =IFERROR(__xludf.DUMMYFUNCTION("""COMPUTED_VALUE"""),3.5666666666666664) -> 3.5666667
A19: 11 | B19: Times Trading Co., Inc. | C19: 4.8333333 | E19: 12 | F19: One Supply | I19: 11 | J19: CD Books International, Inc | M19: =IFERROR(__xludf.DUMMYFUNCTION("""COMPUTED_VALUE"""),"Gift Republic, Inc.") -> Gift Republic, Inc. | N19: =IFERROR(__xludf.DUMMYFUNCTION("""COMPUTED_VALUE"""),2.066666666666667) -> 2.0666667 | O19: =IFERROR(__xludf.DUMMYFUNCTION("""COMPUTED_VALUE"""),44774.0) -> 44774 | Q19: =IFERROR(__xludf.DUMMYFUNCTION("""COMPUTED_VALUE"""),"Lordfel Marketing") -> Lordfel Marketing | R19: =IFERROR(__xludf.DUMMYFUNCTION("""COMPUTED_VALUE"""),4.0) -> 4 | S19: =IFERROR(__xludf.DUMMYFUNCTION("""COMPUTED_VALUE"""),45149.0) -> 45149 | U19: =IFERROR(__xludf.DUMMYFUNCTION("""COMPUTED_VALUE"""),"Contrade Integrated Depot") -> Contrade Integrated Depot | V19: =IFERROR(__xludf.DUMMYFUNCTION("""COMPUTED_VALUE"""),4.833333333333333) -> 4.8333333 | W19: =IFERROR(__xludf.DUMMYFUNCTION("""COMPUTED_VALUE"""),45510.0) -> 45510 | Y19: =IFERROR(__xludf.DUMMYFUNCTION("""COMPUTED_VALUE"""),"Creative Juice Digital Printing") -> Creative Juice Digital Printing | Z19: =IFERROR(__xludf.DUMMYFUNCTION("""COMPUTED_VALUE"""),4.775192307692308) -> 4.7751923 | AB19: =IFERROR(__xludf.DUMMYFUNCTION("""COMPUTED_VALUE"""),"Chemtrust Global Market, Inc.") -> Chemtrust Global Market, Inc. | AC19: =IFERROR(__xludf.DUMMYFUNCTION("""COMPUTED_VALUE"""),4.794444444444444) -> 4.7944444 | AE19: =IFERROR(__xludf.DUMMYFUNCTION("""COMPUTED_VALUE"""),"Belview Co., Inc.") -> Belview Co., Inc. | AF19: =IFERROR(__xludf.DUMMYFUNCTION("""COMPUTED_VALUE"""),4.986706349206351) -> 4.9867063
A20: 12 | B20: Paper Tree Marketing Group, Inc. | C20: 4.9166667 | E20: 13 | F20: Commerce Asia Inc. | G20: 4.7483333 | I20: 12 | J20: CREATIVE MIND BOOKS CENTER | M20: =IFERROR(__xludf.DUMMYFUNCTION("""COMPUTED_VALUE"""),"Awardextremes, Inc.") -> Awardextremes, Inc. | N20: =IFERROR(__xludf.DUMMYFUNCTION("""COMPUTED_VALUE"""),4.666666666666667) -> 4.6666667 | O20: =IFERROR(__xludf.DUMMYFUNCTION("""COMPUTED_VALUE"""),44778.0) -> 44778 | Q20: =IFERROR(__xludf.DUMMYFUNCTION("""COMPUTED_VALUE"""),"Lordfel Marketing") -> Lordfel Marketing | R20: =IFERROR(__xludf.DUMMYFUNCTION("""COMPUTED_VALUE"""),4.0) -> 4 | S20: =IFERROR(__xludf.DUMMYFUNCTION("""COMPUTED_VALUE"""),45149.0) -> 45149 | U20: =IFERROR(__xludf.DUMMYFUNCTION("""COMPUTED_VALUE"""),"Belview Co., Inc.") -> Belview Co., Inc. | V20: =IFERROR(__xludf.DUMMYFUNCTION("""COMPUTED_VALUE"""),4.833333333333333) -> 4.8333333 | W20: =IFERROR(__xludf.DUMMYFUNCTION("""COMPUTED_VALUE"""),45510.0) -> 45510 | Y20: =IFERROR(__xludf.DUMMYFUNCTION("""COMPUTED_VALUE"""),"DKL Laboratory Supplies") -> DKL Laboratory Supplies | Z20: =IFERROR(__xludf.DUMMYFUNCTION("""COMPUTED_VALUE"""),3.8333333333333335) -> 3.8333333 | AB20: =IFERROR(__xludf.DUMMYFUNCTION("""COMPUTED_VALUE"""),"Chronos Athletics Shop") -> Chronos Athletics Shop | AC20: =IFERROR(__xludf.DUMMYFUNCTION("""COMPUTED_VALUE"""),4.519444444444445) -> 4.5194444 | AE20: =IFERROR(__xludf.DUMMYFUNCTION("""COMPUTED_VALUE"""),"Bobman Trading") -> Bobman Trading | AF20: =IFERROR(__xludf.DUMMYFUNCTION("""COMPUTED_VALUE"""),4.89074074074074) -> 4.8907407
A21: 13 | B21: EA Intertrade General Merchandising, Inc. | E21: 14 | F21: EXPRESS CARDS ENTERPRISES, CO. | I21: 13 | J21: Forefront Book Co., Inc. | M21: =IFERROR(__xludf.DUMMYFUNCTION("""COMPUTED_VALUE"""),"Gift Republic, Inc.") -> Gift Republic, Inc. | N21: =IFERROR(__xludf.DUMMYFUNCTION("""COMPUTED_VALUE"""),4.713333333333334) -> 4.7133333 | O21: =IFERROR(__xludf.DUMMYFUNCTION("""COMPUTED_VALUE"""),44778.0) -> 44778 | Q21: =IFERROR(__xludf.DUMMYFUNCTION("""COMPUTED_VALUE"""),"Lordfel Marketing") -> Lordfel Marketing | R21: =IFERROR(__xludf.DUMMYFUNCTION("""COMPUTED_VALUE"""),4.0) -> 4 | S21: =IFERROR(__xludf.DUMMYFUNCTION("""COMPUTED_VALUE"""),45149.0) -> 45149 | U21: =IFERROR(__xludf.DUMMYFUNCTION("""COMPUTED_VALUE"""),"Abacus Book & Card Corp.") -> Abacus Book & Card Corp. | V21: =IFERROR(__xludf.DUMMYFUNCTION("""COMPUTED_VALUE"""),4.75) -> 4.75 | W21: =IFERROR(__xludf.DUMMYFUNCTION("""COMPUTED_VALUE"""),45512.0) -> 45512 | Y21: =IFERROR(__xludf.DUMMYFUNCTION("""COMPUTED_VALUE"""),"Data Computer Forms, Inc.") -> Data Computer Forms, Inc. | Z21: =IFERROR(__xludf.DUMMYFUNCTION("""COMPUTED_VALUE"""),4.966666666666667) -> 4.9666667 | AB21: =IFERROR(__xludf.DUMMYFUNCTION("""COMPUTED_VALUE"""),"Circuitrocks Electronic Store") -> Circuitrocks Electronic Store | AC21: =IFERROR(__xludf.DUMMYFUNCTION("""COMPUTED_VALUE"""),4.908333333333333) -> 4.9083333 | AE21: =IFERROR(__xludf.DUMMYFUNCTION("""COMPUTED_VALUE"""),"CD Books International, Inc.") -> CD Books International, Inc. | AF21: =IFERROR(__xludf.DUMMYFUNCTION("""COMPUTED_VALUE"""),4.866666666666666) -> 4.8666667
A22: 14 | B22: One Supply | E22: Computer/Peripherals/Software | G22: =average(G23:G27) -> 4.6472222 | I22: Computer/Peripherals/Software | K22: =average(K23:K30) -> 4.9320833 | M22: =IFERROR(__xludf.DUMMYFUNCTION("""COMPUTED_VALUE"""),"Leonard Prints Inc.") -> Leonard Prints Inc. | N22: =IFERROR(__xludf.DUMMYFUNCTION("""COMPUTED_VALUE"""),4.8) -> 4.8 | O22: =IFERROR(__xludf.DUMMYFUNCTION("""COMPUTED_VALUE"""),44789.0) -> 44789 | Q22: =IFERROR(__xludf.DUMMYFUNCTION("""COMPUTED_VALUE"""),"Contrade Integrated Depot") -> Contrade Integrated Depot | R22: =IFERROR(__xludf.DUMMYFUNCTION("""COMPUTED_VALUE"""),4.690833333333334) -> 4.6908333 | S22: =IFERROR(__xludf.DUMMYFUNCTION("""COMPUTED_VALUE"""),45152.0) -> 45152 | U22: =IFERROR(__xludf.DUMMYFUNCTION("""COMPUTED_VALUE"""),"Mostaco Printing") -> Mostaco Printing | V22: =IFERROR(__xludf.DUMMYFUNCTION("""COMPUTED_VALUE"""),4.75) -> 4.75 | W22: =IFERROR(__xludf.DUMMYFUNCTION("""COMPUTED_VALUE"""),45513.0) -> 45513 | Y22: =IFERROR(__xludf.DUMMYFUNCTION("""COMPUTED_VALUE"""),"EIG Metal Engravers") -> EIG Metal Engravers | Z22: =IFERROR(__xludf.DUMMYFUNCTION("""COMPUTED_VALUE"""),4.5) -> 4.5 | AB22: =IFERROR(__xludf.DUMMYFUNCTION("""COMPUTED_VALUE"""),"Colent Marketing Philippines, Inc.") -> Colent Marketing Philippines, Inc. | AC22: =IFERROR(__xludf.DUMMYFUNCTION("""COMPUTED_VALUE"""),5.0) -> 5 | AE22: =IFERROR(__xludf.DUMMYFUNCTION("""COMPUTED_VALUE"""),"COMPUTECHNOLOGIES CORP.") -> COMPUTECHNOLOGIES CORP. | AF22: =IFERROR(__xludf.DUMMYFUNCTION("""COMPUTED_VALUE"""),4.858333333333333) -> 4.8583333
A23: 15 | B23: Commerce Asia Inc. | C23: 4.8125 | E23: 15 | F23: NetAd IT Solutions | G23: 4.7472222 | I23: 14 | J23: Commerce Asia Inc | M23: =IFERROR(__xludf.DUMMYFUNCTION("""COMPUTED_VALUE"""),"Contrade Integrated Depot") -> Contrade Integrated Depot | N23: =IFERROR(__xludf.DUMMYFUNCTION("""COMPUTED_VALUE"""),4.0) -> 4 | O23: =IFERROR(__xludf.DUMMYFUNCTION("""COMPUTED_VALUE"""),44791.0) -> 44791 | Q23: =IFERROR(__xludf.DUMMYFUNCTION("""COMPUTED_VALUE"""),"Polaris Prime Air Tech Corporation") -> Polaris Prime Air Tech Corporation | R23: =IFERROR(__xludf.DUMMYFUNCTION("""COMPUTED_VALUE"""),4.0) -> 4 | S23: =IFERROR(__xludf.DUMMYFUNCTION("""COMPUTED_VALUE"""),45152.0) -> 45152 | U23: =IFERROR(__xludf.DUMMYFUNCTION("""COMPUTED_VALUE"""),"Print Depot Inc.") -> Print Depot Inc. | V23: =IFERROR(__xludf.DUMMYFUNCTION("""COMPUTED_VALUE"""),4.833333333333333) -> 4.8333333 | W23: =IFERROR(__xludf.DUMMYFUNCTION("""COMPUTED_VALUE"""),45514.0) -> 45514 | Y23: =IFERROR(__xludf.DUMMYFUNCTION("""COMPUTED_VALUE"""),"Ergo Contracts Phil., Inc.") -> Ergo Contracts Phil., Inc. | Z23: =IFERROR(__xludf.DUMMYFUNCTION("""COMPUTED_VALUE"""),4.766666666666667) -> 4.7666667 | AB23: =IFERROR(__xludf.DUMMYFUNCTION("""COMPUTED_VALUE"""),"Columbia Technologies, Inc.") -> Columbia Technologies, Inc. | AC23: =IFERROR(__xludf.DUMMYFUNCTION("""COMPUTED_VALUE"""),4.0) -> 4 | AE23: =IFERROR(__xludf.DUMMYFUNCTION("""COMPUTED_VALUE"""),"Chemtrust Global Market, Inc.") -> Chemtrust Global Market, Inc. | AF23: =IFERROR(__xludf.DUMMYFUNCTION("""COMPUTED_VALUE"""),4.775277777777777) -> 4.7752778
A24: 16 | B24: EXPRESS CARDS ENTERPRISES, CO. | E24: 16 | F24: Alpha-Cored Technology Systems, Inc. | G24: 5 | I24: 15 | J24: IEquity Technologies Corporation | M24: =IFERROR(__xludf.DUMMYFUNCTION("""COMPUTED_VALUE"""),"Amazon") -> Amazon | N24: =IFERROR(__xludf.DUMMYFUNCTION("""COMPUTED_VALUE"""),4.2283333333333335) -> 4.2283333 | O24: =IFERROR(__xludf.DUMMYFUNCTION("""COMPUTED_VALUE"""),44793.0) -> 44793 | Q24: =IFERROR(__xludf.DUMMYFUNCTION("""COMPUTED_VALUE"""),"Abacus Book & Card Corp.") -> Abacus Book & Card Corp. | R24: =IFERROR(__xludf.DUMMYFUNCTION("""COMPUTED_VALUE"""),4.666666666666667) -> 4.6666667 | S24: =IFERROR(__xludf.DUMMYFUNCTION("""COMPUTED_VALUE"""),45153.0) -> 45153 | U24: =IFERROR(__xludf.DUMMYFUNCTION("""COMPUTED_VALUE"""),"Crosspoint Paper, Inc.") -> Crosspoint Paper, Inc. | V24: =IFERROR(__xludf.DUMMYFUNCTION("""COMPUTED_VALUE"""),4.833333333333333) -> 4.8333333 | W24: =IFERROR(__xludf.DUMMYFUNCTION("""COMPUTED_VALUE"""),45514.0) -> 45514 | Y24: =IFERROR(__xludf.DUMMYFUNCTION("""COMPUTED_VALUE"""),"Falcon Waterfree Philippines, Inc.") -> Falcon Waterfree Philippines, Inc. | Z24: =IFERROR(__xludf.DUMMYFUNCTION("""COMPUTED_VALUE"""),5.0) -> 5 | AB24: =IFERROR(__xludf.DUMMYFUNCTION("""COMPUTED_VALUE"""),"Commerce Asia, Inc.") -> Commerce Asia, Inc. | AC24: =IFERROR(__xludf.DUMMYFUNCTION("""COMPUTED_VALUE"""),4.748333333333333) -> 4.7483333 | AE24: =IFERROR(__xludf.DUMMYFUNCTION("""COMPUTED_VALUE"""),"Colent Marketing Philippines, Inc.") -> Colent Marketing Philippines, Inc. | AF24: =IFERROR(__xludf.DUMMYFUNCTION("""COMPUTED_VALUE"""),4.5) -> 4.5
A25: 17 | B25: Amalgamated Specialties Corp | E25: 8 | F25: Microsmith Technology Systems, Inc. | G25: 4.8416667 | I25: 16 | J25: Columbia Technologies ,Inc | K25: 4.9583333 | M25: =IFERROR(__xludf.DUMMYFUNCTION("""COMPUTED_VALUE"""),"Rivchem Enterprises") -> Rivchem Enterprises | N25: =IFERROR(__xludf.DUMMYFUNCTION("""COMPUTED_VALUE"""),4.766666666666667) -> 4.7666667 | O25: =IFERROR(__xludf.DUMMYFUNCTION("""COMPUTED_VALUE"""),44798.0) -> 44798 | Q25: =IFERROR(__xludf.DUMMYFUNCTION("""COMPUTED_VALUE"""),"Net Ad IT Solutions") -> Net Ad IT Solutions | R25: =IFERROR(__xludf.DUMMYFUNCTION("""COMPUTED_VALUE"""),4.875) -> 4.875 | S25: =IFERROR(__xludf.DUMMYFUNCTION("""COMPUTED_VALUE"""),45157.0) -> 45157 | U25: =IFERROR(__xludf.DUMMYFUNCTION("""COMPUTED_VALUE"""),"Mostaco Printing") -> Mostaco Printing | V25: =IFERROR(__xludf.DUMMYFUNCTION("""COMPUTED_VALUE"""),4.75) -> 4.75 | W25: =IFERROR(__xludf.DUMMYFUNCTION("""COMPUTED_VALUE"""),45516.0) -> 45516 | Y25: =IFERROR(__xludf.DUMMYFUNCTION("""COMPUTED_VALUE"""),"Gift Republic, Inc.") -> Gift Republic, Inc. | Z25: =IFERROR(__xludf.DUMMYFUNCTION("""COMPUTED_VALUE"""),2.926666666666667) -> 2.9266667 | AB25: =IFERROR(__xludf.DUMMYFUNCTION("""COMPUTED_VALUE"""),"Contrade Integrated Depot") -> Contrade Integrated Depot | AC25: =IFERROR(__xludf.DUMMYFUNCTION("""COMPUTED_VALUE"""),4.6089166666666666) -> 4.6089167 | AE25: =IFERROR(__xludf.DUMMYFUNCTION("""COMPUTED_VALUE"""),"Columbia Technologies, Inc.") -> Columbia Technologies, Inc. | AF25: =IFERROR(__xludf.DUMMYFUNCTION("""COMPUTED_VALUE"""),4.941666666666666) -> 4.9416667
A26: 18 | B26: MOSTACO | C26: 4.7037037 | E26: 18 | F26: Columbia Technologies, Inc. | G26: 4 | I26: 17 | J26: Microsmith Technologies | K26: 4.9416667 | M26: =IFERROR(__xludf.DUMMYFUNCTION("""COMPUTED_VALUE"""),"Contrade Integrated Depot") -> Contrade Integrated Depot | N26: =IFERROR(__xludf.DUMMYFUNCTION("""COMPUTED_VALUE"""),3.8166666666666664) -> 3.8166667 | O26: =IFERROR(__xludf.DUMMYFUNCTION("""COMPUTED_VALUE"""),44799.0) -> 44799 | Q26: =IFERROR(__xludf.DUMMYFUNCTION("""COMPUTED_VALUE"""),"Microsmith Technology System,Inc.") -> Microsmith Technology System,Inc. | R26: =IFERROR(__xludf.DUMMYFUNCTION("""COMPUTED_VALUE"""),4.833333333333333) -> 4.8333333 | S26: =IFERROR(__xludf.DUMMYFUNCTION("""COMPUTED_VALUE"""),45163.0) -> 45163 | U26: =IFERROR(__xludf.DUMMYFUNCTION("""COMPUTED_VALUE"""),"Abacus Book & Card Corp.") -> Abacus Book & Card Corp. | V26: =IFERROR(__xludf.DUMMYFUNCTION("""COMPUTED_VALUE"""),4.75) -> 4.75 | W26: =IFERROR(__xludf.DUMMYFUNCTION("""COMPUTED_VALUE"""),45516.0) -> 45516 | Y26: =IFERROR(__xludf.DUMMYFUNCTION("""COMPUTED_VALUE"""),"Hospeco Philippines, Inc.") -> Hospeco Philippines, Inc. | Z26: =IFERROR(__xludf.DUMMYFUNCTION("""COMPUTED_VALUE"""),4.683333333333334) -> 4.6833333 | AB26: =IFERROR(__xludf.DUMMYFUNCTION("""COMPUTED_VALUE"""),"Creative Juice Digital Printing") -> Creative Juice Digital Printing | AC26: =IFERROR(__xludf.DUMMYFUNCTION("""COMPUTED_VALUE"""),4.629938271604938) -> 4.6299383 | AE26: =IFERROR(__xludf.DUMMYFUNCTION("""COMPUTED_VALUE"""),"Commerce Asia, Inc.") -> Commerce Asia, Inc. | AF26: =IFERROR(__xludf.DUMMYFUNCTION("""COMPUTED_VALUE"""),4.8125) -> 4.8125
A27: Computer/Peripherals/Software | C27: =average(C28:C32) -> 4.8585438 | E27: 19 | F27: iEquity Technologies Corporation | I27: 18 | J27: EXPRESS CARDS ENTERPRISES, CO. | M27: =IFERROR(__xludf.DUMMYFUNCTION("""COMPUTED_VALUE"""),"Atlas Superflags") -> Atlas Superflags | N27: =IFERROR(__xludf.DUMMYFUNCTION("""COMPUTED_VALUE"""),5.0) -> 5 | O27: =IFERROR(__xludf.DUMMYFUNCTION("""COMPUTED_VALUE"""),44800.0) -> 44800 | Q27: =IFERROR(__xludf.DUMMYFUNCTION("""COMPUTED_VALUE"""),"Atlas Superflags") -> Atlas Superflags | R27: =IFERROR(__xludf.DUMMYFUNCTION("""COMPUTED_VALUE"""),4.0) -> 4 | S27: =IFERROR(__xludf.DUMMYFUNCTION("""COMPUTED_VALUE"""),45165.0) -> 45165 | U27: =IFERROR(__xludf.DUMMYFUNCTION("""COMPUTED_VALUE"""),"Mostaco Printing") -> Mostaco Printing | V27: =IFERROR(__xludf.DUMMYFUNCTION("""COMPUTED_VALUE"""),4.75) -> 4.75 | W27: =IFERROR(__xludf.DUMMYFUNCTION("""COMPUTED_VALUE"""),45516.0) -> 45516 | Y27: =IFERROR(__xludf.DUMMYFUNCTION("""COMPUTED_VALUE"""),"Hytec Power, Inc.") -> Hytec Power, Inc. | Z27: =IFERROR(__xludf.DUMMYFUNCTION("""COMPUTED_VALUE"""),3.466666666666667) -> 3.4666667 | AB27: =IFERROR(__xludf.DUMMYFUNCTION("""COMPUTED_VALUE"""),"Crosspoint Paper, Inc.") -> Crosspoint Paper, Inc. | AC27: =IFERROR(__xludf.DUMMYFUNCTION("""COMPUTED_VALUE"""),5.0) -> 5 | AE27: =IFERROR(__xludf.DUMMYFUNCTION("""COMPUTED_VALUE"""),"Contrade Integrated Depot") -> Contrade Integrated Depot | AF27: =IFERROR(__xludf.DUMMYFUNCTION("""COMPUTED_VALUE"""),4.743253968253969) -> 4.743254
A28: 19 | B28: NetAd IT Solutions | C28: 4.8263889 | E28: Printing and Publication | G28: =average(G29:G40) -> 4.8047068 | I28: 19 | J28: Sert Technology Inc. | K28: 5 | M28: =IFERROR(__xludf.DUMMYFUNCTION("""COMPUTED_VALUE"""),"Leonard Prints Inc.") -> Leonard Prints Inc. | N28: =IFERROR(__xludf.DUMMYFUNCTION("""COMPUTED_VALUE"""),4.833333333333333) -> 4.8333333 | O28: =IFERROR(__xludf.DUMMYFUNCTION("""COMPUTED_VALUE"""),44803.0) -> 44803 | Q28: =IFERROR(__xludf.DUMMYFUNCTION("""COMPUTED_VALUE"""),"Microsmith Technology System,Inc.") -> Microsmith Technology System,Inc. | R28: =IFERROR(__xludf.DUMMYFUNCTION("""COMPUTED_VALUE"""),5.0) -> 5 | S28: =IFERROR(__xludf.DUMMYFUNCTION("""COMPUTED_VALUE"""),45166.0) -> 45166 | U28: =IFERROR(__xludf.DUMMYFUNCTION("""COMPUTED_VALUE"""),"EIG Metal Engravers") -> EIG Metal Engravers | V28: =IFERROR(__xludf.DUMMYFUNCTION("""COMPUTED_VALUE"""),4.833333333333333) -> 4.8333333 | W28: =IFERROR(__xludf.DUMMYFUNCTION("""COMPUTED_VALUE"""),45517.0) -> 45517 | Y28: =IFERROR(__xludf.DUMMYFUNCTION("""COMPUTED_VALUE"""),"JC Campit And Michael Berza") -> JC Campit And Michael Berza | Z28: =IFERROR(__xludf.DUMMYFUNCTION("""COMPUTED_VALUE"""),5.0) -> 5 | AB28: =IFERROR(__xludf.DUMMYFUNCTION("""COMPUTED_VALUE"""),"DKL Laboratory Supplies") -> DKL Laboratory Supplies | AC28: =IFERROR(__xludf.DUMMYFUNCTION("""COMPUTED_VALUE"""),3.6666666666666665) -> 3.6666667 | AE28: =IFERROR(__xludf.DUMMYFUNCTION("""COMPUTED_VALUE"""),"Creative Juice Digital Printing") -> Creative Juice Digital Printing | AF28: =IFERROR(__xludf.DUMMYFUNCTION("""COMPUTED_VALUE"""),4.831249999999999) -> 4.83125
A29: 20 | B29: Alpha-Cored Technology Systems, Inc. | C29: 4.9166667 | E29: 20 | F29: Creative Juice Digital Printing | G29: 4.6299383 | I29: 20 | J29: NetAd IT Solutions | K29: 4.7604167 | M29: =IFERROR(__xludf.DUMMYFUNCTION("""COMPUTED_VALUE"""),"Microsmith Technology System,Inc.") -> Microsmith Technology System,Inc. | N29: =IFERROR(__xludf.DUMMYFUNCTION("""COMPUTED_VALUE"""),5.0) -> 5 | O29: =IFERROR(__xludf.DUMMYFUNCTION("""COMPUTED_VALUE"""),44805.0) -> 44805 | Q29: =IFERROR(__xludf.DUMMYFUNCTION("""COMPUTED_VALUE"""),"Net Ad IT Solutions") -> Net Ad IT Solutions | R29: =IFERROR(__xludf.DUMMYFUNCTION("""COMPUTED_VALUE"""),5.0) -> 5 | S29: =IFERROR(__xludf.DUMMYFUNCTION("""COMPUTED_VALUE"""),45181.0) -> 45181 | U29: =IFERROR(__xludf.DUMMYFUNCTION("""COMPUTED_VALUE"""),"Commerce Asia, Inc.") -> Commerce Asia, Inc. | V29: =IFERROR(__xludf.DUMMYFUNCTION("""COMPUTED_VALUE"""),4.791666666666667) -> 4.7916667 | W29: =IFERROR(__xludf.DUMMYFUNCTION("""COMPUTED_VALUE"""),45517.0) -> 45517 | Y29: =IFERROR(__xludf.DUMMYFUNCTION("""COMPUTED_VALUE"""),"Jarm Printing Press") -> Jarm Printing Press | Z29: =IFERROR(__xludf.DUMMYFUNCTION("""COMPUTED_VALUE"""),4.75) -> 4.75 | AB29: =IFERROR(__xludf.DUMMYFUNCTION("""COMPUTED_VALUE"""),"DOOPLO ADVERTISING") -> DOOPLO ADVERTISING | AC29: =IFERROR(__xludf.DUMMYFUNCTION("""COMPUTED_VALUE"""),4.375) -> 4.375 | AE29: =IFERROR(__xludf.DUMMYFUNCTION("""COMPUTED_VALUE"""),"Crosspoint Paper, Inc.") -> Crosspoint Paper, Inc. | AF29: =IFERROR(__xludf.DUMMYFUNCTION("""COMPUTED_VALUE"""),4.944444444444444) -> 4.9444444
A30: 21 | B30: Microsmith Technology Systems, Inc. | C30: 4.8325758 | E30: 21 | F30: Velprint Corporation | I30: 21 | J30: Alpha-Cored Technology Systems Inc. | K30: 5 | M30: =IFERROR(__xludf.DUMMYFUNCTION("""COMPUTED_VALUE"""),"Amazon") -> Amazon | N30: =IFERROR(__xludf.DUMMYFUNCTION("""COMPUTED_VALUE"""),5.0) -> 5 | O30: =IFERROR(__xludf.DUMMYFUNCTION("""COMPUTED_VALUE"""),44810.0) -> 44810 | Q30: =IFERROR(__xludf.DUMMYFUNCTION("""COMPUTED_VALUE"""),"Net Ad IT Solutions") -> Net Ad IT Solutions | R30: =IFERROR(__xludf.DUMMYFUNCTION("""COMPUTED_VALUE"""),4.875) -> 4.875 | S30: =IFERROR(__xludf.DUMMYFUNCTION("""COMPUTED_VALUE"""),45181.0) -> 45181 | U30: =IFERROR(__xludf.DUMMYFUNCTION("""COMPUTED_VALUE"""),"Shelves and Cups Book Store") -> Shelves and Cups Book Store | V30: =IFERROR(__xludf.DUMMYFUNCTION("""COMPUTED_VALUE"""),4.833333333333333) -> 4.8333333 | W30: =IFERROR(__xludf.DUMMYFUNCTION("""COMPUTED_VALUE"""),45517.0) -> 45517 | Y30: =IFERROR(__xludf.DUMMYFUNCTION("""COMPUTED_VALUE"""),"Leonard Prints Inc.") -> Leonard Prints Inc. | Z30: =IFERROR(__xludf.DUMMYFUNCTION("""COMPUTED_VALUE"""),4.816666666666666) -> 4.8166667 | AB30: =IFERROR(__xludf.DUMMYFUNCTION("""COMPUTED_VALUE"""),"Data Computer Forms, Inc.") -> Data Computer Forms, Inc. | AC30: =IFERROR(__xludf.DUMMYFUNCTION("""COMPUTED_VALUE"""),4.25) -> 4.25 | AE30: =IFERROR(__xludf.DUMMYFUNCTION("""COMPUTED_VALUE"""),"Data Computer Forms, Inc.") -> Data Computer Forms, Inc. | AF30: =IFERROR(__xludf.DUMMYFUNCTION("""COMPUTED_VALUE"""),4.952777777777778) -> 4.9527778
A31: 22 | B31: Columbia Technologies, Inc. | E31: 22 | F31: Luminaire Printing and Publication Corp. | G31: 4.8666667 | I31: Cleaning Supplies & Equipment | K31: =average(K32:K39) -> 4.616369 | M31: =IFERROR(__xludf.DUMMYFUNCTION("""COMPUTED_VALUE"""),"PNB Credit Card") -> PNB Credit Card | N31: =IFERROR(__xludf.DUMMYFUNCTION("""COMPUTED_VALUE"""),3.9166666666666665) -> 3.9166667 | O31: =IFERROR(__xludf.DUMMYFUNCTION("""COMPUTED_VALUE"""),44810.0) -> 44810 | Q31: =IFERROR(__xludf.DUMMYFUNCTION("""COMPUTED_VALUE"""),"Abacus Book & Card Corp.") -> Abacus Book & Card Corp. | R31: =IFERROR(__xludf.DUMMYFUNCTION("""COMPUTED_VALUE"""),4.833333333333333) -> 4.8333333 | S31: =IFERROR(__xludf.DUMMYFUNCTION("""COMPUTED_VALUE"""),45181.0) -> 45181 | U31: =IFERROR(__xludf.DUMMYFUNCTION("""COMPUTED_VALUE"""),"Contrade Integrated Depot") -> Contrade Integrated Depot | V31: =IFERROR(__xludf.DUMMYFUNCTION("""COMPUTED_VALUE"""),4.666666666666667) -> 4.6666667 | W31: =IFERROR(__xludf.DUMMYFUNCTION("""COMPUTED_VALUE"""),45521.0) -> 45521 | Y31: =IFERROR(__xludf.DUMMYFUNCTION("""COMPUTED_VALUE"""),"Lordfel Marketing") -> Lordfel Marketing | Z31: =IFERROR(__xludf.DUMMYFUNCTION("""COMPUTED_VALUE"""),5.0) -> 5 | AB31: =IFERROR(__xludf.DUMMYFUNCTION("""COMPUTED_VALUE"""),"Dynamics Electrical Supply and Hardware") -> Dynamics Electrical Supply and Hardware | AC31: =IFERROR(__xludf.DUMMYFUNCTION("""COMPUTED_VALUE"""),4.0) -> 4 | AE31: =IFERROR(__xludf.DUMMYFUNCTION("""COMPUTED_VALUE"""),"Dynamics Electrical Supply and Hardware") -> Dynamics Electrical Supply and Hardware | AF31: =IFERROR(__xludf.DUMMYFUNCTION("""COMPUTED_VALUE"""),4.333333333333333) -> 4.3333333
A32: 23 | B32: iEquity Technologies Corporation | E32: 23 | F32: JARM Printing Press | G32: 4.875 | I32: 22 | J32: Belvedere Cleanvironment Phils., Inc. | M32: =IFERROR(__xludf.DUMMYFUNCTION("""COMPUTED_VALUE"""),"Abenson Ventures, Inc.") -> Abenson Ventures, Inc. | N32: =IFERROR(__xludf.DUMMYFUNCTION("""COMPUTED_VALUE"""),4.833333333333333) -> 4.8333333 | O32: =IFERROR(__xludf.DUMMYFUNCTION("""COMPUTED_VALUE"""),44812.0) -> 44812 | Q32: =IFERROR(__xludf.DUMMYFUNCTION("""COMPUTED_VALUE"""),"Chemtrust Global Market, Inc.") -> Chemtrust Global Market, Inc. | R32: =IFERROR(__xludf.DUMMYFUNCTION("""COMPUTED_VALUE"""),5.0) -> 5 | S32: =IFERROR(__xludf.DUMMYFUNCTION("""COMPUTED_VALUE"""),45182.0) -> 45182 | U32: =IFERROR(__xludf.DUMMYFUNCTION("""COMPUTED_VALUE"""),"Printing Shop PrintPilipinas.com") -> Printing Shop PrintPilipinas.com | V32: =IFERROR(__xludf.DUMMYFUNCTION("""COMPUTED_VALUE"""),4.833333333333333) -> 4.8333333 | W32: =IFERROR(__xludf.DUMMYFUNCTION("""COMPUTED_VALUE"""),45523.0) -> 45523 | Y32: =IFERROR(__xludf.DUMMYFUNCTION("""COMPUTED_VALUE"""),"Luminaire Printing And Publishing Corp.") -> Luminaire Printing And Publishing Corp. | Z32: =IFERROR(__xludf.DUMMYFUNCTION("""COMPUTED_VALUE"""),4.785714285714286) -> 4.7857143 | AB32: =IFERROR(__xludf.DUMMYFUNCTION("""COMPUTED_VALUE"""),"EA Intertrade General Merchandising, Inc.") -> EA Intertrade General Merchandising, Inc. | AC32: =IFERROR(__xludf.DUMMYFUNCTION("""COMPUTED_VALUE"""),5.0) -> 5 | AE32: =IFERROR(__xludf.DUMMYFUNCTION("""COMPUTED_VALUE"""),"ECOSHIFT CORPORATION") -> ECOSHIFT CORPORATION | AF32: =IFERROR(__xludf.DUMMYFUNCTION("""COMPUTED_VALUE"""),4.966666666666667) -> 4.9666667
A33: Printing and Publication | C33: =average(C34:C44) -> 4.6960648 | E33: 24 | F33: Sprintec Printing Press, Inc. | I33: 23 | J33: Goldlink Industrial Sales | M33: =IFERROR(__xludf.DUMMYFUNCTION("""COMPUTED_VALUE"""),"Contrade Integrated Depot") -> Contrade Integrated Depot | N33: =IFERROR(__xludf.DUMMYFUNCTION("""COMPUTED_VALUE"""),4.833333333333333) -> 4.8333333 | O33: =IFERROR(__xludf.DUMMYFUNCTION("""COMPUTED_VALUE"""),44813.0) -> 44813 | Q33: =IFERROR(__xludf.DUMMYFUNCTION("""COMPUTED_VALUE"""),"Chemtrust Global Market, Inc.") -> Chemtrust Global Market, Inc. | R33: =IFERROR(__xludf.DUMMYFUNCTION("""COMPUTED_VALUE"""),5.0) -> 5 | S33: =IFERROR(__xludf.DUMMYFUNCTION("""COMPUTED_VALUE"""),45184.0) -> 45184 | U33: =IFERROR(__xludf.DUMMYFUNCTION("""COMPUTED_VALUE"""),"Leonard Prints Inc.") -> Leonard Prints Inc. | V33: =IFERROR(__xludf.DUMMYFUNCTION("""COMPUTED_VALUE"""),4.791666666666667) -> 4.7916667 | W33: =IFERROR(__xludf.DUMMYFUNCTION("""COMPUTED_VALUE"""),45523.0) -> 45523 | Y33: =IFERROR(__xludf.DUMMYFUNCTION("""COMPUTED_VALUE"""),"Marguerita Maria Nina I. Kanapi") -> Marguerita Maria Nina I. Kanapi | Z33: =IFERROR(__xludf.DUMMYFUNCTION("""COMPUTED_VALUE"""),5.0) -> 5 | AB33: =IFERROR(__xludf.DUMMYFUNCTION("""COMPUTED_VALUE"""),"EESM Bookstore") -> EESM Bookstore | AC33: =IFERROR(__xludf.DUMMYFUNCTION("""COMPUTED_VALUE"""),4.808333333333333) -> 4.8083333 | AE33: =IFERROR(__xludf.DUMMYFUNCTION("""COMPUTED_VALUE"""),"EIG Metal Engravers") -> EIG Metal Engravers | AF33: =IFERROR(__xludf.DUMMYFUNCTION("""COMPUTED_VALUE"""),4.944444444444444) -> 4.9444444
A34: 24 | B34: Creative Juice Digital Printing | E34: 25 | F34: Leonard Prints, Inc. | G34: 4.8472222 | I34: 24 | J34: Palces Manufacturing, Inc. | M34: =IFERROR(__xludf.DUMMYFUNCTION("""COMPUTED_VALUE"""),"Contrade Integrated Depot") -> Contrade Integrated Depot | N34: =IFERROR(__xludf.DUMMYFUNCTION("""COMPUTED_VALUE"""),4.533333333333333) -> 4.5333333 | O34: =IFERROR(__xludf.DUMMYFUNCTION("""COMPUTED_VALUE"""),44816.0) -> 44816 | Q34: =IFERROR(__xludf.DUMMYFUNCTION("""COMPUTED_VALUE"""),"Rivchem Enterprises") -> Rivchem Enterprises | R34: =IFERROR(__xludf.DUMMYFUNCTION("""COMPUTED_VALUE"""),2.7416666666666667) -> 2.7416667 | S34: =IFERROR(__xludf.DUMMYFUNCTION("""COMPUTED_VALUE"""),45185.0) -> 45185 | U34: =IFERROR(__xludf.DUMMYFUNCTION("""COMPUTED_VALUE"""),"Printing Shop PrintPilipinas.com") -> Printing Shop PrintPilipinas.com | V34: =IFERROR(__xludf.DUMMYFUNCTION("""COMPUTED_VALUE"""),4.816666666666666) -> 4.8166667 | W34: =IFERROR(__xludf.DUMMYFUNCTION("""COMPUTED_VALUE"""),45523.0) -> 45523 | Y34: =IFERROR(__xludf.DUMMYFUNCTION("""COMPUTED_VALUE"""),"Microsmith Technology System,Inc.") -> Microsmith Technology System,Inc. | Z34: =IFERROR(__xludf.DUMMYFUNCTION("""COMPUTED_VALUE"""),4.941666666666666) -> 4.9416667 | AB34: =IFERROR(__xludf.DUMMYFUNCTION("""COMPUTED_VALUE"""),"EIG Metal Engravers") -> EIG Metal Engravers | AC34: =IFERROR(__xludf.DUMMYFUNCTION("""COMPUTED_VALUE"""),4.75) -> 4.75 | AE34: =IFERROR(__xludf.DUMMYFUNCTION("""COMPUTED_VALUE"""),"Elle Tech and Trend Office Furniture and Interiors") -> Elle Tech and Trend Office Furniture and Interiors | AF34: =IFERROR(__xludf.DUMMYFUNCTION("""COMPUTED_VALUE"""),4.7) -> 4.7
A35: 25 | B35: Velprint Corporation | E35: 26 | F35: Sales Trojan Manufacturing MFG. Corp | I35: 25 | J35: Rivchem Enterprises | K35: 4.7154762 | M35: =IFERROR(__xludf.DUMMYFUNCTION("""COMPUTED_VALUE"""),"Contrade Integrated Depot") -> Contrade Integrated Depot | N35: =IFERROR(__xludf.DUMMYFUNCTION("""COMPUTED_VALUE"""),4.675) -> 4.675 | O35: =IFERROR(__xludf.DUMMYFUNCTION("""COMPUTED_VALUE"""),44816.0) -> 44816 | Q35: =IFERROR(__xludf.DUMMYFUNCTION("""COMPUTED_VALUE"""),"Rivchem Enterprises") -> Rivchem Enterprises | R35: =IFERROR(__xludf.DUMMYFUNCTION("""COMPUTED_VALUE"""),2.891666666666667) -> 2.8916667 | S35: =IFERROR(__xludf.DUMMYFUNCTION("""COMPUTED_VALUE"""),45185.0) -> 45185 | U35: =IFERROR(__xludf.DUMMYFUNCTION("""COMPUTED_VALUE"""),"Abiva Publishing House, Inc.") -> Abiva Publishing House, Inc. | V35: =IFERROR(__xludf.DUMMYFUNCTION("""COMPUTED_VALUE"""),4.833333333333333) -> 4.8333333 | W35: =IFERROR(__xludf.DUMMYFUNCTION("""COMPUTED_VALUE"""),45524.0) -> 45524 | Y35: =IFERROR(__xludf.DUMMYFUNCTION("""COMPUTED_VALUE"""),"Net Ad IT Solutions") -> Net Ad IT Solutions | Z35: =IFERROR(__xludf.DUMMYFUNCTION("""COMPUTED_VALUE"""),4.760416666666666) -> 4.7604167 | AB35: =IFERROR(__xludf.DUMMYFUNCTION("""COMPUTED_VALUE"""),"Falcon Waterfree Philippines, Inc.") -> Falcon Waterfree Philippines, Inc. | AC35: =IFERROR(__xludf.DUMMYFUNCTION("""COMPUTED_VALUE"""),4.541666666666666) -> 4.5416667 | AE35: =IFERROR(__xludf.DUMMYFUNCTION("""COMPUTED_VALUE"""),"Express Cards Enterprises Co.") -> Express Cards Enterprises Co. | AF35: =IFERROR(__xludf.DUMMYFUNCTION("""COMPUTED_VALUE"""),5.0) -> 5
A36: 26 | B36: Luminaire Printing and Publication Corp. | C36: 4.5833333 | E36: 27 | F36: MPLUS | I36: 26 | J36: Chemtrust Global Market Inc. | K36: 4.0666667 | M36: =IFERROR(__xludf.DUMMYFUNCTION("""COMPUTED_VALUE"""),"Luminaire Printing And Publishing Corp.") -> Luminaire Printing And Publishing Corp. | N36: =IFERROR(__xludf.DUMMYFUNCTION("""COMPUTED_VALUE"""),4.683333333333334) -> 4.6833333 | O36: =IFERROR(__xludf.DUMMYFUNCTION("""COMPUTED_VALUE"""),44817.0) -> 44817 | Q36: =IFERROR(__xludf.DUMMYFUNCTION("""COMPUTED_VALUE"""),"Contrade Integrated Depot") -> Contrade Integrated Depot | R36: =IFERROR(__xludf.DUMMYFUNCTION("""COMPUTED_VALUE"""),4.566666666666666) -> 4.5666667 | S36: =IFERROR(__xludf.DUMMYFUNCTION("""COMPUTED_VALUE"""),45189.0) -> 45189 | U36: =IFERROR(__xludf.DUMMYFUNCTION("""COMPUTED_VALUE"""),"Alpha Steel Office and Home Furnishing Company") -> Alpha Steel Office and Home Furnishing Company | V36: =IFERROR(__xludf.DUMMYFUNCTION("""COMPUTED_VALUE"""),4.833333333333333) -> 4.8333333 | W36: =IFERROR(__xludf.DUMMYFUNCTION("""COMPUTED_VALUE"""),45526.0) -> 45526 | Y36: =IFERROR(__xludf.DUMMYFUNCTION("""COMPUTED_VALUE"""),"One Supply") -> One Supply | Z36: =IFERROR(__xludf.DUMMYFUNCTION("""COMPUTED_VALUE"""),5.0) -> 5 | AB36: =IFERROR(__xludf.DUMMYFUNCTION("""COMPUTED_VALUE"""),"Forefront Book Co., Inc.") -> Forefront Book Co., Inc. | AC36: =IFERROR(__xludf.DUMMYFUNCTION("""COMPUTED_VALUE"""),4.733333333333333) -> 4.7333333 | AE36: =IFERROR(__xludf.DUMMYFUNCTION("""COMPUTED_VALUE"""),"Falcon Waterfree Philippines, Inc.") -> Falcon Waterfree Philippines, Inc. | AF36: =IFERROR(__xludf.DUMMYFUNCTION("""COMPUTED_VALUE"""),4.791666666666667) -> 4.7916667
A37: 27 | B37: JARM Printing Press | E37: 28 | F37: 17th St. Maxiprint Co | I37: 27 | J37: WISECHOICE CLEANING SUPPLIES AND TRADING CORP. | M37: =IFERROR(__xludf.DUMMYFUNCTION("""COMPUTED_VALUE"""),"Polaris Prime Air Tech Corporation") -> Polaris Prime Air Tech Corporation | N37: =IFERROR(__xludf.DUMMYFUNCTION("""COMPUTED_VALUE"""),4.0) -> 4 | O37: =IFERROR(__xludf.DUMMYFUNCTION("""COMPUTED_VALUE"""),44817.0) -> 44817 | Q37: =IFERROR(__xludf.DUMMYFUNCTION("""COMPUTED_VALUE"""),"Booktrens Enterprises") -> Booktrens Enterprises | R37: =IFERROR(__xludf.DUMMYFUNCTION("""COMPUTED_VALUE"""),5.0) -> 5 | S37: =IFERROR(__xludf.DUMMYFUNCTION("""COMPUTED_VALUE"""),45191.0) -> 45191 | U37: =IFERROR(__xludf.DUMMYFUNCTION("""COMPUTED_VALUE"""),"Printing Shop PrintPilipinas.com") -> Printing Shop PrintPilipinas.com | V37: =IFERROR(__xludf.DUMMYFUNCTION("""COMPUTED_VALUE"""),4.333333333333333) -> 4.3333333 | W37: =IFERROR(__xludf.DUMMYFUNCTION("""COMPUTED_VALUE"""),45526.0) -> 45526 | Y37: =IFERROR(__xludf.DUMMYFUNCTION("""COMPUTED_VALUE"""),"Oray Copier Solutions") -> Oray Copier Solutions | Z37: =IFERROR(__xludf.DUMMYFUNCTION("""COMPUTED_VALUE"""),5.0) -> 5 | AB37: =IFERROR(__xludf.DUMMYFUNCTION("""COMPUTED_VALUE"""),"Goldlink Indsutrial Sales") -> Goldlink Indsutrial Sales | AC37: =IFERROR(__xludf.DUMMYFUNCTION("""COMPUTED_VALUE"""),4.541666666666666) -> 4.5416667 | AE37: =IFERROR(__xludf.DUMMYFUNCTION("""COMPUTED_VALUE"""),"Golden Advance Marketing") -> Golden Advance Marketing | AF37: =IFERROR(__xludf.DUMMYFUNCTION("""COMPUTED_VALUE"""),4.763888888888889) -> 4.7638889
A38: 28 | B38: Sprintec Printing Press, Inc. | E38: 29 | F38: Print Depot, Inc. | I38: 28 | J38: Hospeco Philippines, Inc. | K38: 4.6833333 | M38: =IFERROR(__xludf.DUMMYFUNCTION("""COMPUTED_VALUE"""),"Hospeco Philippines, Inc.") -> Hospeco Philippines, Inc. | N38: =IFERROR(__xludf.DUMMYFUNCTION("""COMPUTED_VALUE"""),4.833333333333333) -> 4.8333333 | O38: =IFERROR(__xludf.DUMMYFUNCTION("""COMPUTED_VALUE"""),44825.0) -> 44825 | Q38: =IFERROR(__xludf.DUMMYFUNCTION("""COMPUTED_VALUE"""),"Microsmith Technology System,Inc.") -> Microsmith Technology System,Inc. | R38: =IFERROR(__xludf.DUMMYFUNCTION("""COMPUTED_VALUE"""),4.666666666666667) -> 4.6666667 | S38: =IFERROR(__xludf.DUMMYFUNCTION("""COMPUTED_VALUE"""),45195.0) -> 45195 | U38: =IFERROR(__xludf.DUMMYFUNCTION("""COMPUTED_VALUE"""),"Commerce Asia, Inc.") -> Commerce Asia, Inc. | V38: =IFERROR(__xludf.DUMMYFUNCTION("""COMPUTED_VALUE"""),4.833333333333333) -> 4.8333333 | W38: =IFERROR(__xludf.DUMMYFUNCTION("""COMPUTED_VALUE"""),45527.0) -> 45527 | Y38: =IFERROR(__xludf.DUMMYFUNCTION("""COMPUTED_VALUE"""),"PNB Credit Card") -> PNB Credit Card | Z38: =IFERROR(__xludf.DUMMYFUNCTION("""COMPUTED_VALUE"""),3.9166666666666665) -> 3.9166667 | AB38: =IFERROR(__xludf.DUMMYFUNCTION("""COMPUTED_VALUE"""),"Hospeco Philippines, Inc.") -> Hospeco Philippines, Inc. | AC38: =IFERROR(__xludf.DUMMYFUNCTION("""COMPUTED_VALUE"""),4.416666666666666) -> 4.4166667 | AE38: =IFERROR(__xludf.DUMMYFUNCTION("""COMPUTED_VALUE"""),"Hospeco Philippines, Inc.") -> Hospeco Philippines, Inc. | AF38: =IFERROR(__xludf.DUMMYFUNCTION("""COMPUTED_VALUE"""),4.811111111111111) -> 4.8111111
A39: 29 | B39: Leonard Prints, Inc. | C39: 4.6046296 | E39: 30 | F39: Gleam Photography Studio | I39: 29 | J39: Falcon Waterfree Philippines, Inc. | K39: 5 | M39: =IFERROR(__xludf.DUMMYFUNCTION("""COMPUTED_VALUE"""),"Contrade Integrated Depot") -> Contrade Integrated Depot | N39: =IFERROR(__xludf.DUMMYFUNCTION("""COMPUTED_VALUE"""),3.8733333333333335) -> 3.8733333 | O39: =IFERROR(__xludf.DUMMYFUNCTION("""COMPUTED_VALUE"""),44827.0) -> 44827 | Q39: =IFERROR(__xludf.DUMMYFUNCTION("""COMPUTED_VALUE"""),"Creative Juice Digital Printing") -> Creative Juice Digital Printing | R39: =IFERROR(__xludf.DUMMYFUNCTION("""COMPUTED_VALUE"""),5.0) -> 5 | S39: =IFERROR(__xludf.DUMMYFUNCTION("""COMPUTED_VALUE"""),45196.0) -> 45196 | U39: =IFERROR(__xludf.DUMMYFUNCTION("""COMPUTED_VALUE"""),"Contrade Integrated Depot") -> Contrade Integrated Depot | V39: =IFERROR(__xludf.DUMMYFUNCTION("""COMPUTED_VALUE"""),4.75) -> 4.75 | W39: =IFERROR(__xludf.DUMMYFUNCTION("""COMPUTED_VALUE"""),45528.0) -> 45528 | Y39: =IFERROR(__xludf.DUMMYFUNCTION("""COMPUTED_VALUE"""),"Polaris Integrated Industries, Inc.") -> Polaris Integrated Industries, Inc. | Z39: =IFERROR(__xludf.DUMMYFUNCTION("""COMPUTED_VALUE"""),4.991666666666666) -> 4.9916667 | AB39: =IFERROR(__xludf.DUMMYFUNCTION("""COMPUTED_VALUE"""),"I-Stop Graphics and Business Center") -> I-Stop Graphics and Business Center | AC39: =IFERROR(__xludf.DUMMYFUNCTION("""COMPUTED_VALUE"""),4.083333333333334) -> 4.0833333 | AE39: =IFERROR(__xludf.DUMMYFUNCTION("""COMPUTED_VALUE"""),"Hytec Power, Inc.") -> Hytec Power, Inc. | AF39: =IFERROR(__xludf.DUMMYFUNCTION("""COMPUTED_VALUE"""),3.8333333333333335) -> 3.8333333
A40: 30 | B40: Sales Trojan Manufacturing MFG. Corp | E40: 31 | F40: POSH Studio | I40: Constructions and Electrical Materials | K40: =average(K41:K58) -> 4.7458333 | M40: =IFERROR(__xludf.DUMMYFUNCTION("""COMPUTED_VALUE"""),"Net Ad IT Solutions") -> Net Ad IT Solutions | N40: =IFERROR(__xludf.DUMMYFUNCTION("""COMPUTED_VALUE"""),5.0) -> 5 | O40: =IFERROR(__xludf.DUMMYFUNCTION("""COMPUTED_VALUE"""),44827.0) -> 44827 | Q40: =IFERROR(__xludf.DUMMYFUNCTION("""COMPUTED_VALUE"""),"Creative Juice Digital Printing") -> Creative Juice Digital Printing | R40: =IFERROR(__xludf.DUMMYFUNCTION("""COMPUTED_VALUE"""),5.0) -> 5 | S40: =IFERROR(__xludf.DUMMYFUNCTION("""COMPUTED_VALUE"""),45196.0) -> 45196 | U40: =IFERROR(__xludf.DUMMYFUNCTION("""COMPUTED_VALUE"""),"Contrade Integrated Depot") -> Contrade Integrated Depot | V40: =IFERROR(__xludf.DUMMYFUNCTION("""COMPUTED_VALUE"""),4.75) -> 4.75 | W40: =IFERROR(__xludf.DUMMYFUNCTION("""COMPUTED_VALUE"""),45528.0) -> 45528 | Y40: =IFERROR(__xludf.DUMMYFUNCTION("""COMPUTED_VALUE"""),"Polaris Prime Air Tech Corporation") -> Polaris Prime Air Tech Corporation | Z40: =IFERROR(__xludf.DUMMYFUNCTION("""COMPUTED_VALUE"""),4.5) -> 4.5 | AB40: =IFERROR(__xludf.DUMMYFUNCTION("""COMPUTED_VALUE"""),"JLY Garment Trading") -> JLY Garment Trading | AC40: =IFERROR(__xludf.DUMMYFUNCTION("""COMPUTED_VALUE"""),4.713888888888889) -> 4.7138889 | AE40: =IFERROR(__xludf.DUMMYFUNCTION("""COMPUTED_VALUE"""),"Inkonvert Enterprises") -> Inkonvert Enterprises | AF40: =IFERROR(__xludf.DUMMYFUNCTION("""COMPUTED_VALUE"""),5.0) -> 5
A41: 31 | B41: Print Depot, Inc. | C41: 4.7916667 | E41: Laboratory Supplies & Equipment | G41: =average(G42:G46) -> #DIV/0! | I41: 30 | J41: ARKIN HARDWARE | M41: =IFERROR(__xludf.DUMMYFUNCTION("""COMPUTED_VALUE"""),"Oray Copier Solutions") -> Oray Copier Solutions | N41: =IFERROR(__xludf.DUMMYFUNCTION("""COMPUTED_VALUE"""),5.0) -> 5 | O41: =IFERROR(__xludf.DUMMYFUNCTION("""COMPUTED_VALUE"""),44830.0) -> 44830 | Q41: =IFERROR(__xludf.DUMMYFUNCTION("""COMPUTED_VALUE"""),"Contrade Integrated Depot") -> Contrade Integrated Depot | R41: =IFERROR(__xludf.DUMMYFUNCTION("""COMPUTED_VALUE"""),4.83) -> 4.83 | S41: =IFERROR(__xludf.DUMMYFUNCTION("""COMPUTED_VALUE"""),45199.0) -> 45199 | U41: =IFERROR(__xludf.DUMMYFUNCTION("""COMPUTED_VALUE"""),"Luminaire Printing And Publishing Corp.") -> Luminaire Printing And Publishing Corp. | V41: =IFERROR(__xludf.DUMMYFUNCTION("""COMPUTED_VALUE"""),4.833333333333333) -> 4.8333333 | W41: =IFERROR(__xludf.DUMMYFUNCTION("""COMPUTED_VALUE"""),45534.0) -> 45534 | Y41: =IFERROR(__xludf.DUMMYFUNCTION("""COMPUTED_VALUE"""),"Rivchem Enterprises") -> Rivchem Enterprises | Z41: =IFERROR(__xludf.DUMMYFUNCTION("""COMPUTED_VALUE"""),4.71547619047619) -> 4.7154762 | AB41: =IFERROR(__xludf.DUMMYFUNCTION("""COMPUTED_VALUE"""),"Jarm Printing Press") -> Jarm Printing Press | AC41: =IFERROR(__xludf.DUMMYFUNCTION("""COMPUTED_VALUE"""),4.874999999999999) -> 4.875 | AE41: =IFERROR(__xludf.DUMMYFUNCTION("""COMPUTED_VALUE"""),"Jassen Harris Industries Corp.") -> Jassen Harris Industries Corp. | AF41: =IFERROR(__xludf.DUMMYFUNCTION("""COMPUTED_VALUE"""),4.833333333333334) -> 4.8333333
A42: 32 | B42: Gleam Photography Studio | E42: 32 | F42: Premier Physic Metrologie | I42: 31 | J42: ACE HARDWARE PHILIPPINES, INC. | M42: =IFERROR(__xludf.DUMMYFUNCTION("""COMPUTED_VALUE"""),"Net Ad IT Solutions") -> Net Ad IT Solutions | N42: =IFERROR(__xludf.DUMMYFUNCTION("""COMPUTED_VALUE"""),4.758333333333334) -> 4.7583333 | O42: =IFERROR(__xludf.DUMMYFUNCTION("""COMPUTED_VALUE"""),44832.0) -> 44832 | Q42: =IFERROR(__xludf.DUMMYFUNCTION("""COMPUTED_VALUE"""),"EESM Bookstore") -> EESM Bookstore | R42: =IFERROR(__xludf.DUMMYFUNCTION("""COMPUTED_VALUE"""),4.733333333333333) -> 4.7333333 | S42: =IFERROR(__xludf.DUMMYFUNCTION("""COMPUTED_VALUE"""),45199.0) -> 45199 | U42: =IFERROR(__xludf.DUMMYFUNCTION("""COMPUTED_VALUE"""),"V.M Industries Corp.") -> V.M Industries Corp. | V42: =IFERROR(__xludf.DUMMYFUNCTION("""COMPUTED_VALUE"""),4.666666666666667) -> 4.6666667 | W42: =IFERROR(__xludf.DUMMYFUNCTION("""COMPUTED_VALUE"""),45534.0) -> 45534 | Y42: =IFERROR(__xludf.DUMMYFUNCTION("""COMPUTED_VALUE"""),"Sert Technology Inc.") -> Sert Technology Inc. | Z42: =IFERROR(__xludf.DUMMYFUNCTION("""COMPUTED_VALUE"""),5.0) -> 5 | AB42: =IFERROR(__xludf.DUMMYFUNCTION("""COMPUTED_VALUE"""),"Leonard Prints Inc.") -> Leonard Prints Inc. | AC42: =IFERROR(__xludf.DUMMYFUNCTION("""COMPUTED_VALUE"""),4.84375) -> 4.84375 | AE42: =IFERROR(__xludf.DUMMYFUNCTION("""COMPUTED_VALUE"""),"Javammp Printing Services") -> Javammp Printing Services | AF42: =IFERROR(__xludf.DUMMYFUNCTION("""COMPUTED_VALUE"""),4.527777777777778) -> 4.5277778
A43: 33 | B43: POSH Studio | E43: 33 | F43: Tadeo's Marketing | I43: 32 | J43: ALL HOME | M43: =IFERROR(__xludf.DUMMYFUNCTION("""COMPUTED_VALUE"""),"Jarm Printing Press") -> Jarm Printing Press | N43: =IFERROR(__xludf.DUMMYFUNCTION("""COMPUTED_VALUE"""),4.75) -> 4.75 | O43: =IFERROR(__xludf.DUMMYFUNCTION("""COMPUTED_VALUE"""),44834.0) -> 44834 | Q43: =IFERROR(__xludf.DUMMYFUNCTION("""COMPUTED_VALUE"""),"EESM Bookstore") -> EESM Bookstore | R43: =IFERROR(__xludf.DUMMYFUNCTION("""COMPUTED_VALUE"""),4.833333333333333) -> 4.8333333 | S43: =IFERROR(__xludf.DUMMYFUNCTION("""COMPUTED_VALUE"""),45199.0) -> 45199 | U43: =IFERROR(__xludf.DUMMYFUNCTION("""COMPUTED_VALUE"""),"Microsmith Technology System,Inc.") -> Microsmith Technology System,Inc. | V43: =IFERROR(__xludf.DUMMYFUNCTION("""COMPUTED_VALUE"""),4.833333333333333) -> 4.8333333 | W43: =IFERROR(__xludf.DUMMYFUNCTION("""COMPUTED_VALUE"""),45537.0) -> 45537 | Y43: =IFERROR(__xludf.DUMMYFUNCTION("""COMPUTED_VALUE"""),"Sparklight Marketing Incorporated") -> Sparklight Marketing Incorporated | Z43: =IFERROR(__xludf.DUMMYFUNCTION("""COMPUTED_VALUE"""),4.2) -> 4.2 | AB43: =IFERROR(__xludf.DUMMYFUNCTION("""COMPUTED_VALUE"""),"Lordfel Marketing") -> Lordfel Marketing | AC43: =IFERROR(__xludf.DUMMYFUNCTION("""COMPUTED_VALUE"""),4.166666666666667) -> 4.1666667 | AE43: =IFERROR(__xludf.DUMMYFUNCTION("""COMPUTED_VALUE"""),"Leonard Prints Inc.") -> Leonard Prints Inc. | AF43: =IFERROR(__xludf.DUMMYFUNCTION("""COMPUTED_VALUE"""),4.632777777777778) -> 4.6327778
A44: 34 | B44: Printing Shop PrintPilipinas | C44: 4.8046296 | E44: 34 | F44: Yana Chemodities, Incorporated | I44: 33 | J44: Jamex | M44: =IFERROR(__xludf.DUMMYFUNCTION("""COMPUTED_VALUE"""),"Creative Juice Digital Printing") -> Creative Juice Digital Printing | N44: =IFERROR(__xludf.DUMMYFUNCTION("""COMPUTED_VALUE"""),4.816666666666666) -> 4.8166667 | O44: =IFERROR(__xludf.DUMMYFUNCTION("""COMPUTED_VALUE"""),44837.0) -> 44837 | Q44: =IFERROR(__xludf.DUMMYFUNCTION("""COMPUTED_VALUE"""),"EESM Bookstore") -> EESM Bookstore | R44: =IFERROR(__xludf.DUMMYFUNCTION("""COMPUTED_VALUE"""),4.833333333333333) -> 4.8333333 | S44: =IFERROR(__xludf.DUMMYFUNCTION("""COMPUTED_VALUE"""),45199.0) -> 45199 | U44: =IFERROR(__xludf.DUMMYFUNCTION("""COMPUTED_VALUE"""),"Contrade Integrated Depot") -> Contrade Integrated Depot | V44: =IFERROR(__xludf.DUMMYFUNCTION("""COMPUTED_VALUE"""),4.833333333333333) -> 4.8333333 | W44: =IFERROR(__xludf.DUMMYFUNCTION("""COMPUTED_VALUE"""),45538.0) -> 45538 | Y44: =IFERROR(__xludf.DUMMYFUNCTION("""COMPUTED_VALUE"""),"Sprintec Printing Press, Inc.") -> Sprintec Printing Press, Inc. | Z44: =IFERROR(__xludf.DUMMYFUNCTION("""COMPUTED_VALUE"""),3.3333333333333335) -> 3.3333333 | AB44: =IFERROR(__xludf.DUMMYFUNCTION("""COMPUTED_VALUE"""),"Luminaire Printing And Publishing Corp.") -> Luminaire Printing And Publishing Corp. | AC44: =IFERROR(__xludf.DUMMYFUNCTION("""COMPUTED_VALUE"""),4.866666666666666) -> 4.8666667 | AE44: =IFERROR(__xludf.DUMMYFUNCTION("""COMPUTED_VALUE"""),"Litera Trading Inc.") -> Litera Trading Inc. | AF44: =IFERROR(__xludf.DUMMYFUNCTION("""COMPUTED_VALUE"""),4.833333333333333) -> 4.8333333
A45: Laboratory Supplies & Equipment | C45: =average(C46:C47) -> #DIV/0! | E45: 35 | F45: Paddington Trading | I45: 34 | J45: Prescriptive Constructions | M45: =IFERROR(__xludf.DUMMYFUNCTION("""COMPUTED_VALUE"""),"Net Ad IT Solutions") -> Net Ad IT Solutions | N45: =IFERROR(__xludf.DUMMYFUNCTION("""COMPUTED_VALUE"""),4.833333333333333) -> 4.8333333 | O45: =IFERROR(__xludf.DUMMYFUNCTION("""COMPUTED_VALUE"""),44839.0) -> 44839 | Q45: =IFERROR(__xludf.DUMMYFUNCTION("""COMPUTED_VALUE"""),"Chemtrust Global Market, Inc.") -> Chemtrust Global Market, Inc. | R45: =IFERROR(__xludf.DUMMYFUNCTION("""COMPUTED_VALUE"""),4.558333333333334) -> 4.5583333 | S45: =IFERROR(__xludf.DUMMYFUNCTION("""COMPUTED_VALUE"""),45201.0) -> 45201 | U45: =IFERROR(__xludf.DUMMYFUNCTION("""COMPUTED_VALUE"""),"Microsmith Technology System,Inc.") -> Microsmith Technology System,Inc. | V45: =IFERROR(__xludf.DUMMYFUNCTION("""COMPUTED_VALUE"""),4.833333333333333) -> 4.8333333 | W45: =IFERROR(__xludf.DUMMYFUNCTION("""COMPUTED_VALUE"""),45539.0) -> 45539 | Y45: =IFERROR(__xludf.DUMMYFUNCTION("""COMPUTED_VALUE"""),"Tropical Palms Fashion House, Inc.") -> Tropical Palms Fashion House, Inc. | Z45: =IFERROR(__xludf.DUMMYFUNCTION("""COMPUTED_VALUE"""),4.783333333333333) -> 4.7833333 | AB45: =IFERROR(__xludf.DUMMYFUNCTION("""COMPUTED_VALUE"""),"Manila Rubber Corporation") -> Manila Rubber Corporation | AC45: =IFERROR(__xludf.DUMMYFUNCTION("""COMPUTED_VALUE"""),4.375) -> 4.375 | AE45: =IFERROR(__xludf.DUMMYFUNCTION("""COMPUTED_VALUE"""),"Luminaire Printing And Publishing Corp.") -> Luminaire Printing And Publishing Corp. | AF45: =IFERROR(__xludf.DUMMYFUNCTION("""COMPUTED_VALUE"""),4.583333333333333) -> 4.5833333
A46: 35 | B46: Premier Physic Metrologie | E46: 36 | F46: Mars Laboratory | I46: 35 | J46: Microlynx Systems Enterprises | M46: =IFERROR(__xludf.DUMMYFUNCTION("""COMPUTED_VALUE"""),"Contrade Integrated Depot") -> Contrade Integrated Depot | N46: =IFERROR(__xludf.DUMMYFUNCTION("""COMPUTED_VALUE"""),3.9166666666666665) -> 3.9166667 | O46: =IFERROR(__xludf.DUMMYFUNCTION("""COMPUTED_VALUE"""),44846.0) -> 44846 | Q46: =IFERROR(__xludf.DUMMYFUNCTION("""COMPUTED_VALUE"""),"Chemtrust Global Market, Inc.") -> Chemtrust Global Market, Inc. | R46: =IFERROR(__xludf.DUMMYFUNCTION("""COMPUTED_VALUE"""),4.558333333333334) -> 4.5583333 | S46: =IFERROR(__xludf.DUMMYFUNCTION("""COMPUTED_VALUE"""),45201.0) -> 45201 | U46: =IFERROR(__xludf.DUMMYFUNCTION("""COMPUTED_VALUE"""),"Abenson Ventures, Inc.") -> Abenson Ventures, Inc. | V46: =IFERROR(__xludf.DUMMYFUNCTION("""COMPUTED_VALUE"""),4.833333333333333) -> 4.8333333 | W46: =IFERROR(__xludf.DUMMYFUNCTION("""COMPUTED_VALUE"""),45539.0) -> 45539 | AB46: =IFERROR(__xludf.DUMMYFUNCTION("""COMPUTED_VALUE"""),"Marrbont Corporation") -> Marrbont Corporation | AC46: =IFERROR(__xludf.DUMMYFUNCTION("""COMPUTED_VALUE"""),4.6) -> 4.6 | AE46: =IFERROR(__xludf.DUMMYFUNCTION("""COMPUTED_VALUE"""),"Ma Espiritu Tiles Trading ") -> Ma Espiritu Tiles Trading | AF46: =IFERROR(__xludf.DUMMYFUNCTION("""COMPUTED_VALUE"""),4.691666666666666) -> 4.6916667
A47: 36 | B47: Labotech Trading | E47: Personalized Materials | G47: =average(G48:G52) -> 4.65 | I47: 36 | J47: Roavsan General Merchandise | M47: =IFERROR(__xludf.DUMMYFUNCTION("""COMPUTED_VALUE"""),"Rivchem Enterprises") -> Rivchem Enterprises | N47: =IFERROR(__xludf.DUMMYFUNCTION("""COMPUTED_VALUE"""),4.758333333333334) -> 4.7583333 | O47: =IFERROR(__xludf.DUMMYFUNCTION("""COMPUTED_VALUE"""),44849.0) -> 44849 | Q47: =IFERROR(__xludf.DUMMYFUNCTION("""COMPUTED_VALUE"""),"Creative Juice Digital Printing") -> Creative Juice Digital Printing | R47: =IFERROR(__xludf.DUMMYFUNCTION("""COMPUTED_VALUE"""),5.0) -> 5 | S47: =IFERROR(__xludf.DUMMYFUNCTION("""COMPUTED_VALUE"""),45201.0) -> 45201 | U47: =IFERROR(__xludf.DUMMYFUNCTION("""COMPUTED_VALUE"""),"Net Ad IT Solutions") -> Net Ad IT Solutions | V47: =IFERROR(__xludf.DUMMYFUNCTION("""COMPUTED_VALUE"""),4.833333333333333) -> 4.8333333 | W47: =IFERROR(__xludf.DUMMYFUNCTION("""COMPUTED_VALUE"""),45539.0) -> 45539 | AB47: =IFERROR(__xludf.DUMMYFUNCTION("""COMPUTED_VALUE"""),"Microsmith Technology System,Inc.") -> Microsmith Technology System,Inc. | AC47: =IFERROR(__xludf.DUMMYFUNCTION("""COMPUTED_VALUE"""),4.868055555555555) -> 4.8680556 | AE47: =IFERROR(__xludf.DUMMYFUNCTION("""COMPUTED_VALUE"""),"Manos Allied Corporation") -> Manos Allied Corporation | AF47: =IFERROR(__xludf.DUMMYFUNCTION("""COMPUTED_VALUE"""),4.933333333333334) -> 4.9333333
A48: Personalized Materials | C48: =average(C49:C53) -> 4.6041667 | E48: 37 | F48: Ahrcel's Gift Shop | I48: 37 | J48: YKP General Merchandise | M48: =IFERROR(__xludf.DUMMYFUNCTION("""COMPUTED_VALUE"""),"Net Ad IT Solutions") -> Net Ad IT Solutions | N48: =IFERROR(__xludf.DUMMYFUNCTION("""COMPUTED_VALUE"""),4.45) -> 4.45 | O48: =IFERROR(__xludf.DUMMYFUNCTION("""COMPUTED_VALUE"""),44853.0) -> 44853 | Q48: =IFERROR(__xludf.DUMMYFUNCTION("""COMPUTED_VALUE"""),"Creative Juice Digital Printing") -> Creative Juice Digital Printing | R48: =IFERROR(__xludf.DUMMYFUNCTION("""COMPUTED_VALUE"""),4.733333333333333) -> 4.7333333 | S48: =IFERROR(__xludf.DUMMYFUNCTION("""COMPUTED_VALUE"""),45201.0) -> 45201 | U48: =IFERROR(__xludf.DUMMYFUNCTION("""COMPUTED_VALUE"""),"Printing Shop PrintPilipinas.com") -> Printing Shop PrintPilipinas.com | V48: =IFERROR(__xludf.DUMMYFUNCTION("""COMPUTED_VALUE"""),4.833333333333333) -> 4.8333333 | W48: =IFERROR(__xludf.DUMMYFUNCTION("""COMPUTED_VALUE"""),45540.0) -> 45540 | AB48: =IFERROR(__xludf.DUMMYFUNCTION("""COMPUTED_VALUE"""),"Mostaco Printing") -> Mostaco Printing | AC48: =IFERROR(__xludf.DUMMYFUNCTION("""COMPUTED_VALUE"""),5.0) -> 5 | AE48: =IFERROR(__xludf.DUMMYFUNCTION("""COMPUTED_VALUE"""),"Microsmith Technology System,Inc.") -> Microsmith Technology System,Inc. | AF48: =IFERROR(__xludf.DUMMYFUNCTION("""COMPUTED_VALUE"""),4.861257309941521) -> 4.8612573
A49: 37 | B49: Ahrcel's Gift Shop | E49: 38 | F49: Awardextremes, Inc. | G49: 4.5666667 | I49: 38 | J49: Wilcon Depot Sucat | M49: =IFERROR(__xludf.DUMMYFUNCTION("""COMPUTED_VALUE"""),"Columbia Technologies, Inc.") -> Columbia Technologies, Inc. | N49: =IFERROR(__xludf.DUMMYFUNCTION("""COMPUTED_VALUE"""),5.0) -> 5 | O49: =IFERROR(__xludf.DUMMYFUNCTION("""COMPUTED_VALUE"""),44859.0) -> 44859 | Q49: =IFERROR(__xludf.DUMMYFUNCTION("""COMPUTED_VALUE"""),"Rivchem Enterprises") -> Rivchem Enterprises | R49: =IFERROR(__xludf.DUMMYFUNCTION("""COMPUTED_VALUE"""),4.6) -> 4.6 | S49: =IFERROR(__xludf.DUMMYFUNCTION("""COMPUTED_VALUE"""),45201.0) -> 45201 | U49: =IFERROR(__xludf.DUMMYFUNCTION("""COMPUTED_VALUE"""),"Microsmith Technology System,Inc.") -> Microsmith Technology System,Inc. | V49: =IFERROR(__xludf.DUMMYFUNCTION("""COMPUTED_VALUE"""),4.783333333333334) -> 4.7833333 | W49: =IFERROR(__xludf.DUMMYFUNCTION("""COMPUTED_VALUE"""),45541.0) -> 45541 | AB49: =IFERROR(__xludf.DUMMYFUNCTION("""COMPUTED_VALUE"""),"Net Ad IT Solutions") -> Net Ad IT Solutions | AC49: =IFERROR(__xludf.DUMMYFUNCTION("""COMPUTED_VALUE"""),4.8314814814814815) -> 4.8314815 | AE49: =IFERROR(__xludf.DUMMYFUNCTION("""COMPUTED_VALUE"""),"Montesan Enterprises") -> Montesan Enterprises | AF49: =IFERROR(__xludf.DUMMYFUNCTION("""COMPUTED_VALUE"""),4.833333333333333) -> 4.8333333
A50: 38 | B50: Awardextremes, Inc. | E50: 39 | F50: Raynard's Enterprise | G50: 4.7333333 | I50: 39 | J50: Circuit Solutions, Inc. | M50: =IFERROR(__xludf.DUMMYFUNCTION("""COMPUTED_VALUE"""),"Contrade Integrated Depot") -> Contrade Integrated Depot | N50: =IFERROR(__xludf.DUMMYFUNCTION("""COMPUTED_VALUE"""),3.9166666666666665) -> 3.9166667 | O50: =IFERROR(__xludf.DUMMYFUNCTION("""COMPUTED_VALUE"""),44860.0) -> 44860 | Q50: =IFERROR(__xludf.DUMMYFUNCTION("""COMPUTED_VALUE"""),"Falcon Waterfree Philippines, Inc.") -> Falcon Waterfree Philippines, Inc. | R50: =IFERROR(__xludf.DUMMYFUNCTION("""COMPUTED_VALUE"""),4.75) -> 4.75 | S50: =IFERROR(__xludf.DUMMYFUNCTION("""COMPUTED_VALUE"""),45203.0) -> 45203 | U50: =IFERROR(__xludf.DUMMYFUNCTION("""COMPUTED_VALUE"""),"Microsmith Technology System,Inc.") -> Microsmith Technology System,Inc. | V50: =IFERROR(__xludf.DUMMYFUNCTION("""COMPUTED_VALUE"""),4.791666666666667) -> 4.7916667 | W50: =IFERROR(__xludf.DUMMYFUNCTION("""COMPUTED_VALUE"""),45541.0) -> 45541 | AB50: =IFERROR(__xludf.DUMMYFUNCTION("""COMPUTED_VALUE"""),"Oray Copier Solutions") -> Oray Copier Solutions | AC50: =IFERROR(__xludf.DUMMYFUNCTION("""COMPUTED_VALUE"""),4.666666666666667) -> 4.6666667 | AE50: =IFERROR(__xludf.DUMMYFUNCTION("""COMPUTED_VALUE"""),"Mostaco Marketing") -> Mostaco Marketing | AF50: =IFERROR(__xludf.DUMMYFUNCTION("""COMPUTED_VALUE"""),5.0) -> 5
A51: 39 | B51: Raynard's Enterprise | E51: 40 | F51: EIG Metal Engravers | I51: 40 | J51: CW Marketing & Development Corporation | M51: =IFERROR(__xludf.DUMMYFUNCTION("""COMPUTED_VALUE"""),"Microsmith Technology System,Inc.") -> Microsmith Technology System,Inc. | N51: =IFERROR(__xludf.DUMMYFUNCTION("""COMPUTED_VALUE"""),4.766666666666667) -> 4.7666667 | O51: =IFERROR(__xludf.DUMMYFUNCTION("""COMPUTED_VALUE"""),44862.0) -> 44862 | Q51: =IFERROR(__xludf.DUMMYFUNCTION("""COMPUTED_VALUE"""),"Contrade Integrated Depot") -> Contrade Integrated Depot | R51: =IFERROR(__xludf.DUMMYFUNCTION("""COMPUTED_VALUE"""),4.83) -> 4.83 | S51: =IFERROR(__xludf.DUMMYFUNCTION("""COMPUTED_VALUE"""),45205.0) -> 45205 | U51: =IFERROR(__xludf.DUMMYFUNCTION("""COMPUTED_VALUE"""),"Microsmith Technology System,Inc.") -> Microsmith Technology System,Inc. | V51: =IFERROR(__xludf.DUMMYFUNCTION("""COMPUTED_VALUE"""),4.916666666666667) -> 4.9166667 | W51: =IFERROR(__xludf.DUMMYFUNCTION("""COMPUTED_VALUE"""),45541.0) -> 45541 | AB51: =IFERROR(__xludf.DUMMYFUNCTION("""COMPUTED_VALUE"""),"Paper Tree Marketing Group, Inc.") -> Paper Tree Marketing Group, Inc. | AC51: =IFERROR(__xludf.DUMMYFUNCTION("""COMPUTED_VALUE"""),4.8) -> 4.8 | AE51: =IFERROR(__xludf.DUMMYFUNCTION("""COMPUTED_VALUE"""),"Mostaco Printing") -> Mostaco Printing | AF51: =IFERROR(__xludf.DUMMYFUNCTION("""COMPUTED_VALUE"""),4.694444444444445) -> 4.6944444
A52: 40 | B52: EIG Metal Engravers | C52: 4.9166667 | E52: 41 | F52: MMP Friendly Gift Ideas Store | I52: 41 | J52: Polaris Integrated Industries, Inc. | K52: 4.9916667 | M52: =IFERROR(__xludf.DUMMYFUNCTION("""COMPUTED_VALUE"""),"Microsmith Technology System,Inc.") -> Microsmith Technology System,Inc. | N52: =IFERROR(__xludf.DUMMYFUNCTION("""COMPUTED_VALUE"""),5.0) -> 5 | O52: =IFERROR(__xludf.DUMMYFUNCTION("""COMPUTED_VALUE"""),44862.0) -> 44862 | Q52: =IFERROR(__xludf.DUMMYFUNCTION("""COMPUTED_VALUE"""),"Contrade Integrated Depot") -> Contrade Integrated Depot | R52: =IFERROR(__xludf.DUMMYFUNCTION("""COMPUTED_VALUE"""),4.83) -> 4.83 | S52: =IFERROR(__xludf.DUMMYFUNCTION("""COMPUTED_VALUE"""),45205.0) -> 45205 | U52: =IFERROR(__xludf.DUMMYFUNCTION("""COMPUTED_VALUE"""),"Printing Shop PrintPilipinas.com") -> Printing Shop PrintPilipinas.com | V52: =IFERROR(__xludf.DUMMYFUNCTION("""COMPUTED_VALUE"""),4.733333333333333) -> 4.7333333 | W52: =IFERROR(__xludf.DUMMYFUNCTION("""COMPUTED_VALUE"""),45544.0) -> 45544 | AB52: =IFERROR(__xludf.DUMMYFUNCTION("""COMPUTED_VALUE"""),"Patagonian Enterprises ") -> Patagonian Enterprises | AC52: =IFERROR(__xludf.DUMMYFUNCTION("""COMPUTED_VALUE"""),3.6666666666666665) -> 3.6666667 | AE52: =IFERROR(__xludf.DUMMYFUNCTION("""COMPUTED_VALUE"""),"Multiflex RNC Philippines inc.") -> Multiflex RNC Philippines inc. | AF52: =IFERROR(__xludf.DUMMYFUNCTION("""COMPUTED_VALUE"""),4.972222222222221) -> 4.9722222
A53: 41 | B53: JAVAMMP | C53: 4.2916667 | E53: Cloth & Uniforms | G53: =average(G54:G56) -> 4.8694444 | I53: 42 | J53: POLARIS PRIME AIR TECH CORPORATION | K53: 4.5 | M53: =IFERROR(__xludf.DUMMYFUNCTION("""COMPUTED_VALUE"""),"Amazon") -> Amazon | N53: =IFERROR(__xludf.DUMMYFUNCTION("""COMPUTED_VALUE"""),5.0) -> 5 | O53: =IFERROR(__xludf.DUMMYFUNCTION("""COMPUTED_VALUE"""),44867.0) -> 44867 | Q53: =IFERROR(__xludf.DUMMYFUNCTION("""COMPUTED_VALUE"""),"EESM Bookstore") -> EESM Bookstore | R53: =IFERROR(__xludf.DUMMYFUNCTION("""COMPUTED_VALUE"""),4.833333333333333) -> 4.8333333 | S53: =IFERROR(__xludf.DUMMYFUNCTION("""COMPUTED_VALUE"""),45205.0) -> 45205 | U53: =IFERROR(__xludf.DUMMYFUNCTION("""COMPUTED_VALUE"""),"Mostaco Printing") -> Mostaco Printing | V53: =IFERROR(__xludf.DUMMYFUNCTION("""COMPUTED_VALUE"""),4.833333333333333) -> 4.8333333 | W53: =IFERROR(__xludf.DUMMYFUNCTION("""COMPUTED_VALUE"""),45548.0) -> 45548 | AB53: =IFERROR(__xludf.DUMMYFUNCTION("""COMPUTED_VALUE"""),"Polaris Prime Air Tech Corporation") -> Polaris Prime Air Tech Corporation | AC53: =IFERROR(__xludf.DUMMYFUNCTION("""COMPUTED_VALUE"""),4.666666666666667) -> 4.6666667 | AE53: =IFERROR(__xludf.DUMMYFUNCTION("""COMPUTED_VALUE"""),"Net Ad IT Solutions") -> Net Ad IT Solutions | AF53: =IFERROR(__xludf.DUMMYFUNCTION("""COMPUTED_VALUE"""),4.907638888888888) -> 4.9076389
A54: Cloth & Uniforms | C54: =average(C55:C57) -> 4.5 | E54: 42 | F54: Tropical Palms Fashion House, Inc | G54: 4.8694444 | I54: 43 | J54: Eyarti Construction Services | M54: =IFERROR(__xludf.DUMMYFUNCTION("""COMPUTED_VALUE"""),"Amazon") -> Amazon | N54: =IFERROR(__xludf.DUMMYFUNCTION("""COMPUTED_VALUE"""),5.0) -> 5 | O54: =IFERROR(__xludf.DUMMYFUNCTION("""COMPUTED_VALUE"""),44867.0) -> 44867 | Q54: =IFERROR(__xludf.DUMMYFUNCTION("""COMPUTED_VALUE"""),"Rivchem Enterprises") -> Rivchem Enterprises | R54: =IFERROR(__xludf.DUMMYFUNCTION("""COMPUTED_VALUE"""),4.183333333333334) -> 4.1833333 | S54: =IFERROR(__xludf.DUMMYFUNCTION("""COMPUTED_VALUE"""),45205.0) -> 45205 | U54: =IFERROR(__xludf.DUMMYFUNCTION("""COMPUTED_VALUE"""),"Printing Shop PrintPilipinas.com") -> Printing Shop PrintPilipinas.com | V54: =IFERROR(__xludf.DUMMYFUNCTION("""COMPUTED_VALUE"""),4.833333333333333) -> 4.8333333 | W54: =IFERROR(__xludf.DUMMYFUNCTION("""COMPUTED_VALUE"""),45551.0) -> 45551 | AB54: =IFERROR(__xludf.DUMMYFUNCTION("""COMPUTED_VALUE"""),"Primeline Products Philippines, Inc.") -> Primeline Products Philippines, Inc. | AC54: =IFERROR(__xludf.DUMMYFUNCTION("""COMPUTED_VALUE"""),4.75) -> 4.75 | AE54: =IFERROR(__xludf.DUMMYFUNCTION("""COMPUTED_VALUE"""),"Northwind Communications and Electronics") -> Northwind Communications and Electronics | AF54: =IFERROR(__xludf.DUMMYFUNCTION("""COMPUTED_VALUE"""),4.3125) -> 4.3125
A55: 42 | B55: Tropical Palms Fashion House, Inc | C55: 5 | E55: 43 | F55: Big League Sports Wear Shop, The | I55: 44 | J55: Non-Residential Building Construction Lucky Construction | M55: =IFERROR(__xludf.DUMMYFUNCTION("""COMPUTED_VALUE"""),"JC Campit And Michael Berza") -> JC Campit And Michael Berza | N55: =IFERROR(__xludf.DUMMYFUNCTION("""COMPUTED_VALUE"""),5.0) -> 5 | O55: =IFERROR(__xludf.DUMMYFUNCTION("""COMPUTED_VALUE"""),44868.0) -> 44868 | Q55: =IFERROR(__xludf.DUMMYFUNCTION("""COMPUTED_VALUE"""),"Marrbont Corporation") -> Marrbont Corporation | R55: =IFERROR(__xludf.DUMMYFUNCTION("""COMPUTED_VALUE"""),4.6) -> 4.6 | S55: =IFERROR(__xludf.DUMMYFUNCTION("""COMPUTED_VALUE"""),45205.0) -> 45205 | U55: =IFERROR(__xludf.DUMMYFUNCTION("""COMPUTED_VALUE"""),"Net Ad IT Solutions") -> Net Ad IT Solutions | V55: =IFERROR(__xludf.DUMMYFUNCTION("""COMPUTED_VALUE"""),4.833333333333333) -> 4.8333333 | W55: =IFERROR(__xludf.DUMMYFUNCTION("""COMPUTED_VALUE"""),45553.0) -> 45553 | AB55: =IFERROR(__xludf.DUMMYFUNCTION("""COMPUTED_VALUE"""),"Printing Shop PrintPilipinas.com") -> Printing Shop PrintPilipinas.com | AC55: =IFERROR(__xludf.DUMMYFUNCTION("""COMPUTED_VALUE"""),4.732916666666667) -> 4.7329167 | AE55: =IFERROR(__xludf.DUMMYFUNCTION("""COMPUTED_VALUE"""),"Oray Copier Solutions") -> Oray Copier Solutions | AF55: =IFERROR(__xludf.DUMMYFUNCTION("""COMPUTED_VALUE"""),5.0) -> 5
A56: 43 | B56: Big League Sports Wear Shop, The | C56: 4 | E56: 44 | F56: Tieline, Inc | I56: 45 | J56: Cesar T. Bandoy Construction Services | M56: =IFERROR(__xludf.DUMMYFUNCTION("""COMPUTED_VALUE"""),"Rivchem Enterprises") -> Rivchem Enterprises | N56: =IFERROR(__xludf.DUMMYFUNCTION("""COMPUTED_VALUE"""),4.516666666666667) -> 4.5166667 | O56: =IFERROR(__xludf.DUMMYFUNCTION("""COMPUTED_VALUE"""),44868.0) -> 44868 | Q56: =IFERROR(__xludf.DUMMYFUNCTION("""COMPUTED_VALUE"""),"Wisechoice Cleaning Supplies and Trading Corp.") -> Wisechoice Cleaning Supplies and Trading Corp. | R56: =IFERROR(__xludf.DUMMYFUNCTION("""COMPUTED_VALUE"""),4.6) -> 4.6 | S56: =IFERROR(__xludf.DUMMYFUNCTION("""COMPUTED_VALUE"""),45205.0) -> 45205 | U56: =IFERROR(__xludf.DUMMYFUNCTION("""COMPUTED_VALUE"""),"Abenson Ventures, Inc.") -> Abenson Ventures, Inc. | V56: =IFERROR(__xludf.DUMMYFUNCTION("""COMPUTED_VALUE"""),4.833333333333333) -> 4.8333333 | W56: =IFERROR(__xludf.DUMMYFUNCTION("""COMPUTED_VALUE"""),45553.0) -> 45553 | AB56: =IFERROR(__xludf.DUMMYFUNCTION("""COMPUTED_VALUE"""),"REX Bookstore, Inc.") -> REX Bookstore, Inc. | AC56: =IFERROR(__xludf.DUMMYFUNCTION("""COMPUTED_VALUE"""),4.833333333333333) -> 4.8333333 | AE56: =IFERROR(__xludf.DUMMYFUNCTION("""COMPUTED_VALUE"""),"Palces Manufacturing, Inc.") -> Palces Manufacturing, Inc. | AF56: =IFERROR(__xludf.DUMMYFUNCTION("""COMPUTED_VALUE"""),4.933333333333334) -> 4.9333333
A57: 44 | B57: Tieline, Inc | E57: Furniture | G57: =average(G58:G62) -> 5 | I57: 46 | J57: Becabs Electrical Engineering Services | M57: =IFERROR(__xludf.DUMMYFUNCTION("""COMPUTED_VALUE"""),"Rivchem Enterprises") -> Rivchem Enterprises | N57: =IFERROR(__xludf.DUMMYFUNCTION("""COMPUTED_VALUE"""),4.766666666666667) -> 4.7666667 | O57: =IFERROR(__xludf.DUMMYFUNCTION("""COMPUTED_VALUE"""),44868.0) -> 44868 | Q57: =IFERROR(__xludf.DUMMYFUNCTION("""COMPUTED_VALUE"""),"Contrade Integrated Depot") -> Contrade Integrated Depot | R57: =IFERROR(__xludf.DUMMYFUNCTION("""COMPUTED_VALUE"""),4.83) -> 4.83 | S57: =IFERROR(__xludf.DUMMYFUNCTION("""COMPUTED_VALUE"""),45212.0) -> 45212 | U57: =IFERROR(__xludf.DUMMYFUNCTION("""COMPUTED_VALUE"""),"Chemtrust Global Market, Inc.") -> Chemtrust Global Market, Inc. | V57: =IFERROR(__xludf.DUMMYFUNCTION("""COMPUTED_VALUE"""),4.791666666666667) -> 4.7916667 | W57: =IFERROR(__xludf.DUMMYFUNCTION("""COMPUTED_VALUE"""),45553.0) -> 45553 | AB57: =IFERROR(__xludf.DUMMYFUNCTION("""COMPUTED_VALUE"""),"RSAZ Corporation") -> RSAZ Corporation | AC57: =IFERROR(__xludf.DUMMYFUNCTION("""COMPUTED_VALUE"""),4.833333333333333) -> 4.8333333 | AE57: =IFERROR(__xludf.DUMMYFUNCTION("""COMPUTED_VALUE"""),"Paper Tree Marketing Group, Inc.") -> Paper Tree Marketing Group, Inc. | AF57: =IFERROR(__xludf.DUMMYFUNCTION("""COMPUTED_VALUE"""),4.916666666666667) -> 4.9166667
A58: Furniture | C58: =average(C59:C60) -> 4.6666667 | E58: 45 | F58: Alpha Steel Office & Home Furnishing Company Inc. | G58: 5 | I58: 47 | J58: Takumina | M58: =IFERROR(__xludf.DUMMYFUNCTION("""COMPUTED_VALUE"""),"Columbia Technologies, Inc.") -> Columbia Technologies, Inc. | N58: =IFERROR(__xludf.DUMMYFUNCTION("""COMPUTED_VALUE"""),4.833333333333333) -> 4.8333333 | O58: =IFERROR(__xludf.DUMMYFUNCTION("""COMPUTED_VALUE"""),44869.0) -> 44869 | Q58: =IFERROR(__xludf.DUMMYFUNCTION("""COMPUTED_VALUE"""),"Creative Juice Digital Printing") -> Creative Juice Digital Printing | R58: =IFERROR(__xludf.DUMMYFUNCTION("""COMPUTED_VALUE"""),4.833333333333333) -> 4.8333333 | S58: =IFERROR(__xludf.DUMMYFUNCTION("""COMPUTED_VALUE"""),45212.0) -> 45212 | U58: =IFERROR(__xludf.DUMMYFUNCTION("""COMPUTED_VALUE"""),"Leonard Prints Inc.") -> Leonard Prints Inc. | V58: =IFERROR(__xludf.DUMMYFUNCTION("""COMPUTED_VALUE"""),4.508333333333333) -> 4.5083333 | W58: =IFERROR(__xludf.DUMMYFUNCTION("""COMPUTED_VALUE"""),45554.0) -> 45554 | AB58: =IFERROR(__xludf.DUMMYFUNCTION("""COMPUTED_VALUE"""),"Raynard's Enterprises") -> Raynard's Enterprises | AC58: =IFERROR(__xludf.DUMMYFUNCTION("""COMPUTED_VALUE"""),4.733333333333333) -> 4.7333333 | AE58: =IFERROR(__xludf.DUMMYFUNCTION("""COMPUTED_VALUE"""),"Patagonian Enterprises ") -> Patagonian Enterprises | AF58: =IFERROR(__xludf.DUMMYFUNCTION("""COMPUTED_VALUE"""),4.0) -> 4
A59: 45 | B59: Alpha Steel Office & Home Furnishing Company Inc. | C59: 4.8333333 | E59: 46 | F59: Elle Tech & Trend | I59: Office Supplies and Equipment | K59: =average(K60:K71) -> 4.6438611 | M59: =IFERROR(__xludf.DUMMYFUNCTION("""COMPUTED_VALUE"""),"Abenson Ventures, Inc.") -> Abenson Ventures, Inc. | N59: =IFERROR(__xludf.DUMMYFUNCTION("""COMPUTED_VALUE"""),5.0) -> 5 | O59: =IFERROR(__xludf.DUMMYFUNCTION("""COMPUTED_VALUE"""),44874.0) -> 44874 | Q59: =IFERROR(__xludf.DUMMYFUNCTION("""COMPUTED_VALUE"""),"Rivchem Enterprises") -> Rivchem Enterprises | R59: =IFERROR(__xludf.DUMMYFUNCTION("""COMPUTED_VALUE"""),5.0) -> 5 | S59: =IFERROR(__xludf.DUMMYFUNCTION("""COMPUTED_VALUE"""),45212.0) -> 45212 | U59: =IFERROR(__xludf.DUMMYFUNCTION("""COMPUTED_VALUE"""),"Leonard Prints Inc.") -> Leonard Prints Inc. | V59: =IFERROR(__xludf.DUMMYFUNCTION("""COMPUTED_VALUE"""),4.833333333333333) -> 4.8333333 | W59: =IFERROR(__xludf.DUMMYFUNCTION("""COMPUTED_VALUE"""),45554.0) -> 45554 | AB59: =IFERROR(__xludf.DUMMYFUNCTION("""COMPUTED_VALUE"""),"Rivchem Enterprises") -> Rivchem Enterprises | AC59: =IFERROR(__xludf.DUMMYFUNCTION("""COMPUTED_VALUE"""),4.545740740740741) -> 4.5457407 | AE59: =IFERROR(__xludf.DUMMYFUNCTION("""COMPUTED_VALUE"""),"Philippine Chinese Education Research Center Inc.") -> Philippine Chinese Education Research Center Inc. | AF59: =IFERROR(__xludf.DUMMYFUNCTION("""COMPUTED_VALUE"""),4.166666666666667) -> 4.1666667
A60: 46 | B60: Elle Tech & Trend | C60: 4.5 | E60: 47 | F60: ARKWOOD PLUS FINE FURNITURE | I60: 48 | J60: Inkonvert Enterprise | M60: =IFERROR(__xludf.DUMMYFUNCTION("""COMPUTED_VALUE"""),"Arkwood Plus Fine Furniture") -> Arkwood Plus Fine Furniture | N60: =IFERROR(__xludf.DUMMYFUNCTION("""COMPUTED_VALUE"""),4.0) -> 4 | O60: =IFERROR(__xludf.DUMMYFUNCTION("""COMPUTED_VALUE"""),44879.0) -> 44879 | Q60: =IFERROR(__xludf.DUMMYFUNCTION("""COMPUTED_VALUE"""),"Rivchem Enterprises") -> Rivchem Enterprises | R60: =IFERROR(__xludf.DUMMYFUNCTION("""COMPUTED_VALUE"""),4.258333333333334) -> 4.2583333 | S60: =IFERROR(__xludf.DUMMYFUNCTION("""COMPUTED_VALUE"""),45213.0) -> 45213 | U60: =IFERROR(__xludf.DUMMYFUNCTION("""COMPUTED_VALUE"""),"Leonard Prints Inc.") -> Leonard Prints Inc. | V60: =IFERROR(__xludf.DUMMYFUNCTION("""COMPUTED_VALUE"""),4.833333333333333) -> 4.8333333 | W60: =IFERROR(__xludf.DUMMYFUNCTION("""COMPUTED_VALUE"""),45554.0) -> 45554 | AB60: =IFERROR(__xludf.DUMMYFUNCTION("""COMPUTED_VALUE"""),"Roavsan General Merchandise") -> Roavsan General Merchandise | AC60: =IFERROR(__xludf.DUMMYFUNCTION("""COMPUTED_VALUE"""),4.0) -> 4 | AE60: =IFERROR(__xludf.DUMMYFUNCTION("""COMPUTED_VALUE"""),"Philippine Educational Theater Association, Inc.") -> Philippine Educational Theater Association, Inc. | AF60: =IFERROR(__xludf.DUMMYFUNCTION("""COMPUTED_VALUE"""),4.766666666666667) -> 4.7666667
A61: Construction and Engineering Supplies/Equipments | C61: =average(C62:C77) -> 4.4166667 | E61: 48 | F61: Asahi Design Centre Inc. | I61: 49 | J61: Abacus Book & Card Corp | M61: =IFERROR(__xludf.DUMMYFUNCTION("""COMPUTED_VALUE"""),"Creative Juice Digital Printing") -> Creative Juice Digital Printing | N61: =IFERROR(__xludf.DUMMYFUNCTION("""COMPUTED_VALUE"""),4.8) -> 4.8 | O61: =IFERROR(__xludf.DUMMYFUNCTION("""COMPUTED_VALUE"""),44879.0) -> 44879 | Q61: =IFERROR(__xludf.DUMMYFUNCTION("""COMPUTED_VALUE"""),"Rivchem Enterprises") -> Rivchem Enterprises | R61: =IFERROR(__xludf.DUMMYFUNCTION("""COMPUTED_VALUE"""),4.333333333333333) -> 4.3333333 | S61: =IFERROR(__xludf.DUMMYFUNCTION("""COMPUTED_VALUE"""),45213.0) -> 45213 | U61: =IFERROR(__xludf.DUMMYFUNCTION("""COMPUTED_VALUE"""),"Printing Shop PrintPilipinas.com") -> Printing Shop PrintPilipinas.com | V61: =IFERROR(__xludf.DUMMYFUNCTION("""COMPUTED_VALUE"""),4.825) -> 4.825 | W61: =IFERROR(__xludf.DUMMYFUNCTION("""COMPUTED_VALUE"""),45555.0) -> 45555 | AB61: =IFERROR(__xludf.DUMMYFUNCTION("""COMPUTED_VALUE"""),"Ronald Personalized Fashion Specialist") -> Ronald Personalized Fashion Specialist | AC61: =IFERROR(__xludf.DUMMYFUNCTION("""COMPUTED_VALUE"""),4.0) -> 4 | AE61: =IFERROR(__xludf.DUMMYFUNCTION("""COMPUTED_VALUE"""),"Primeline Products Philippines, Inc.") -> Primeline Products Philippines, Inc. | AF61: =IFERROR(__xludf.DUMMYFUNCTION("""COMPUTED_VALUE"""),4.674444444444444) -> 4.6744444
A62: 47 | B62: ARKIN HARDWARE | C62: 4.4166667 | E62: 49 | F62: Ergo Contracts Phil., Inc. | I62: 50 | J62: Amalgamated Specialties Corporation | K62: 4.3333333 | M62: =IFERROR(__xludf.DUMMYFUNCTION("""COMPUTED_VALUE"""),"Creative Juice Digital Printing") -> Creative Juice Digital Printing | N62: =IFERROR(__xludf.DUMMYFUNCTION("""COMPUTED_VALUE"""),4.833333333333333) -> 4.8333333 | O62: =IFERROR(__xludf.DUMMYFUNCTION("""COMPUTED_VALUE"""),44881.0) -> 44881 | Q62: =IFERROR(__xludf.DUMMYFUNCTION("""COMPUTED_VALUE"""),"Rivchem Enterprises") -> Rivchem Enterprises | R62: =IFERROR(__xludf.DUMMYFUNCTION("""COMPUTED_VALUE"""),5.0) -> 5 | S62: =IFERROR(__xludf.DUMMYFUNCTION("""COMPUTED_VALUE"""),45213.0) -> 45213 | U62: =IFERROR(__xludf.DUMMYFUNCTION("""COMPUTED_VALUE"""),"Mostaco Printing") -> Mostaco Printing | V62: =IFERROR(__xludf.DUMMYFUNCTION("""COMPUTED_VALUE"""),4.833333333333333) -> 4.8333333 | W62: =IFERROR(__xludf.DUMMYFUNCTION("""COMPUTED_VALUE"""),45555.0) -> 45555 | AB62: =IFERROR(__xludf.DUMMYFUNCTION("""COMPUTED_VALUE"""),"Times Trading Co., Inc.") -> Times Trading Co., Inc. | AC62: =IFERROR(__xludf.DUMMYFUNCTION("""COMPUTED_VALUE"""),4.686041666666667) -> 4.6860417 | AE62: =IFERROR(__xludf.DUMMYFUNCTION("""COMPUTED_VALUE"""),"Print Depot Inc.") -> Print Depot Inc. | AF62: =IFERROR(__xludf.DUMMYFUNCTION("""COMPUTED_VALUE"""),4.791666666666666) -> 4.7916667
A63: 48 | B63: Jamex | E63: Construction and Engineering Supplies/Equipments | G63: =average(G64:G80) -> 4.3793651 | I63: 51 | J63: Contrade Integrated Depot | K63: 4.3254444 | M63: =IFERROR(__xludf.DUMMYFUNCTION("""COMPUTED_VALUE"""),"Sparklight Marketing Incorporated") -> Sparklight Marketing Incorporated | N63: =IFERROR(__xludf.DUMMYFUNCTION("""COMPUTED_VALUE"""),4.2) -> 4.2 | O63: =IFERROR(__xludf.DUMMYFUNCTION("""COMPUTED_VALUE"""),44882.0) -> 44882 | Q63: =IFERROR(__xludf.DUMMYFUNCTION("""COMPUTED_VALUE"""),"Commerce Asia, Inc.") -> Commerce Asia, Inc. | R63: =IFERROR(__xludf.DUMMYFUNCTION("""COMPUTED_VALUE"""),5.0) -> 5 | S63: =IFERROR(__xludf.DUMMYFUNCTION("""COMPUTED_VALUE"""),45215.0) -> 45215 | U63: =IFERROR(__xludf.DUMMYFUNCTION("""COMPUTED_VALUE"""),"Printing Shop PrintPilipinas.com") -> Printing Shop PrintPilipinas.com | V63: =IFERROR(__xludf.DUMMYFUNCTION("""COMPUTED_VALUE"""),4.833333333333333) -> 4.8333333 | W63: =IFERROR(__xludf.DUMMYFUNCTION("""COMPUTED_VALUE"""),45555.0) -> 45555 | AB63: =IFERROR(__xludf.DUMMYFUNCTION("""COMPUTED_VALUE"""),"Tropical Palms Fashion House, Inc.") -> Tropical Palms Fashion House, Inc. | AC63: =IFERROR(__xludf.DUMMYFUNCTION("""COMPUTED_VALUE"""),4.729761904761905) -> 4.7297619 | AE63: =IFERROR(__xludf.DUMMYFUNCTION("""COMPUTED_VALUE"""),"Printing Shop PrintPilipinas.com") -> Printing Shop PrintPilipinas.com | AF63: =IFERROR(__xludf.DUMMYFUNCTION("""COMPUTED_VALUE"""),4.87138888888889) -> 4.8713889
A64: 49 | B64: Prescriptive Constructions | E64: 50 | F64: ARKIN HARDWARE | G64: 4.4714286 | I64: 52 | J64: Crosspoint Paper, Inc | M64: =IFERROR(__xludf.DUMMYFUNCTION("""COMPUTED_VALUE"""),"Sprintec Printing Press, Inc.") -> Sprintec Printing Press, Inc. | N64: =IFERROR(__xludf.DUMMYFUNCTION("""COMPUTED_VALUE"""),3.3333333333333335) -> 3.3333333 | O64: =IFERROR(__xludf.DUMMYFUNCTION("""COMPUTED_VALUE"""),44882.0) -> 44882 | Q64: =IFERROR(__xludf.DUMMYFUNCTION("""COMPUTED_VALUE"""),"Ronald Personalized Fashion Specialist") -> Ronald Personalized Fashion Specialist | R64: =IFERROR(__xludf.DUMMYFUNCTION("""COMPUTED_VALUE"""),4.0) -> 4 | S64: =IFERROR(__xludf.DUMMYFUNCTION("""COMPUTED_VALUE"""),45216.0) -> 45216 | U64: =IFERROR(__xludf.DUMMYFUNCTION("""COMPUTED_VALUE"""),"Rivchem Enterprises") -> Rivchem Enterprises | V64: =IFERROR(__xludf.DUMMYFUNCTION("""COMPUTED_VALUE"""),4.625) -> 4.625 | W64: =IFERROR(__xludf.DUMMYFUNCTION("""COMPUTED_VALUE"""),45558.0) -> 45558 | AB64: =IFERROR(__xludf.DUMMYFUNCTION("""COMPUTED_VALUE"""),"ULTRA PETRONNE INTERIOR SUPPLY CORPORATION") -> ULTRA PETRONNE INTERIOR SUPPLY CORPORATION | AC64: =IFERROR(__xludf.DUMMYFUNCTION("""COMPUTED_VALUE"""),4.5) -> 4.5 | AE64: =IFERROR(__xludf.DUMMYFUNCTION("""COMPUTED_VALUE"""),"RSAZ Corporation") -> RSAZ Corporation | AF64: =IFERROR(__xludf.DUMMYFUNCTION("""COMPUTED_VALUE"""),5.0) -> 5
A65: 50 | B65: Microlynx Systems Enterprises | E65: 51 | F65: ACE HARDWARE PHILIPPINES, INC. | I65: 53 | J65: One Supply | K65: 5 | M65: =IFERROR(__xludf.DUMMYFUNCTION("""COMPUTED_VALUE"""),"Columbia Technologies, Inc.") -> Columbia Technologies, Inc. | N65: =IFERROR(__xludf.DUMMYFUNCTION("""COMPUTED_VALUE"""),5.0) -> 5 | O65: =IFERROR(__xludf.DUMMYFUNCTION("""COMPUTED_VALUE"""),44883.0) -> 44883 | Q65: =IFERROR(__xludf.DUMMYFUNCTION("""COMPUTED_VALUE"""),"Crosspoint Paper, Inc.") -> Crosspoint Paper, Inc. | R65: =IFERROR(__xludf.DUMMYFUNCTION("""COMPUTED_VALUE"""),5.0) -> 5 | S65: =IFERROR(__xludf.DUMMYFUNCTION("""COMPUTED_VALUE"""),45217.0) -> 45217 | U65: =IFERROR(__xludf.DUMMYFUNCTION("""COMPUTED_VALUE"""),"Contrade Integrated Depot") -> Contrade Integrated Depot | V65: =IFERROR(__xludf.DUMMYFUNCTION("""COMPUTED_VALUE"""),4.833333333333333) -> 4.8333333 | W65: =IFERROR(__xludf.DUMMYFUNCTION("""COMPUTED_VALUE"""),45558.0) -> 45558 | AB65: =IFERROR(__xludf.DUMMYFUNCTION("""COMPUTED_VALUE"""),"V.M Industries Corp.") -> V.M Industries Corp. | AC65: =IFERROR(__xludf.DUMMYFUNCTION("""COMPUTED_VALUE"""),4.441666666666666) -> 4.4416667 | AE65: =IFERROR(__xludf.DUMMYFUNCTION("""COMPUTED_VALUE"""),"Rivchem Enterprises") -> Rivchem Enterprises | AF65: =IFERROR(__xludf.DUMMYFUNCTION("""COMPUTED_VALUE"""),4.758006535947713) -> 4.7580065
A66: 51 | B66: Roavsan General Merchandise | E66: 52 | F66: Jamex | I66: 54 | J66: Western Grand Central Co, Inc | M66: =IFERROR(__xludf.DUMMYFUNCTION("""COMPUTED_VALUE"""),"Microsmith Technology System,Inc.") -> Microsmith Technology System,Inc. | N66: =IFERROR(__xludf.DUMMYFUNCTION("""COMPUTED_VALUE"""),5.0) -> 5 | O66: =IFERROR(__xludf.DUMMYFUNCTION("""COMPUTED_VALUE"""),44883.0) -> 44883 | Q66: =IFERROR(__xludf.DUMMYFUNCTION("""COMPUTED_VALUE"""),"Jarm Printing Press") -> Jarm Printing Press | R66: =IFERROR(__xludf.DUMMYFUNCTION("""COMPUTED_VALUE"""),5.0) -> 5 | S66: =IFERROR(__xludf.DUMMYFUNCTION("""COMPUTED_VALUE"""),45217.0) -> 45217 | U66: =IFERROR(__xludf.DUMMYFUNCTION("""COMPUTED_VALUE"""),"Contrade Integrated Depot") -> Contrade Integrated Depot | V66: =IFERROR(__xludf.DUMMYFUNCTION("""COMPUTED_VALUE"""),4.833333333333333) -> 4.8333333 | W66: =IFERROR(__xludf.DUMMYFUNCTION("""COMPUTED_VALUE"""),45558.0) -> 45558 | AB66: =IFERROR(__xludf.DUMMYFUNCTION("""COMPUTED_VALUE"""),"Wisechoice Cleaning Supplies and Trading Corp.") -> Wisechoice Cleaning Supplies and Trading Corp. | AC66: =IFERROR(__xludf.DUMMYFUNCTION("""COMPUTED_VALUE"""),4.536111111111111) -> 4.5361111 | AE66: =IFERROR(__xludf.DUMMYFUNCTION("""COMPUTED_VALUE"""),"Roavsan General Merchandise") -> Roavsan General Merchandise | AF66: =IFERROR(__xludf.DUMMYFUNCTION("""COMPUTED_VALUE"""),4.758333333333334) -> 4.7583333
A67: 52 | B67: YKP General Merchandise | E67: 53 | F67: Prescriptive Constructions | I67: 55 | J67: ABENSON VENTURES INC., | K67: 4.9166667 | M67: =IFERROR(__xludf.DUMMYFUNCTION("""COMPUTED_VALUE"""),"Chemtrust Global Market, Inc.") -> Chemtrust Global Market, Inc. | N67: =IFERROR(__xludf.DUMMYFUNCTION("""COMPUTED_VALUE"""),4.533333333333333) -> 4.5333333 | O67: =IFERROR(__xludf.DUMMYFUNCTION("""COMPUTED_VALUE"""),44888.0) -> 44888 | Q67: =IFERROR(__xludf.DUMMYFUNCTION("""COMPUTED_VALUE"""),"Crosspoint Paper, Inc.") -> Crosspoint Paper, Inc. | R67: =IFERROR(__xludf.DUMMYFUNCTION("""COMPUTED_VALUE"""),5.0) -> 5 | S67: =IFERROR(__xludf.DUMMYFUNCTION("""COMPUTED_VALUE"""),45218.0) -> 45218 | U67: =IFERROR(__xludf.DUMMYFUNCTION("""COMPUTED_VALUE"""),"Contrade Integrated Depot") -> Contrade Integrated Depot | V67: =IFERROR(__xludf.DUMMYFUNCTION("""COMPUTED_VALUE"""),4.833333333333333) -> 4.8333333 | W67: =IFERROR(__xludf.DUMMYFUNCTION("""COMPUTED_VALUE"""),45558.0) -> 45558 | AB67: =IFERROR(__xludf.DUMMYFUNCTION("""COMPUTED_VALUE"""),"World Magazine Exchange Marketing Corp.") -> World Magazine Exchange Marketing Corp. | AC67: =IFERROR(__xludf.DUMMYFUNCTION("""COMPUTED_VALUE"""),4.733333333333333) -> 4.7333333 | AE67: =IFERROR(__xludf.DUMMYFUNCTION("""COMPUTED_VALUE"""),"Shelves and Cups Book Store") -> Shelves and Cups Book Store | AF67: =IFERROR(__xludf.DUMMYFUNCTION("""COMPUTED_VALUE"""),4.833333333333333) -> 4.8333333
A68: 53 | B68: Wilcon Depot Sucat | E68: 54 | F68: Microlynx Systems Enterprises | I68: 56 | J68: Times Trading, Inc | M68: =IFERROR(__xludf.DUMMYFUNCTION("""COMPUTED_VALUE"""),"Tropical Palms Fashion House, Inc.") -> Tropical Palms Fashion House, Inc. | N68: =IFERROR(__xludf.DUMMYFUNCTION("""COMPUTED_VALUE"""),5.0) -> 5 | O68: =IFERROR(__xludf.DUMMYFUNCTION("""COMPUTED_VALUE"""),44895.0) -> 44895 | Q68: =IFERROR(__xludf.DUMMYFUNCTION("""COMPUTED_VALUE"""),"Abacus Book & Card Corp.") -> Abacus Book & Card Corp. | R68: =IFERROR(__xludf.DUMMYFUNCTION("""COMPUTED_VALUE"""),5.0) -> 5 | S68: =IFERROR(__xludf.DUMMYFUNCTION("""COMPUTED_VALUE"""),45225.0) -> 45225 | U68: =IFERROR(__xludf.DUMMYFUNCTION("""COMPUTED_VALUE"""),"Contrade Integrated Depot") -> Contrade Integrated Depot | V68: =IFERROR(__xludf.DUMMYFUNCTION("""COMPUTED_VALUE"""),4.833333333333333) -> 4.8333333 | W68: =IFERROR(__xludf.DUMMYFUNCTION("""COMPUTED_VALUE"""),45558.0) -> 45558 | AB68: =IFERROR(__xludf.DUMMYFUNCTION("""COMPUTED_VALUE"""),"Zariah's Non-Specialized Wholesale Trading") -> Zariah's Non-Specialized Wholesale Trading | AC68: =IFERROR(__xludf.DUMMYFUNCTION("""COMPUTED_VALUE"""),4.791666666666667) -> 4.7916667 | AE68: =IFERROR(__xludf.DUMMYFUNCTION("""COMPUTED_VALUE"""),"Sprintec Printing Press, Inc.") -> Sprintec Printing Press, Inc. | AF68: =IFERROR(__xludf.DUMMYFUNCTION("""COMPUTED_VALUE"""),3.4166666666666665) -> 3.4166667
A69: 54 | B69: CW Marketing & Development Corporation | E69: 55 | F69: Roavsan General Merchandise | G69: 4 | I69: 57 | J69: EA Intertrade General Merchandising, Inc. | M69: =IFERROR(__xludf.DUMMYFUNCTION("""COMPUTED_VALUE"""),"Data Computer Forms, Inc.") -> Data Computer Forms, Inc. | N69: =IFERROR(__xludf.DUMMYFUNCTION("""COMPUTED_VALUE"""),4.966666666666667) -> 4.9666667 | O69: =IFERROR(__xludf.DUMMYFUNCTION("""COMPUTED_VALUE"""),44896.0) -> 44896 | Q69: =IFERROR(__xludf.DUMMYFUNCTION("""COMPUTED_VALUE"""),"Abacus Book & Card Corp.") -> Abacus Book & Card Corp. | R69: =IFERROR(__xludf.DUMMYFUNCTION("""COMPUTED_VALUE"""),5.0) -> 5 | S69: =IFERROR(__xludf.DUMMYFUNCTION("""COMPUTED_VALUE"""),45225.0) -> 45225 | U69: =IFERROR(__xludf.DUMMYFUNCTION("""COMPUTED_VALUE"""),"Contrade Integrated Depot") -> Contrade Integrated Depot | V69: =IFERROR(__xludf.DUMMYFUNCTION("""COMPUTED_VALUE"""),4.833333333333333) -> 4.8333333 | W69: =IFERROR(__xludf.DUMMYFUNCTION("""COMPUTED_VALUE"""),45558.0) -> 45558 | AE69: =IFERROR(__xludf.DUMMYFUNCTION("""COMPUTED_VALUE"""),"Tadeos Scientific Industries OPC") -> Tadeos Scientific Industries OPC | AF69: =IFERROR(__xludf.DUMMYFUNCTION("""COMPUTED_VALUE"""),4.0) -> 4
A70: 55 | B70: Majesty Builders & Electrical Supply | E70: 56 | F70: YKP General Merchandise | I70: 58 | J70: Print Depot Inc. | M70: =IFERROR(__xludf.DUMMYFUNCTION("""COMPUTED_VALUE"""),"DKL Laboratory Supplies") -> DKL Laboratory Supplies | N70: =IFERROR(__xludf.DUMMYFUNCTION("""COMPUTED_VALUE"""),3.8333333333333335) -> 3.8333333 | O70: =IFERROR(__xludf.DUMMYFUNCTION("""COMPUTED_VALUE"""),44909.0) -> 44909 | Q70: =IFERROR(__xludf.DUMMYFUNCTION("""COMPUTED_VALUE"""),"Contrade Integrated Depot") -> Contrade Integrated Depot | R70: =IFERROR(__xludf.DUMMYFUNCTION("""COMPUTED_VALUE"""),4.83) -> 4.83 | S70: =IFERROR(__xludf.DUMMYFUNCTION("""COMPUTED_VALUE"""),45226.0) -> 45226 | U70: =IFERROR(__xludf.DUMMYFUNCTION("""COMPUTED_VALUE"""),"Contrade Integrated Depot") -> Contrade Integrated Depot | V70: =IFERROR(__xludf.DUMMYFUNCTION("""COMPUTED_VALUE"""),4.75) -> 4.75 | W70: =IFERROR(__xludf.DUMMYFUNCTION("""COMPUTED_VALUE"""),45558.0) -> 45558 | AE70: =IFERROR(__xludf.DUMMYFUNCTION("""COMPUTED_VALUE"""),"Times Trading Co., Inc.") -> Times Trading Co., Inc. | AF70: =IFERROR(__xludf.DUMMYFUNCTION("""COMPUTED_VALUE"""),4.929166666666666) -> 4.9291667
A71: 56 | B71: Megabuilders & Building Care Services | E71: 57 | F71: Wilcon Depot Sucat | I71: 59 | J71: Cosmotech Philippines, Inc. | M71: =IFERROR(__xludf.DUMMYFUNCTION("""COMPUTED_VALUE"""),"Ahrcel's Gift Shop") -> Ahrcel's Gift Shop | N71: =IFERROR(__xludf.DUMMYFUNCTION("""COMPUTED_VALUE"""),5.0) -> 5 | O71: =IFERROR(__xludf.DUMMYFUNCTION("""COMPUTED_VALUE"""),44915.0) -> 44915 | Q71: =IFERROR(__xludf.DUMMYFUNCTION("""COMPUTED_VALUE"""),"Creative Juice Digital Printing") -> Creative Juice Digital Printing | R71: =IFERROR(__xludf.DUMMYFUNCTION("""COMPUTED_VALUE"""),4.0) -> 4 | S71: =IFERROR(__xludf.DUMMYFUNCTION("""COMPUTED_VALUE"""),45226.0) -> 45226 | U71: =IFERROR(__xludf.DUMMYFUNCTION("""COMPUTED_VALUE"""),"Contrade Integrated Depot") -> Contrade Integrated Depot | V71: =IFERROR(__xludf.DUMMYFUNCTION("""COMPUTED_VALUE"""),4.666666666666667) -> 4.6666667 | W71: =IFERROR(__xludf.DUMMYFUNCTION("""COMPUTED_VALUE"""),45558.0) -> 45558 | AE71: =IFERROR(__xludf.DUMMYFUNCTION("""COMPUTED_VALUE"""),"Trojan Computer Forms Mfg. Corp.") -> Trojan Computer Forms Mfg. Corp. | AF71: =IFERROR(__xludf.DUMMYFUNCTION("""COMPUTED_VALUE"""),5.0) -> 5
A72: 57 | B72: Polaris Integrated Industries, Inc. | E72: 58 | F72: CW Marketing & Development Corporation | I72: Printing and Publication | K72: =average(K73:K82) -> 4.5304762 | M72: =IFERROR(__xludf.DUMMYFUNCTION("""COMPUTED_VALUE"""),"Brown Movement for Cultural Advancement, Inc.") -> Brown Movement for Cultural Advancement, Inc. | N72: =IFERROR(__xludf.DUMMYFUNCTION("""COMPUTED_VALUE"""),5.0) -> 5 | O72: =IFERROR(__xludf.DUMMYFUNCTION("""COMPUTED_VALUE"""),44915.0) -> 44915 | Q72: =IFERROR(__xludf.DUMMYFUNCTION("""COMPUTED_VALUE"""),"Times Trading Co., Inc.") -> Times Trading Co., Inc. | R72: =IFERROR(__xludf.DUMMYFUNCTION("""COMPUTED_VALUE"""),5.0) -> 5 | S72: =IFERROR(__xludf.DUMMYFUNCTION("""COMPUTED_VALUE"""),45227.0) -> 45227 | U72: =IFERROR(__xludf.DUMMYFUNCTION("""COMPUTED_VALUE"""),"Rivchem Enterprises") -> Rivchem Enterprises | V72: =IFERROR(__xludf.DUMMYFUNCTION("""COMPUTED_VALUE"""),4.791666666666667) -> 4.7916667 | W72: =IFERROR(__xludf.DUMMYFUNCTION("""COMPUTED_VALUE"""),45558.0) -> 45558 | AE72: =IFERROR(__xludf.DUMMYFUNCTION("""COMPUTED_VALUE"""),"Tropical Palms Fashion House, Inc.") -> Tropical Palms Fashion House, Inc. | AF72: =IFERROR(__xludf.DUMMYFUNCTION("""COMPUTED_VALUE"""),5.0) -> 5
A73: 58 | B73: POLARIS PRIME AIR TECH CORPORATION | E73: 59 | F73: Majesty Builders & Electrical Supply | I73: 60 | J73: 17th Street Maxiprint Co. | M73: =IFERROR(__xludf.DUMMYFUNCTION("""COMPUTED_VALUE"""),"Contrade Integrated Depot") -> Contrade Integrated Depot | N73: =IFERROR(__xludf.DUMMYFUNCTION("""COMPUTED_VALUE"""),4.95) -> 4.95 | O73: =IFERROR(__xludf.DUMMYFUNCTION("""COMPUTED_VALUE"""),44915.0) -> 44915 | Q73: =IFERROR(__xludf.DUMMYFUNCTION("""COMPUTED_VALUE"""),"Contrade Integrated Depot") -> Contrade Integrated Depot | R73: =IFERROR(__xludf.DUMMYFUNCTION("""COMPUTED_VALUE"""),4.83) -> 4.83 | S73: =IFERROR(__xludf.DUMMYFUNCTION("""COMPUTED_VALUE"""),45230.0) -> 45230 | U73: =IFERROR(__xludf.DUMMYFUNCTION("""COMPUTED_VALUE"""),"Rivchem Enterprises") -> Rivchem Enterprises | V73: =IFERROR(__xludf.DUMMYFUNCTION("""COMPUTED_VALUE"""),4.791666666666667) -> 4.7916667 | W73: =IFERROR(__xludf.DUMMYFUNCTION("""COMPUTED_VALUE"""),45558.0) -> 45558 | AE73: =IFERROR(__xludf.DUMMYFUNCTION("""COMPUTED_VALUE"""),"V.M Industries Corp.") -> V.M Industries Corp. | AF73: =IFERROR(__xludf.DUMMYFUNCTION("""COMPUTED_VALUE"""),4.645833333333334) -> 4.6458333
A74: 59 | B74: Non-Residential Building Construction Lucky Construction | E74: 60 | F74: Megabuilders & Building Care Services | I74: 61 | J74: Luminaire Printing and Publishing Corp | K74: 4.7857143 | M74: =IFERROR(__xludf.DUMMYFUNCTION("""COMPUTED_VALUE"""),"Contrade Integrated Depot") -> Contrade Integrated Depot | N74: =IFERROR(__xludf.DUMMYFUNCTION("""COMPUTED_VALUE"""),5.0) -> 5 | O74: =IFERROR(__xludf.DUMMYFUNCTION("""COMPUTED_VALUE"""),44915.0) -> 44915 | Q74: =IFERROR(__xludf.DUMMYFUNCTION("""COMPUTED_VALUE"""),"Contrade Integrated Depot") -> Contrade Integrated Depot | R74: =IFERROR(__xludf.DUMMYFUNCTION("""COMPUTED_VALUE"""),4.83) -> 4.83 | S74: =IFERROR(__xludf.DUMMYFUNCTION("""COMPUTED_VALUE"""),45230.0) -> 45230 | U74: =IFERROR(__xludf.DUMMYFUNCTION("""COMPUTED_VALUE"""),"Chemtrust Global Market, Inc.") -> Chemtrust Global Market, Inc. | V74: =IFERROR(__xludf.DUMMYFUNCTION("""COMPUTED_VALUE"""),4.791666666666667) -> 4.7916667 | W74: =IFERROR(__xludf.DUMMYFUNCTION("""COMPUTED_VALUE"""),45558.0) -> 45558 | AE74: =IFERROR(__xludf.DUMMYFUNCTION("""COMPUTED_VALUE"""),"Velca Equipment And Engineered ") -> Velca Equipment And Engineered | AF74: =IFERROR(__xludf.DUMMYFUNCTION("""COMPUTED_VALUE"""),4.0) -> 4
A75: 60 | B75: Cesar T. Bandoy Construction Services | E75: 61 | F75: Polaris Integrated Industries, Inc. | I75: 62 | J75: Leonard Prints Inc | K75: 4.8166667 | M75: =IFERROR(__xludf.DUMMYFUNCTION("""COMPUTED_VALUE"""),"Contrade Integrated Depot") -> Contrade Integrated Depot | N75: =IFERROR(__xludf.DUMMYFUNCTION("""COMPUTED_VALUE"""),4.966666666666667) -> 4.9666667 | O75: =IFERROR(__xludf.DUMMYFUNCTION("""COMPUTED_VALUE"""),44915.0) -> 44915 | Q75: =IFERROR(__xludf.DUMMYFUNCTION("""COMPUTED_VALUE"""),"Leonard Prints Inc.") -> Leonard Prints Inc. | R75: =IFERROR(__xludf.DUMMYFUNCTION("""COMPUTED_VALUE"""),4.916666666666667) -> 4.9166667 | S75: =IFERROR(__xludf.DUMMYFUNCTION("""COMPUTED_VALUE"""),45230.0) -> 45230 | U75: =IFERROR(__xludf.DUMMYFUNCTION("""COMPUTED_VALUE"""),"Chemtrust Global Market, Inc.") -> Chemtrust Global Market, Inc. | V75: =IFERROR(__xludf.DUMMYFUNCTION("""COMPUTED_VALUE"""),4.791666666666667) -> 4.7916667 | W75: =IFERROR(__xludf.DUMMYFUNCTION("""COMPUTED_VALUE"""),45558.0) -> 45558 | AE75: =IFERROR(__xludf.DUMMYFUNCTION("""COMPUTED_VALUE"""),"Wilcon Depot Inc.") -> Wilcon Depot Inc. | AF75: =IFERROR(__xludf.DUMMYFUNCTION("""COMPUTED_VALUE"""),4.486111111111111) -> 4.4861111
A76: 61 | B76: Becabs Electrical Engineering Services | E76: 62 | F76: POLARIS PRIME AIR TECH CORPORATION | G76: 4.6666667 | I76: 63 | J76: Jarm Printing Press | K76: 4.75 | M76: =IFERROR(__xludf.DUMMYFUNCTION("""COMPUTED_VALUE"""),"Contrade Integrated Depot") -> Contrade Integrated Depot | N76: =IFERROR(__xludf.DUMMYFUNCTION("""COMPUTED_VALUE"""),4.883333333333334) -> 4.8833333 | O76: =IFERROR(__xludf.DUMMYFUNCTION("""COMPUTED_VALUE"""),44915.0) -> 44915 | Q76: =IFERROR(__xludf.DUMMYFUNCTION("""COMPUTED_VALUE"""),"Rivchem Enterprises") -> Rivchem Enterprises | R76: =IFERROR(__xludf.DUMMYFUNCTION("""COMPUTED_VALUE"""),4.333333333333333) -> 4.3333333 | S76: =IFERROR(__xludf.DUMMYFUNCTION("""COMPUTED_VALUE"""),45230.0) -> 45230 | U76: =IFERROR(__xludf.DUMMYFUNCTION("""COMPUTED_VALUE"""),"Rivchem Enterprises") -> Rivchem Enterprises | V76: =IFERROR(__xludf.DUMMYFUNCTION("""COMPUTED_VALUE"""),4.791666666666667) -> 4.7916667 | W76: =IFERROR(__xludf.DUMMYFUNCTION("""COMPUTED_VALUE"""),45559.0) -> 45559 | AE76: =IFERROR(__xludf.DUMMYFUNCTION("""COMPUTED_VALUE"""),"Wisechoice Cleaning Supplies and Trading Corp.") -> Wisechoice Cleaning Supplies and Trading Corp. | AF76: =IFERROR(__xludf.DUMMYFUNCTION("""COMPUTED_VALUE"""),4.708333333333333) -> 4.7083333
A77: 62 | B77: Takumina | E77: 63 | F77: Non-Residential Building Construction Lucky Construction | I77: 64 | J77: Prettie Prints Graphic Arts | M77: =IFERROR(__xludf.DUMMYFUNCTION("""COMPUTED_VALUE"""),"Creative Juice Digital Printing") -> Creative Juice Digital Printing | N77: =IFERROR(__xludf.DUMMYFUNCTION("""COMPUTED_VALUE"""),5.0) -> 5 | O77: =IFERROR(__xludf.DUMMYFUNCTION("""COMPUTED_VALUE"""),44915.0) -> 44915 | Q77: =IFERROR(__xludf.DUMMYFUNCTION("""COMPUTED_VALUE"""),"Falcon Waterfree Philippines, Inc.") -> Falcon Waterfree Philippines, Inc. | R77: =IFERROR(__xludf.DUMMYFUNCTION("""COMPUTED_VALUE"""),4.333333333333333) -> 4.3333333 | S77: =IFERROR(__xludf.DUMMYFUNCTION("""COMPUTED_VALUE"""),45233.0) -> 45233 | U77: =IFERROR(__xludf.DUMMYFUNCTION("""COMPUTED_VALUE"""),"Rivchem Enterprises") -> Rivchem Enterprises | V77: =IFERROR(__xludf.DUMMYFUNCTION("""COMPUTED_VALUE"""),4.791666666666667) -> 4.7916667 | W77: =IFERROR(__xludf.DUMMYFUNCTION("""COMPUTED_VALUE"""),45559.0) -> 45559 | AE77: =IFERROR(__xludf.DUMMYFUNCTION("""COMPUTED_VALUE"""),"Zariah's Non-Specialized Wholesale Trading") -> Zariah's Non-Specialized Wholesale Trading | AF77: =IFERROR(__xludf.DUMMYFUNCTION("""COMPUTED_VALUE"""),5.0) -> 5
A78: Outsource Services | C78: =average(C79:C85) -> 5 | E78: 64 | F78: Cesar T. Bandoy Construction Services | I78: 65 | J78: ADVANCE COMPUTER FORMS | M78: =IFERROR(__xludf.DUMMYFUNCTION("""COMPUTED_VALUE"""),"Creative Juice Digital Printing") -> Creative Juice Digital Printing | N78: =IFERROR(__xludf.DUMMYFUNCTION("""COMPUTED_VALUE"""),5.0) -> 5 | O78: =IFERROR(__xludf.DUMMYFUNCTION("""COMPUTED_VALUE"""),44915.0) -> 44915 | Q78: =IFERROR(__xludf.DUMMYFUNCTION("""COMPUTED_VALUE"""),"Rivchem Enterprises") -> Rivchem Enterprises | R78: =IFERROR(__xludf.DUMMYFUNCTION("""COMPUTED_VALUE"""),4.258333333333334) -> 4.2583333 | S78: =IFERROR(__xludf.DUMMYFUNCTION("""COMPUTED_VALUE"""),45233.0) -> 45233 | U78: =IFERROR(__xludf.DUMMYFUNCTION("""COMPUTED_VALUE"""),"Rivchem Enterprises") -> Rivchem Enterprises | V78: =IFERROR(__xludf.DUMMYFUNCTION("""COMPUTED_VALUE"""),4.791666666666667) -> 4.7916667 | W78: =IFERROR(__xludf.DUMMYFUNCTION("""COMPUTED_VALUE"""),45559.0) -> 45559 | AE78: =IFERROR(__xludf.DUMMYFUNCTION("""COMPUTED_VALUE"""),"iEquity Technologies Corp.") -> iEquity Technologies Corp. | AF78: =IFERROR(__xludf.DUMMYFUNCTION("""COMPUTED_VALUE"""),4.958333333333334) -> 4.9583333
A79: 63 | B79: Maximum Security and Services Corp | E79: 65 | F79: Becabs Electrical Engineering Services | I79: 66 | J79: Data Computer Forms, Inc. | K79: 4.9666667 | M79: =IFERROR(__xludf.DUMMYFUNCTION("""COMPUTED_VALUE"""),"EIG Metal Engravers") -> EIG Metal Engravers | N79: =IFERROR(__xludf.DUMMYFUNCTION("""COMPUTED_VALUE"""),5.0) -> 5 | O79: =IFERROR(__xludf.DUMMYFUNCTION("""COMPUTED_VALUE"""),44915.0) -> 44915 | Q79: =IFERROR(__xludf.DUMMYFUNCTION("""COMPUTED_VALUE"""),"Rivchem Enterprises") -> Rivchem Enterprises | R79: =IFERROR(__xludf.DUMMYFUNCTION("""COMPUTED_VALUE"""),4.258333333333334) -> 4.2583333 | S79: =IFERROR(__xludf.DUMMYFUNCTION("""COMPUTED_VALUE"""),45233.0) -> 45233 | U79: =IFERROR(__xludf.DUMMYFUNCTION("""COMPUTED_VALUE"""),"Rivchem Enterprises") -> Rivchem Enterprises | V79: =IFERROR(__xludf.DUMMYFUNCTION("""COMPUTED_VALUE"""),4.791666666666667) -> 4.7916667 | W79: =IFERROR(__xludf.DUMMYFUNCTION("""COMPUTED_VALUE"""),45559.0) -> 45559
A80: 64 | B80: Altaserv Inc. | E80: 66 | F80: Takumina | I80: 67 | J80: SPRINTEC PRINTING PRESS, INC. | K80: 3.3333333 | M80: =IFERROR(__xludf.DUMMYFUNCTION("""COMPUTED_VALUE"""),"Luminaire Printing And Publishing Corp.") -> Luminaire Printing And Publishing Corp. | N80: =IFERROR(__xludf.DUMMYFUNCTION("""COMPUTED_VALUE"""),5.0) -> 5 | O80: =IFERROR(__xludf.DUMMYFUNCTION("""COMPUTED_VALUE"""),44915.0) -> 44915 | Q80: =IFERROR(__xludf.DUMMYFUNCTION("""COMPUTED_VALUE"""),"Rivchem Enterprises") -> Rivchem Enterprises | R80: =IFERROR(__xludf.DUMMYFUNCTION("""COMPUTED_VALUE"""),4.333333333333333) -> 4.3333333 | S80: =IFERROR(__xludf.DUMMYFUNCTION("""COMPUTED_VALUE"""),45233.0) -> 45233 | U80: =IFERROR(__xludf.DUMMYFUNCTION("""COMPUTED_VALUE"""),"Rivchem Enterprises") -> Rivchem Enterprises | V80: =IFERROR(__xludf.DUMMYFUNCTION("""COMPUTED_VALUE"""),4.791666666666667) -> 4.7916667 | W80: =IFERROR(__xludf.DUMMYFUNCTION("""COMPUTED_VALUE"""),45559.0) -> 45559
A81: 65 | B81: Oray Copier Solutions | C81: 5 | E81: Outsource Services | G81: =average(G82:G87) -> 4.67 | I81: 68 | J81: Trojan Computer Forms Mfg. Corp. | M81: =IFERROR(__xludf.DUMMYFUNCTION("""COMPUTED_VALUE"""),"Luminaire Printing And Publishing Corp.") -> Luminaire Printing And Publishing Corp. | N81: =IFERROR(__xludf.DUMMYFUNCTION("""COMPUTED_VALUE"""),5.0) -> 5 | O81: =IFERROR(__xludf.DUMMYFUNCTION("""COMPUTED_VALUE"""),44915.0) -> 44915 | Q81: =IFERROR(__xludf.DUMMYFUNCTION("""COMPUTED_VALUE"""),"Beyond Global Multiales Corp.") -> Beyond Global Multiales Corp. | R81: =IFERROR(__xludf.DUMMYFUNCTION("""COMPUTED_VALUE"""),4.833333333333333) -> 4.8333333 | S81: =IFERROR(__xludf.DUMMYFUNCTION("""COMPUTED_VALUE"""),45233.0) -> 45233 | U81: =IFERROR(__xludf.DUMMYFUNCTION("""COMPUTED_VALUE"""),"Rivchem Enterprises") -> Rivchem Enterprises | V81: =IFERROR(__xludf.DUMMYFUNCTION("""COMPUTED_VALUE"""),4.791666666666667) -> 4.7916667 | W81: =IFERROR(__xludf.DUMMYFUNCTION("""COMPUTED_VALUE"""),45559.0) -> 45559
A82: 66 | B82: Inkonvert Enterprise | E82: 67 | F82: Maximum Security and Services Corp | I82: 69 | J82: M-PLUS PRINTGRAPHICS | M82: =IFERROR(__xludf.DUMMYFUNCTION("""COMPUTED_VALUE"""),"Luminaire Printing And Publishing Corp.") -> Luminaire Printing And Publishing Corp. | N82: =IFERROR(__xludf.DUMMYFUNCTION("""COMPUTED_VALUE"""),4.833333333333333) -> 4.8333333 | O82: =IFERROR(__xludf.DUMMYFUNCTION("""COMPUTED_VALUE"""),44915.0) -> 44915 | Q82: =IFERROR(__xludf.DUMMYFUNCTION("""COMPUTED_VALUE"""),"Columbia Technologies, Inc.") -> Columbia Technologies, Inc. | R82: =IFERROR(__xludf.DUMMYFUNCTION("""COMPUTED_VALUE"""),4.0) -> 4 | S82: =IFERROR(__xludf.DUMMYFUNCTION("""COMPUTED_VALUE"""),45237.0) -> 45237 | U82: =IFERROR(__xludf.DUMMYFUNCTION("""COMPUTED_VALUE"""),"Printing Shop PrintPilipinas.com") -> Printing Shop PrintPilipinas.com | V82: =IFERROR(__xludf.DUMMYFUNCTION("""COMPUTED_VALUE"""),4.833333333333333) -> 4.8333333 | W82: =IFERROR(__xludf.DUMMYFUNCTION("""COMPUTED_VALUE"""),45561.0) -> 45561
A83: 67 | B83: GBert Pest Control | E83: 68 | F83: Altaserv Inc. | I83: Laboratory Supplies & Equipment | K83: =average(K84:K89) -> #DIV/0! | M83: =IFERROR(__xludf.DUMMYFUNCTION("""COMPUTED_VALUE"""),"Microsmith Technology System,Inc.") -> Microsmith Technology System,Inc. | N83: =IFERROR(__xludf.DUMMYFUNCTION("""COMPUTED_VALUE"""),5.0) -> 5 | O83: =IFERROR(__xludf.DUMMYFUNCTION("""COMPUTED_VALUE"""),44915.0) -> 44915 | Q83: =IFERROR(__xludf.DUMMYFUNCTION("""COMPUTED_VALUE"""),"Polaris Prime Air Tech Corporation") -> Polaris Prime Air Tech Corporation | R83: =IFERROR(__xludf.DUMMYFUNCTION("""COMPUTED_VALUE"""),5.0) -> 5 | S83: =IFERROR(__xludf.DUMMYFUNCTION("""COMPUTED_VALUE"""),45242.0) -> 45242 | U83: =IFERROR(__xludf.DUMMYFUNCTION("""COMPUTED_VALUE"""),"Contrade Integrated Depot") -> Contrade Integrated Depot | V83: =IFERROR(__xludf.DUMMYFUNCTION("""COMPUTED_VALUE"""),4.666666666666667) -> 4.6666667 | W83: =IFERROR(__xludf.DUMMYFUNCTION("""COMPUTED_VALUE"""),45561.0) -> 45561
A84: 68 | B84: Klad Sanitation Services | E84: 69 | F84: Oray Copier Solutions | G84: 4.67 | I84: 70 | J84: ANESCHEM TECHNOLOGIES, INC. | M84: =IFERROR(__xludf.DUMMYFUNCTION("""COMPUTED_VALUE"""),"One Supply") -> One Supply | N84: =IFERROR(__xludf.DUMMYFUNCTION("""COMPUTED_VALUE"""),5.0) -> 5 | O84: =IFERROR(__xludf.DUMMYFUNCTION("""COMPUTED_VALUE"""),44915.0) -> 44915 | Q84: =IFERROR(__xludf.DUMMYFUNCTION("""COMPUTED_VALUE"""),"Abacus Book & Card Corp.") -> Abacus Book & Card Corp. | R84: =IFERROR(__xludf.DUMMYFUNCTION("""COMPUTED_VALUE"""),5.0) -> 5 | S84: =IFERROR(__xludf.DUMMYFUNCTION("""COMPUTED_VALUE"""),45247.0) -> 45247 | U84: =IFERROR(__xludf.DUMMYFUNCTION("""COMPUTED_VALUE"""),"Printing Shop PrintPilipinas.com") -> Printing Shop PrintPilipinas.com | V84: =IFERROR(__xludf.DUMMYFUNCTION("""COMPUTED_VALUE"""),4.833333333333333) -> 4.8333333 | W84: =IFERROR(__xludf.DUMMYFUNCTION("""COMPUTED_VALUE"""),45561.0) -> 45561
A85: 69 | B85: Jmarsean junkshop | E85: 70 | F85: Inkonvert Enterprise | I85: 71 | J85: Paddington Trading | M85: =IFERROR(__xludf.DUMMYFUNCTION("""COMPUTED_VALUE"""),"Polaris Integrated Industries, Inc.") -> Polaris Integrated Industries, Inc. | N85: =IFERROR(__xludf.DUMMYFUNCTION("""COMPUTED_VALUE"""),4.991666666666666) -> 4.9916667 | O85: =IFERROR(__xludf.DUMMYFUNCTION("""COMPUTED_VALUE"""),44915.0) -> 44915 | Q85: =IFERROR(__xludf.DUMMYFUNCTION("""COMPUTED_VALUE"""),"Creative Juice Digital Printing") -> Creative Juice Digital Printing | R85: =IFERROR(__xludf.DUMMYFUNCTION("""COMPUTED_VALUE"""),4.0) -> 4 | S85: =IFERROR(__xludf.DUMMYFUNCTION("""COMPUTED_VALUE"""),45248.0) -> 45248 | U85: =IFERROR(__xludf.DUMMYFUNCTION("""COMPUTED_VALUE"""),"Microsmith Technology System,Inc.") -> Microsmith Technology System,Inc. | V85: =IFERROR(__xludf.DUMMYFUNCTION("""COMPUTED_VALUE"""),4.833333333333333) -> 4.8333333 | W85: =IFERROR(__xludf.DUMMYFUNCTION("""COMPUTED_VALUE"""),45562.0) -> 45562
A86: Sports Supplies & Equipment | C86: =average(C87) -> 4.8333333 | E86: 71 | F86: GBert Pest Control | I86: 72 | J86: Tadeo's Marketing | M86: =IFERROR(__xludf.DUMMYFUNCTION("""COMPUTED_VALUE"""),"Polaris Prime Air Tech Corporation") -> Polaris Prime Air Tech Corporation | N86: =IFERROR(__xludf.DUMMYFUNCTION("""COMPUTED_VALUE"""),5.0) -> 5 | O86: =IFERROR(__xludf.DUMMYFUNCTION("""COMPUTED_VALUE"""),44915.0) -> 44915 | Q86: =IFERROR(__xludf.DUMMYFUNCTION("""COMPUTED_VALUE"""),"Printing Shop PrintPilipinas.com") -> Printing Shop PrintPilipinas.com | R86: =IFERROR(__xludf.DUMMYFUNCTION("""COMPUTED_VALUE"""),4.93) -> 4.93 | S86: =IFERROR(__xludf.DUMMYFUNCTION("""COMPUTED_VALUE"""),45248.0) -> 45248 | U86: =IFERROR(__xludf.DUMMYFUNCTION("""COMPUTED_VALUE"""),"Contrade Integrated Depot") -> Contrade Integrated Depot | V86: =IFERROR(__xludf.DUMMYFUNCTION("""COMPUTED_VALUE"""),4.833333333333333) -> 4.8333333 | W86: =IFERROR(__xludf.DUMMYFUNCTION("""COMPUTED_VALUE"""),45562.0) -> 45562
A87: 70 | B87: Bobman Trading | C87: 4.8333333 | E87: 72 | F87: Klad Sanitation Services | I87: 73 | J87: Oxychem Corporation | M87: =IFERROR(__xludf.DUMMYFUNCTION("""COMPUTED_VALUE"""),"Rivchem Enterprises") -> Rivchem Enterprises | N87: =IFERROR(__xludf.DUMMYFUNCTION("""COMPUTED_VALUE"""),5.0) -> 5 | O87: =IFERROR(__xludf.DUMMYFUNCTION("""COMPUTED_VALUE"""),44915.0) -> 44915 | Q87: =IFERROR(__xludf.DUMMYFUNCTION("""COMPUTED_VALUE"""),"Rivchem Enterprises") -> Rivchem Enterprises | R87: =IFERROR(__xludf.DUMMYFUNCTION("""COMPUTED_VALUE"""),4.333333333333333) -> 4.3333333 | S87: =IFERROR(__xludf.DUMMYFUNCTION("""COMPUTED_VALUE"""),45252.0) -> 45252 | U87: =IFERROR(__xludf.DUMMYFUNCTION("""COMPUTED_VALUE"""),"Litera Trading Inc.") -> Litera Trading Inc. | V87: =IFERROR(__xludf.DUMMYFUNCTION("""COMPUTED_VALUE"""),4.833333333333333) -> 4.8333333 | W87: =IFERROR(__xludf.DUMMYFUNCTION("""COMPUTED_VALUE"""),45565.0) -> 45565
I88: 74 | J88: Yana Chemodities, Inc. | M88: =IFERROR(__xludf.DUMMYFUNCTION("""COMPUTED_VALUE"""),"Sert Technology Inc.") -> Sert Technology Inc. | N88: =IFERROR(__xludf.DUMMYFUNCTION("""COMPUTED_VALUE"""),5.0) -> 5 | O88: =IFERROR(__xludf.DUMMYFUNCTION("""COMPUTED_VALUE"""),44915.0) -> 44915 | Q88: =IFERROR(__xludf.DUMMYFUNCTION("""COMPUTED_VALUE"""),"Data Computer Forms, Inc.") -> Data Computer Forms, Inc. | R88: =IFERROR(__xludf.DUMMYFUNCTION("""COMPUTED_VALUE"""),4.0) -> 4 | S88: =IFERROR(__xludf.DUMMYFUNCTION("""COMPUTED_VALUE"""),45254.0) -> 45254 | U88: =IFERROR(__xludf.DUMMYFUNCTION("""COMPUTED_VALUE"""),"Alpha Steel Office and Home Furnishing Company") -> Alpha Steel Office and Home Furnishing Company | V88: =IFERROR(__xludf.DUMMYFUNCTION("""COMPUTED_VALUE"""),4.833333333333333) -> 4.8333333 | W88: =IFERROR(__xludf.DUMMYFUNCTION("""COMPUTED_VALUE"""),45566.0) -> 45566
I89: 75 | J89: Premier Physic Metrologie | M89: =IFERROR(__xludf.DUMMYFUNCTION("""COMPUTED_VALUE"""),"Tropical Palms Fashion House, Inc.") -> Tropical Palms Fashion House, Inc. | N89: =IFERROR(__xludf.DUMMYFUNCTION("""COMPUTED_VALUE"""),5.0) -> 5 | O89: =IFERROR(__xludf.DUMMYFUNCTION("""COMPUTED_VALUE"""),44915.0) -> 44915 | Q89: =IFERROR(__xludf.DUMMYFUNCTION("""COMPUTED_VALUE"""),"Contrade Integrated Depot") -> Contrade Integrated Depot | R89: =IFERROR(__xludf.DUMMYFUNCTION("""COMPUTED_VALUE"""),4.83) -> 4.83 | S89: =IFERROR(__xludf.DUMMYFUNCTION("""COMPUTED_VALUE"""),45255.0) -> 45255 | U89: =IFERROR(__xludf.DUMMYFUNCTION("""COMPUTED_VALUE"""),"Primeline Products Philippines, Inc.") -> Primeline Products Philippines, Inc. | V89: =IFERROR(__xludf.DUMMYFUNCTION("""COMPUTED_VALUE"""),4.666666666666667) -> 4.6666667 | W89: =IFERROR(__xludf.DUMMYFUNCTION("""COMPUTED_VALUE"""),45566.0) -> 45566
I90: Personalized Materials | K90: =average(K91:K97) -> 4.7333333 | M90: =IFERROR(__xludf.DUMMYFUNCTION("""COMPUTED_VALUE"""),"Tropical Palms Fashion House, Inc.") -> Tropical Palms Fashion House, Inc. | N90: =IFERROR(__xludf.DUMMYFUNCTION("""COMPUTED_VALUE"""),5.0) -> 5 | O90: =IFERROR(__xludf.DUMMYFUNCTION("""COMPUTED_VALUE"""),44915.0) -> 44915 | Q90: =IFERROR(__xludf.DUMMYFUNCTION("""COMPUTED_VALUE"""),"Contrade Integrated Depot") -> Contrade Integrated Depot | R90: =IFERROR(__xludf.DUMMYFUNCTION("""COMPUTED_VALUE"""),4.83) -> 4.83 | S90: =IFERROR(__xludf.DUMMYFUNCTION("""COMPUTED_VALUE"""),45255.0) -> 45255 | U90: =IFERROR(__xludf.DUMMYFUNCTION("""COMPUTED_VALUE"""),"Leonard Prints Inc.") -> Leonard Prints Inc. | V90: =IFERROR(__xludf.DUMMYFUNCTION("""COMPUTED_VALUE"""),4.508333333333333) -> 4.5083333 | W90: =IFERROR(__xludf.DUMMYFUNCTION("""COMPUTED_VALUE"""),45568.0) -> 45568
I91: 76 | J91: Ahrcel's Gift Shop | K91: 5 | M91: =IFERROR(__xludf.DUMMYFUNCTION("""COMPUTED_VALUE"""),"Falcon Waterfree Philippines, Inc.") -> Falcon Waterfree Philippines, Inc. | N91: =IFERROR(__xludf.DUMMYFUNCTION("""COMPUTED_VALUE"""),5.0) -> 5 | O91: =IFERROR(__xludf.DUMMYFUNCTION("""COMPUTED_VALUE"""),44922.0) -> 44922 | Q91: =IFERROR(__xludf.DUMMYFUNCTION("""COMPUTED_VALUE"""),"Contrade Integrated Depot") -> Contrade Integrated Depot | R91: =IFERROR(__xludf.DUMMYFUNCTION("""COMPUTED_VALUE"""),4.83) -> 4.83 | S91: =IFERROR(__xludf.DUMMYFUNCTION("""COMPUTED_VALUE"""),45255.0) -> 45255 | U91: =IFERROR(__xludf.DUMMYFUNCTION("""COMPUTED_VALUE"""),"Contrade Integrated Depot") -> Contrade Integrated Depot | V91: =IFERROR(__xludf.DUMMYFUNCTION("""COMPUTED_VALUE"""),4.833333333333333) -> 4.8333333 | W91: =IFERROR(__xludf.DUMMYFUNCTION("""COMPUTED_VALUE"""),45568.0) -> 45568
I92: 77 | J92: Atlas Super Flags | K92: 4.7666667 | M92: =IFERROR(__xludf.DUMMYFUNCTION("""COMPUTED_VALUE"""),"Creative Juice Digital Printing") -> Creative Juice Digital Printing | N92: =IFERROR(__xludf.DUMMYFUNCTION("""COMPUTED_VALUE"""),5.0) -> 5 | O92: =IFERROR(__xludf.DUMMYFUNCTION("""COMPUTED_VALUE"""),44949.0) -> 44949 | Q92: =IFERROR(__xludf.DUMMYFUNCTION("""COMPUTED_VALUE"""),"Polaris Prime Air Tech Corporation") -> Polaris Prime Air Tech Corporation | R92: =IFERROR(__xludf.DUMMYFUNCTION("""COMPUTED_VALUE"""),5.0) -> 5 | S92: =IFERROR(__xludf.DUMMYFUNCTION("""COMPUTED_VALUE"""),45257.0) -> 45257 | U92: =IFERROR(__xludf.DUMMYFUNCTION("""COMPUTED_VALUE"""),"Rivchem Enterprises") -> Rivchem Enterprises | V92: =IFERROR(__xludf.DUMMYFUNCTION("""COMPUTED_VALUE"""),4.791666666666667) -> 4.7916667 | W92: =IFERROR(__xludf.DUMMYFUNCTION("""COMPUTED_VALUE"""),45568.0) -> 45568
I93: 78 | J93: EIG Metal Engravers | K93: 4.5 | M93: =IFERROR(__xludf.DUMMYFUNCTION("""COMPUTED_VALUE"""),"Alpha-Cored Technology Systems, Inc.") -> Alpha-Cored Technology Systems, Inc. | N93: =IFERROR(__xludf.DUMMYFUNCTION("""COMPUTED_VALUE"""),5.0) -> 5 | O93: =IFERROR(__xludf.DUMMYFUNCTION("""COMPUTED_VALUE"""),44950.0) -> 44950 | Q93: =IFERROR(__xludf.DUMMYFUNCTION("""COMPUTED_VALUE"""),"Goldlink Indsutrial Sales") -> Goldlink Indsutrial Sales | R93: =IFERROR(__xludf.DUMMYFUNCTION("""COMPUTED_VALUE"""),4.333333333333333) -> 4.3333333 | S93: =IFERROR(__xludf.DUMMYFUNCTION("""COMPUTED_VALUE"""),45258.0) -> 45258 | U93: =IFERROR(__xludf.DUMMYFUNCTION("""COMPUTED_VALUE"""),"Northwind Communications and Electronics") -> Northwind Communications and Electronics | V93: =IFERROR(__xludf.DUMMYFUNCTION("""COMPUTED_VALUE"""),4.375) -> 4.375 | W93: =IFERROR(__xludf.DUMMYFUNCTION("""COMPUTED_VALUE"""),45569.0) -> 45569
I94: 79 | J94: MMP Friendly Gift Ideas Store | M94: =IFERROR(__xludf.DUMMYFUNCTION("""COMPUTED_VALUE"""),"Columbia Technologies, Inc.") -> Columbia Technologies, Inc. | N94: =IFERROR(__xludf.DUMMYFUNCTION("""COMPUTED_VALUE"""),5.0) -> 5 | O94: =IFERROR(__xludf.DUMMYFUNCTION("""COMPUTED_VALUE"""),44950.0) -> 44950 | Q94: =IFERROR(__xludf.DUMMYFUNCTION("""COMPUTED_VALUE"""),"Abacus Book & Card Corp.") -> Abacus Book & Card Corp. | R94: =IFERROR(__xludf.DUMMYFUNCTION("""COMPUTED_VALUE"""),5.0) -> 5 | S94: =IFERROR(__xludf.DUMMYFUNCTION("""COMPUTED_VALUE"""),45259.0) -> 45259 | U94: =IFERROR(__xludf.DUMMYFUNCTION("""COMPUTED_VALUE"""),"Philippine Chinese Education Research Center Inc.") -> Philippine Chinese Education Research Center Inc. | V94: =IFERROR(__xludf.DUMMYFUNCTION("""COMPUTED_VALUE"""),4.166666666666667) -> 4.1666667 | W94: =IFERROR(__xludf.DUMMYFUNCTION("""COMPUTED_VALUE"""),45570.0) -> 45570
I95: 80 | J95: Raynard's Enterprises | M95: =IFERROR(__xludf.DUMMYFUNCTION("""COMPUTED_VALUE"""),"Creative Juice Digital Printing") -> Creative Juice Digital Printing | N95: =IFERROR(__xludf.DUMMYFUNCTION("""COMPUTED_VALUE"""),4.625) -> 4.625 | O95: =IFERROR(__xludf.DUMMYFUNCTION("""COMPUTED_VALUE"""),44950.0) -> 44950 | Q95: =IFERROR(__xludf.DUMMYFUNCTION("""COMPUTED_VALUE"""),"Mostaco Printing") -> Mostaco Printing | R95: =IFERROR(__xludf.DUMMYFUNCTION("""COMPUTED_VALUE"""),5.0) -> 5 | S95: =IFERROR(__xludf.DUMMYFUNCTION("""COMPUTED_VALUE"""),45259.0) -> 45259 | U95: =IFERROR(__xludf.DUMMYFUNCTION("""COMPUTED_VALUE"""),"Printing Shop PrintPilipinas.com") -> Printing Shop PrintPilipinas.com | V95: =IFERROR(__xludf.DUMMYFUNCTION("""COMPUTED_VALUE"""),4.833333333333333) -> 4.8333333 | W95: =IFERROR(__xludf.DUMMYFUNCTION("""COMPUTED_VALUE"""),45572.0) -> 45572
I96: 81 | J96: Tieline, Inc | M96: =IFERROR(__xludf.DUMMYFUNCTION("""COMPUTED_VALUE"""),"Creative Juice Digital Printing") -> Creative Juice Digital Printing | N96: =IFERROR(__xludf.DUMMYFUNCTION("""COMPUTED_VALUE"""),4.625) -> 4.625 | O96: =IFERROR(__xludf.DUMMYFUNCTION("""COMPUTED_VALUE"""),44950.0) -> 44950 | Q96: =IFERROR(__xludf.DUMMYFUNCTION("""COMPUTED_VALUE"""),"Printing Shop PrintPilipinas.com") -> Printing Shop PrintPilipinas.com | R96: =IFERROR(__xludf.DUMMYFUNCTION("""COMPUTED_VALUE"""),4.746666666666667) -> 4.7466667 | S96: =IFERROR(__xludf.DUMMYFUNCTION("""COMPUTED_VALUE"""),45259.0) -> 45259 | U96: =IFERROR(__xludf.DUMMYFUNCTION("""COMPUTED_VALUE"""),"Printing Shop PrintPilipinas.com") -> Printing Shop PrintPilipinas.com | V96: =IFERROR(__xludf.DUMMYFUNCTION("""COMPUTED_VALUE"""),4.666666666666667) -> 4.6666667 | W96: =IFERROR(__xludf.DUMMYFUNCTION("""COMPUTED_VALUE"""),45572.0) -> 45572
I97: 82 | J97: Awardextremes, Inc, | K97: 4.6666667 | M97: =IFERROR(__xludf.DUMMYFUNCTION("""COMPUTED_VALUE"""),"Creative Juice Digital Printing") -> Creative Juice Digital Printing | N97: =IFERROR(__xludf.DUMMYFUNCTION("""COMPUTED_VALUE"""),4.625) -> 4.625 | O97: =IFERROR(__xludf.DUMMYFUNCTION("""COMPUTED_VALUE"""),44950.0) -> 44950 | Q97: =IFERROR(__xludf.DUMMYFUNCTION("""COMPUTED_VALUE"""),"Chemtrust Global Market, Inc.") -> Chemtrust Global Market, Inc. | R97: =IFERROR(__xludf.DUMMYFUNCTION("""COMPUTED_VALUE"""),4.516666666666667) -> 4.5166667 | S97: =IFERROR(__xludf.DUMMYFUNCTION("""COMPUTED_VALUE"""),45260.0) -> 45260 | U97: =IFERROR(__xludf.DUMMYFUNCTION("""COMPUTED_VALUE"""),"Printing Shop PrintPilipinas.com") -> Printing Shop PrintPilipinas.com | V97: =IFERROR(__xludf.DUMMYFUNCTION("""COMPUTED_VALUE"""),4.825) -> 4.825 | W97: =IFERROR(__xludf.DUMMYFUNCTION("""COMPUTED_VALUE"""),45572.0) -> 45572
I98: Furniture | K98: =average(K99:K102) -> 4.3833333 | M98: =IFERROR(__xludf.DUMMYFUNCTION("""COMPUTED_VALUE"""),"Creative Juice Digital Printing") -> Creative Juice Digital Printing | N98: =IFERROR(__xludf.DUMMYFUNCTION("""COMPUTED_VALUE"""),4.625) -> 4.625 | O98: =IFERROR(__xludf.DUMMYFUNCTION("""COMPUTED_VALUE"""),44950.0) -> 44950 | Q98: =IFERROR(__xludf.DUMMYFUNCTION("""COMPUTED_VALUE"""),"Rivchem Enterprises") -> Rivchem Enterprises | R98: =IFERROR(__xludf.DUMMYFUNCTION("""COMPUTED_VALUE"""),4.333333333333333) -> 4.3333333 | S98: =IFERROR(__xludf.DUMMYFUNCTION("""COMPUTED_VALUE"""),45260.0) -> 45260 | U98: =IFERROR(__xludf.DUMMYFUNCTION("""COMPUTED_VALUE"""),"Net Ad IT Solutions") -> Net Ad IT Solutions | V98: =IFERROR(__xludf.DUMMYFUNCTION("""COMPUTED_VALUE"""),4.833333333333333) -> 4.8333333 | W98: =IFERROR(__xludf.DUMMYFUNCTION("""COMPUTED_VALUE"""),45573.0) -> 45573
I99: 83 | J99: Alpha Steel Office & Home Furnishing Company Inc. | M99: =IFERROR(__xludf.DUMMYFUNCTION("""COMPUTED_VALUE"""),"Creative Juice Digital Printing") -> Creative Juice Digital Printing | N99: =IFERROR(__xludf.DUMMYFUNCTION("""COMPUTED_VALUE"""),4.625) -> 4.625 | O99: =IFERROR(__xludf.DUMMYFUNCTION("""COMPUTED_VALUE"""),44950.0) -> 44950 | Q99: =IFERROR(__xludf.DUMMYFUNCTION("""COMPUTED_VALUE"""),"Rivchem Enterprises") -> Rivchem Enterprises | R99: =IFERROR(__xludf.DUMMYFUNCTION("""COMPUTED_VALUE"""),5.0) -> 5 | S99: =IFERROR(__xludf.DUMMYFUNCTION("""COMPUTED_VALUE"""),45260.0) -> 45260 | U99: =IFERROR(__xludf.DUMMYFUNCTION("""COMPUTED_VALUE"""),"Javammp Printing Services") -> Javammp Printing Services | V99: =IFERROR(__xludf.DUMMYFUNCTION("""COMPUTED_VALUE"""),4.666666666666667) -> 4.6666667 | W99: =IFERROR(__xludf.DUMMYFUNCTION("""COMPUTED_VALUE"""),45575.0) -> 45575
I100: 84 | J100: Elle Tech & Trend | M100: =IFERROR(__xludf.DUMMYFUNCTION("""COMPUTED_VALUE"""),"Creative Juice Digital Printing") -> Creative Juice Digital Printing | N100: =IFERROR(__xludf.DUMMYFUNCTION("""COMPUTED_VALUE"""),4.625) -> 4.625 | O100: =IFERROR(__xludf.DUMMYFUNCTION("""COMPUTED_VALUE"""),44950.0) -> 44950 | Q100: =IFERROR(__xludf.DUMMYFUNCTION("""COMPUTED_VALUE"""),"EA Intertrade General Merchandising, Inc.") -> EA Intertrade General Merchandising, Inc. | R100: =IFERROR(__xludf.DUMMYFUNCTION("""COMPUTED_VALUE"""),5.0) -> 5 | S100: =IFERROR(__xludf.DUMMYFUNCTION("""COMPUTED_VALUE"""),45260.0) -> 45260 | U100: =IFERROR(__xludf.DUMMYFUNCTION("""COMPUTED_VALUE"""),"Abacus Book & Card Corp.") -> Abacus Book & Card Corp. | V100: =IFERROR(__xludf.DUMMYFUNCTION("""COMPUTED_VALUE"""),4.666666666666667) -> 4.6666667 | W100: =IFERROR(__xludf.DUMMYFUNCTION("""COMPUTED_VALUE"""),45575.0) -> 45575
I101: 85 | J101: ARKWOOD PLUS FINE FURNITURE | K101: 4 | M101: =IFERROR(__xludf.DUMMYFUNCTION("""COMPUTED_VALUE"""),"Luminaire Printing And Publishing Corp.") -> Luminaire Printing And Publishing Corp. | N101: =IFERROR(__xludf.DUMMYFUNCTION("""COMPUTED_VALUE"""),5.0) -> 5 | O101: =IFERROR(__xludf.DUMMYFUNCTION("""COMPUTED_VALUE"""),44950.0) -> 44950 | Q101: =IFERROR(__xludf.DUMMYFUNCTION("""COMPUTED_VALUE"""),"Data Computer Forms, Inc.") -> Data Computer Forms, Inc. | R101: =IFERROR(__xludf.DUMMYFUNCTION("""COMPUTED_VALUE"""),5.0) -> 5 | S101: =IFERROR(__xludf.DUMMYFUNCTION("""COMPUTED_VALUE"""),45266.0) -> 45266 | U101: =IFERROR(__xludf.DUMMYFUNCTION("""COMPUTED_VALUE"""),"Falcon Waterfree Philippines, Inc.") -> Falcon Waterfree Philippines, Inc. | V101: =IFERROR(__xludf.DUMMYFUNCTION("""COMPUTED_VALUE"""),4.791666666666667) -> 4.7916667 | W101: =IFERROR(__xludf.DUMMYFUNCTION("""COMPUTED_VALUE"""),45575.0) -> 45575
I102: 86 | J102: Ergo Contracts Phil., Inc. | K102: 4.7666667 | M102: =IFERROR(__xludf.DUMMYFUNCTION("""COMPUTED_VALUE"""),"Luminaire Printing And Publishing Corp.") -> Luminaire Printing And Publishing Corp. | N102: =IFERROR(__xludf.DUMMYFUNCTION("""COMPUTED_VALUE"""),4.625) -> 4.625 | O102: =IFERROR(__xludf.DUMMYFUNCTION("""COMPUTED_VALUE"""),44950.0) -> 44950 | Q102: =IFERROR(__xludf.DUMMYFUNCTION("""COMPUTED_VALUE"""),"World Magazine Exchange Marketing Corp.") -> World Magazine Exchange Marketing Corp. | R102: =IFERROR(__xludf.DUMMYFUNCTION("""COMPUTED_VALUE"""),4.733333333333333) -> 4.7333333 | S102: =IFERROR(__xludf.DUMMYFUNCTION("""COMPUTED_VALUE"""),45267.0) -> 45267 | U102: =IFERROR(__xludf.DUMMYFUNCTION("""COMPUTED_VALUE"""),"Alpha-Cored Technology Systems, Inc.") -> Alpha-Cored Technology Systems, Inc. | V102: =IFERROR(__xludf.DUMMYFUNCTION("""COMPUTED_VALUE"""),4.833333333333333) -> 4.8333333 | W102: =IFERROR(__xludf.DUMMYFUNCTION("""COMPUTED_VALUE"""),45576.0) -> 45576
...

Sheet raw report copy
A3: 2024-2025 | E3: 2023-2024 | I3: 2022-2023 | N3: 2022-2023 | R3: 2023-2024 | V3: 2024-2025 | Z3: 2022-2023 | AC3: 2023-2024 | AF3: 2024-2025
C4: Average Ratings | G4: Average Ratings | K4: Average Ratings | Z4: =IFERROR(__xludf.DUMMYFUNCTION("QUERY(N:O, ""select N, AVG(O) where N is not null group by N label AVG(O) 'Average Rating'"", 0)"),"") | AA4: =IFERROR(__xludf.DUMMYFUNCTION("""COMPUTED_VALUE"""),"Average Rating") -> Average Rating | AC4: =IFERROR(__xludf.DUMMYFUNCTION("QUERY(R:S, ""select R, AVG(S) where R is not null group by R label AVG(S) 'Average Rating'"", 0)"),"") | AD4: =IFERROR(__xludf.DUMMYFUNCTION("""COMPUTED_VALUE"""),"Average Rating") -> Average Rating | AF4: =IFERROR(__xludf.DUMMYFUNCTION("QUERY(V:W, ""select V, AVG(W) where V is not null group by V label AVG(W) 'Average Rating'"", 0)"),"") | AG4: =IFERROR(__xludf.DUMMYFUNCTION("""COMPUTED_VALUE"""),"Average Rating") -> Average Rating
B5: Company Name | F5: Company Name | I5: COMPANY | K5: =average(K6:K9) -> 4.7751923 | N5: =IFERROR(__xludf.DUMMYFUNCTION("FILTER( {DATABASE!E2:E1099, DATABASE!AC2:AC1099, DATABASE!D2:D1099}, (DATABASE!D2:D1099 >= DATE(2022,7,1)) * (DATABASE!D2:D1099 <= DATE(2023,6,30)) )"),"EIG Metal Engravers") -> EIG Metal Engravers | O5: =IFERROR(__xludf.DUMMYFUNCTION("""COMPUTED_VALUE"""),4.0) -> 4 | P5: =IFERROR(__xludf.DUMMYFUNCTION("""COMPUTED_VALUE"""),44746.0) -> 44746 | R5: =IFERROR(__xludf.DUMMYFUNCTION("FILTER( {DATABASE!E2:E1099, DATABASE!AC2:AC1099, DATABASE!D2:D1099}, (DATABASE!D2:D1099 >= DATE(2023,7,1)) * (DATABASE!D2:D1099 <= DATE(2024,6,30)) )"),"Leonard Prints Inc.") -> Leonard Prints Inc. | S5: =IFERROR(__xludf.DUMMYFUNCTION("""COMPUTED_VALUE"""),4.833333333333333) -> 4.8333333 | T5: =IFERROR(__xludf.DUMMYFUNCTION("""COMPUTED_VALUE"""),45110.0) -> 45110 | V5: =IFERROR(__xludf.DUMMYFUNCTION("FILTER( {DATABASE!E2:E1099, DATABASE!AC2:AC1099, DATABASE!D2:D1099}, (DATABASE!D2:D1099 >= DATE(2024,7,1)) * (DATABASE!D2:D1099 <= DATE(2025,6,30)) )"),"Creative Juice Digital Printing") -> Creative Juice Digital Printing | W5: =IFERROR(__xludf.DUMMYFUNCTION("""COMPUTED_VALUE"""),4.833333333333333) -> 4.8333333 | X5: =IFERROR(__xludf.DUMMYFUNCTION("""COMPUTED_VALUE"""),45476.0) -> 45476 | Z5: =IFERROR(__xludf.DUMMYFUNCTION("""COMPUTED_VALUE"""),"2022-2023") -> 2022-2023 | AC5: =IFERROR(__xludf.DUMMYFUNCTION("""COMPUTED_VALUE"""),"2023-2024") -> 2023-2024 | AF5: =IFERROR(__xludf.DUMMYFUNCTION("""COMPUTED_VALUE"""),"2024-2025") -> 2024-2025
A6: Books | C6: =average(C7:C12) -> 4.5 | E6: Books | G6: =average(G7:G12) -> 4.83125 | I6: Advertisement Printing | N6: =IFERROR(__xludf.DUMMYFUNCTION("""COMPUTED_VALUE"""),"Atlas Superflags") -> Atlas Superflags | O6: =IFERROR(__xludf.DUMMYFUNCTION("""COMPUTED_VALUE"""),5.0) -> 5 | P6: =IFERROR(__xludf.DUMMYFUNCTION("""COMPUTED_VALUE"""),44750.0) -> 44750 | R6: =IFERROR(__xludf.DUMMYFUNCTION("""COMPUTED_VALUE"""),"Leonard Prints Inc.") -> Leonard Prints Inc. | S6: =IFERROR(__xludf.DUMMYFUNCTION("""COMPUTED_VALUE"""),4.833333333333333) -> 4.8333333 | T6: =IFERROR(__xludf.DUMMYFUNCTION("""COMPUTED_VALUE"""),45110.0) -> 45110 | V6: =IFERROR(__xludf.DUMMYFUNCTION("""COMPUTED_VALUE"""),"Arkin Hardware") -> Arkin Hardware | W6: =IFERROR(__xludf.DUMMYFUNCTION("""COMPUTED_VALUE"""),4.625) -> 4.625 | X6: =IFERROR(__xludf.DUMMYFUNCTION("""COMPUTED_VALUE"""),45477.0) -> 45477 | Z6: =IFERROR(__xludf.DUMMYFUNCTION("""COMPUTED_VALUE"""),"Abenson Ventures, Inc.") -> Abenson Ventures, Inc. | AA6: =IFERROR(__xludf.DUMMYFUNCTION("""COMPUTED_VALUE"""),4.916666666666666) -> 4.9166667 | AC6: =IFERROR(__xludf.DUMMYFUNCTION("""COMPUTED_VALUE"""),"ADBM Lightning Equipment Trading") -> ADBM Lightning Equipment Trading | AD6: =IFERROR(__xludf.DUMMYFUNCTION("""COMPUTED_VALUE"""),5.0) -> 5 | AF6: =IFERROR(__xludf.DUMMYFUNCTION("""COMPUTED_VALUE"""),"4David's Book Trading") -> 4David's Book Trading | AG6: =IFERROR(__xludf.DUMMYFUNCTION("""COMPUTED_VALUE"""),4.803333333333333) -> 4.8033333
A7: 1 | B7: REX Book Store | E7: 1 | F7: REX Book Store | G7: 4.8333333 | I7: 1 | J7: Creative Juice Digital Printing | K7: 4.7751923 | N7: =IFERROR(__xludf.DUMMYFUNCTION("""COMPUTED_VALUE"""),"Atlas Superflags") -> Atlas Superflags | O7: =IFERROR(__xludf.DUMMYFUNCTION("""COMPUTED_VALUE"""),4.066666666666666) -> 4.0666667 | P7: =IFERROR(__xludf.DUMMYFUNCTION("""COMPUTED_VALUE"""),44750.0) -> 44750 | R7: =IFERROR(__xludf.DUMMYFUNCTION("""COMPUTED_VALUE"""),"Net Ad IT Solutions") -> Net Ad IT Solutions | S7: =IFERROR(__xludf.DUMMYFUNCTION("""COMPUTED_VALUE"""),4.733333333333333) -> 4.7333333 | T7: =IFERROR(__xludf.DUMMYFUNCTION("""COMPUTED_VALUE"""),45127.0) -> 45127 | V7: =IFERROR(__xludf.DUMMYFUNCTION("""COMPUTED_VALUE"""),"EIG Metal Engravers") -> EIG Metal Engravers | W7: =IFERROR(__xludf.DUMMYFUNCTION("""COMPUTED_VALUE"""),5.0) -> 5 | X7: =IFERROR(__xludf.DUMMYFUNCTION("""COMPUTED_VALUE"""),45478.0) -> 45478 | Z7: =IFERROR(__xludf.DUMMYFUNCTION("""COMPUTED_VALUE"""),"Ahrcel's Gift Shop") -> Ahrcel's Gift Shop | AA7: =IFERROR(__xludf.DUMMYFUNCTION("""COMPUTED_VALUE"""),5.0) -> 5 | AC7: =IFERROR(__xludf.DUMMYFUNCTION("""COMPUTED_VALUE"""),"Abacus Book & Card Corp.") -> Abacus Book & Card Corp. | AD7: =IFERROR(__xludf.DUMMYFUNCTION("""COMPUTED_VALUE"""),4.845897435897436) -> 4.8458974 | AF7: =IFERROR(__xludf.DUMMYFUNCTION("""COMPUTED_VALUE"""),"888 Tile Phil Corp") -> 888 Tile Phil Corp | AG7: =IFERROR(__xludf.DUMMYFUNCTION("""COMPUTED_VALUE"""),4.416666666666667) -> 4.4166667
A8: 2 | B8: BELVIEW CO., INC. | C8: 4.5 | E8: 2 | F8: BELVIEW CO., INC. | G8: 4.7583333 | I8: 2 | J8: Luneta Advertisement Inc. | N8: =IFERROR(__xludf.DUMMYFUNCTION("""COMPUTED_VALUE"""),"Marguerita Maria Nina I. Kanapi") -> Marguerita Maria Nina I. Kanapi | O8: =IFERROR(__xludf.DUMMYFUNCTION("""COMPUTED_VALUE"""),5.0) -> 5 | P8: =IFERROR(__xludf.DUMMYFUNCTION("""COMPUTED_VALUE"""),44756.0) -> 44756 | R8: =IFERROR(__xludf.DUMMYFUNCTION("""COMPUTED_VALUE"""),"Forefront Book Co., Inc.") -> Forefront Book Co., Inc. | S8: =IFERROR(__xludf.DUMMYFUNCTION("""COMPUTED_VALUE"""),4.733333333333333) -> 4.7333333 | T8: =IFERROR(__xludf.DUMMYFUNCTION("""COMPUTED_VALUE"""),45128.0) -> 45128 | V8: =IFERROR(__xludf.DUMMYFUNCTION("""COMPUTED_VALUE"""),"Arkin Hardware") -> Arkin Hardware | W8: =IFERROR(__xludf.DUMMYFUNCTION("""COMPUTED_VALUE"""),4.625) -> 4.625 | X8: =IFERROR(__xludf.DUMMYFUNCTION("""COMPUTED_VALUE"""),45481.0) -> 45481 | Z8: =IFERROR(__xludf.DUMMYFUNCTION("""COMPUTED_VALUE"""),"Alpha-Cored Technology Systems, Inc.") -> Alpha-Cored Technology Systems, Inc. | AA8: =IFERROR(__xludf.DUMMYFUNCTION("""COMPUTED_VALUE"""),5.0) -> 5 | AC8: =IFERROR(__xludf.DUMMYFUNCTION("""COMPUTED_VALUE"""),"Abenson Ventures, Inc.") -> Abenson Ventures, Inc. | AD8: =IFERROR(__xludf.DUMMYFUNCTION("""COMPUTED_VALUE"""),4.608333333333333) -> 4.6083333 | AF8: =IFERROR(__xludf.DUMMYFUNCTION("""COMPUTED_VALUE"""),"Abacus Book & Card Corp.") -> Abacus Book & Card Corp. | AG8: =IFERROR(__xludf.DUMMYFUNCTION("""COMPUTED_VALUE"""),4.805555555555555) -> 4.8055556
A9: 3 | B9: CD Books International, Inc. | C9: 4.5 | E9: 3 | F9: CD Books International, Inc. | I9: 3 | J9: Doo Graphic Services | N9: =IFERROR(__xludf.DUMMYFUNCTION("""COMPUTED_VALUE"""),"Hospeco Philippines, Inc.") -> Hospeco Philippines, Inc. | O9: =IFERROR(__xludf.DUMMYFUNCTION("""COMPUTED_VALUE"""),4.533333333333333) -> 4.5333333 | P9: =IFERROR(__xludf.DUMMYFUNCTION("""COMPUTED_VALUE"""),44757.0) -> 44757 | R9: =IFERROR(__xludf.DUMMYFUNCTION("""COMPUTED_VALUE"""),"Contrade Integrated Depot") -> Contrade Integrated Depot | S9: =IFERROR(__xludf.DUMMYFUNCTION("""COMPUTED_VALUE"""),4.680000000000001) -> 4.68 | T9: =IFERROR(__xludf.DUMMYFUNCTION("""COMPUTED_VALUE"""),45131.0) -> 45131 | V9: =IFERROR(__xludf.DUMMYFUNCTION("""COMPUTED_VALUE"""),"Abiva Publishing House, Inc.") -> Abiva Publishing House, Inc. | W9: =IFERROR(__xludf.DUMMYFUNCTION("""COMPUTED_VALUE"""),4.833333333333333) -> 4.8333333 | X9: =IFERROR(__xludf.DUMMYFUNCTION("""COMPUTED_VALUE"""),45484.0) -> 45484 | Z9: =IFERROR(__xludf.DUMMYFUNCTION("""COMPUTED_VALUE"""),"Amalgamated Specialties Corporation") -> Amalgamated Specialties Corporation | AA9: =IFERROR(__xludf.DUMMYFUNCTION("""COMPUTED_VALUE"""),4.333333333333333) -> 4.3333333 | AC9: =IFERROR(__xludf.DUMMYFUNCTION("""COMPUTED_VALUE"""),"Ahrcel's Gift Shop") -> Ahrcel's Gift Shop | AD9: =IFERROR(__xludf.DUMMYFUNCTION("""COMPUTED_VALUE"""),4.836111111111111) -> 4.8361111 | AF9: =IFERROR(__xludf.DUMMYFUNCTION("""COMPUTED_VALUE"""),"Abenson Ventures, Inc.") -> Abenson Ventures, Inc. | AG9: =IFERROR(__xludf.DUMMYFUNCTION("""COMPUTED_VALUE"""),4.8973958333333325) -> 4.8973958
A10: 4 | B10: Forefront Book Co | E10: 4 | F10: Forefront Book Co | G10: 4.7333333 | I10: Audio Visual and Equipment | K10: =average(K11) -> #DIV/0! | N10: =IFERROR(__xludf.DUMMYFUNCTION("""COMPUTED_VALUE"""),"Oray Copier Solutions") -> Oray Copier Solutions | O10: =IFERROR(__xludf.DUMMYFUNCTION("""COMPUTED_VALUE"""),5.0) -> 5 | P10: =IFERROR(__xludf.DUMMYFUNCTION("""COMPUTED_VALUE"""),44757.0) -> 44757 | R10: =IFERROR(__xludf.DUMMYFUNCTION("""COMPUTED_VALUE"""),"Alpha-Cored Technology Systems, Inc.") -> Alpha-Cored Technology Systems, Inc. | S10: =IFERROR(__xludf.DUMMYFUNCTION("""COMPUTED_VALUE"""),5.0) -> 5 | T10: =IFERROR(__xludf.DUMMYFUNCTION("""COMPUTED_VALUE"""),45134.0) -> 45134 | V10: =IFERROR(__xludf.DUMMYFUNCTION("""COMPUTED_VALUE"""),"Mostaco Printing") -> Mostaco Printing | W10: =IFERROR(__xludf.DUMMYFUNCTION("""COMPUTED_VALUE"""),4.833333333333333) -> 4.8333333 | X10: =IFERROR(__xludf.DUMMYFUNCTION("""COMPUTED_VALUE"""),45492.0) -> 45492 | Z10: =IFERROR(__xludf.DUMMYFUNCTION("""COMPUTED_VALUE"""),"Amazon") -> Amazon | AA10: =IFERROR(__xludf.DUMMYFUNCTION("""COMPUTED_VALUE"""),4.708) -> 4.708 | AC10: =IFERROR(__xludf.DUMMYFUNCTION("""COMPUTED_VALUE"""),"Alpha Steel Office and Home Furnishing Company") -> Alpha Steel Office and Home Furnishing Company | AD10: =IFERROR(__xludf.DUMMYFUNCTION("""COMPUTED_VALUE"""),5.0) -> 5 | AF10: =IFERROR(__xludf.DUMMYFUNCTION("""COMPUTED_VALUE"""),"Abiva Publishing House, Inc.") -> Abiva Publishing House, Inc. | AG10: =IFERROR(__xludf.DUMMYFUNCTION("""COMPUTED_VALUE"""),4.833333333333333) -> 4.8333333
A11: 5 | B11: Phoenix Publishing House | E11: 5 | F11: Phoenix Publishing House | I11: 4 | J11: Lovell de Mesa | N11: =IFERROR(__xludf.DUMMYFUNCTION("""COMPUTED_VALUE"""),"Amazon") -> Amazon | O11: =IFERROR(__xludf.DUMMYFUNCTION("""COMPUTED_VALUE"""),4.3116666666666665) -> 4.3116667 | P11: =IFERROR(__xludf.DUMMYFUNCTION("""COMPUTED_VALUE"""),44762.0) -> 44762 | R11: =IFERROR(__xludf.DUMMYFUNCTION("""COMPUTED_VALUE"""),"Tropical Palms Fashion House, Inc.") -> Tropical Palms Fashion House, Inc. | S11: =IFERROR(__xludf.DUMMYFUNCTION("""COMPUTED_VALUE"""),4.608333333333333) -> 4.6083333 | T11: =IFERROR(__xludf.DUMMYFUNCTION("""COMPUTED_VALUE"""),45140.0) -> 45140 | V11: =IFERROR(__xludf.DUMMYFUNCTION("""COMPUTED_VALUE"""),"CD Books International, Inc.") -> CD Books International, Inc. | W11: =IFERROR(__xludf.DUMMYFUNCTION("""COMPUTED_VALUE"""),4.833333333333333) -> 4.8333333 | X11: =IFERROR(__xludf.DUMMYFUNCTION("""COMPUTED_VALUE"""),45492.0) -> 45492 | Z11: =IFERROR(__xludf.DUMMYFUNCTION("""COMPUTED_VALUE"""),"Arkwood Plus Fine Furniture") -> Arkwood Plus Fine Furniture | AA11: =IFERROR(__xludf.DUMMYFUNCTION("""COMPUTED_VALUE"""),4.0) -> 4 | AC11: =IFERROR(__xludf.DUMMYFUNCTION("""COMPUTED_VALUE"""),"Alpha-Cored Technology Systems, Inc.") -> Alpha-Cored Technology Systems, Inc. | AD11: =IFERROR(__xludf.DUMMYFUNCTION("""COMPUTED_VALUE"""),5.0) -> 5 | AF11: =IFERROR(__xludf.DUMMYFUNCTION("""COMPUTED_VALUE"""),"Ace Hardware") -> Ace Hardware | AG11: =IFERROR(__xludf.DUMMYFUNCTION("""COMPUTED_VALUE"""),4.791666666666667) -> 4.7916667
A12: 6 | B12: Booktrends Enterprises | E12: 6 | F12: Booktrends Enterprises | G12: 5 | I12: Books | K12: =average(K13:K21) -> 4.5 | N12: =IFERROR(__xludf.DUMMYFUNCTION("""COMPUTED_VALUE"""),"Contrade Integrated Depot") -> Contrade Integrated Depot | O12: =IFERROR(__xludf.DUMMYFUNCTION("""COMPUTED_VALUE"""),3.9166666666666665) -> 3.9166667 | P12: =IFERROR(__xludf.DUMMYFUNCTION("""COMPUTED_VALUE"""),44763.0) -> 44763 | R12: =IFERROR(__xludf.DUMMYFUNCTION("""COMPUTED_VALUE"""),"Awardextremes, Inc.") -> Awardextremes, Inc. | S12: =IFERROR(__xludf.DUMMYFUNCTION("""COMPUTED_VALUE"""),4.566666666666666) -> 4.5666667 | T12: =IFERROR(__xludf.DUMMYFUNCTION("""COMPUTED_VALUE"""),45141.0) -> 45141 | V12: =IFERROR(__xludf.DUMMYFUNCTION("""COMPUTED_VALUE"""),"Belview Co., Inc.") -> Belview Co., Inc. | W12: =IFERROR(__xludf.DUMMYFUNCTION("""COMPUTED_VALUE"""),4.833333333333333) -> 4.8333333 | X12: =IFERROR(__xludf.DUMMYFUNCTION("""COMPUTED_VALUE"""),45492.0) -> 45492 | Z12: =IFERROR(__xludf.DUMMYFUNCTION("""COMPUTED_VALUE"""),"Atlas Superflags") -> Atlas Superflags | AA12: =IFERROR(__xludf.DUMMYFUNCTION("""COMPUTED_VALUE"""),4.766666666666667) -> 4.7666667 | AC12: =IFERROR(__xludf.DUMMYFUNCTION("""COMPUTED_VALUE"""),"Amalgamated Specialties Corporation") -> Amalgamated Specialties Corporation | AD12: =IFERROR(__xludf.DUMMYFUNCTION("""COMPUTED_VALUE"""),5.0) -> 5 | AF12: =IFERROR(__xludf.DUMMYFUNCTION("""COMPUTED_VALUE"""),"Alpha Steel Office and Home Furnishing Company") -> Alpha Steel Office and Home Furnishing Company | AG12: =IFERROR(__xludf.DUMMYFUNCTION("""COMPUTED_VALUE"""),4.833333333333333) -> 4.8333333
A13: Cleaning Materials | C13: =average(C14:C15) -> 4.6809896 | E13: School/Office Supplies | G13: =average(G14:G21) -> 4.7778378 | I13: 5 | J13: C & E Publishing Inc | K13: 4.5 | N13: =IFERROR(__xludf.DUMMYFUNCTION("""COMPUTED_VALUE"""),"Rivchem Enterprises") -> Rivchem Enterprises | O13: =IFERROR(__xludf.DUMMYFUNCTION("""COMPUTED_VALUE"""),4.833333333333333) -> 4.8333333 | P13: =IFERROR(__xludf.DUMMYFUNCTION("""COMPUTED_VALUE"""),44763.0) -> 44763 | R13: =IFERROR(__xludf.DUMMYFUNCTION("""COMPUTED_VALUE"""),"Contrade Integrated Depot") -> Contrade Integrated Depot | S13: =IFERROR(__xludf.DUMMYFUNCTION("""COMPUTED_VALUE"""),4.566666666666666) -> 4.5666667 | T13: =IFERROR(__xludf.DUMMYFUNCTION("""COMPUTED_VALUE"""),45142.0) -> 45142 | V13: =IFERROR(__xludf.DUMMYFUNCTION("""COMPUTED_VALUE"""),"Belview Co., Inc.") -> Belview Co., Inc. | W13: =IFERROR(__xludf.DUMMYFUNCTION("""COMPUTED_VALUE"""),4.833333333333333) -> 4.8333333 | X13: =IFERROR(__xludf.DUMMYFUNCTION("""COMPUTED_VALUE"""),45492.0) -> 45492 | Z13: =IFERROR(__xludf.DUMMYFUNCTION("""COMPUTED_VALUE"""),"Awardextremes, Inc.") -> Awardextremes, Inc. | AA13: =IFERROR(__xludf.DUMMYFUNCTION("""COMPUTED_VALUE"""),4.666666666666667) -> 4.6666667 | AC13: =IFERROR(__xludf.DUMMYFUNCTION("""COMPUTED_VALUE"""),"Arkin Hardware") -> Arkin Hardware | AD13: =IFERROR(__xludf.DUMMYFUNCTION("""COMPUTED_VALUE"""),4.4714285714285715) -> 4.4714286 | AF13: =IFERROR(__xludf.DUMMYFUNCTION("""COMPUTED_VALUE"""),"Alpha-Cored Technology Systems, Inc.") -> Alpha-Cored Technology Systems, Inc. | AG13: =IFERROR(__xludf.DUMMYFUNCTION("""COMPUTED_VALUE"""),4.925925925925926) -> 4.9259259
A14: 7 | B14: Rivchem Enterprises | C14: 4.7161458 | E14: 7 | F14: Abacus Book and Card Corporation | G14: 4.8458974 | I14: 6 | J14: National Book Store, Inc | N14: =IFERROR(__xludf.DUMMYFUNCTION("""COMPUTED_VALUE"""),"Belview Co., Inc.") -> Belview Co., Inc. | O14: =IFERROR(__xludf.DUMMYFUNCTION("""COMPUTED_VALUE"""),5.0) -> 5 | P14: =IFERROR(__xludf.DUMMYFUNCTION("""COMPUTED_VALUE"""),44764.0) -> 44764 | R14: =IFERROR(__xludf.DUMMYFUNCTION("""COMPUTED_VALUE"""),"Lordfel Marketing") -> Lordfel Marketing | S14: =IFERROR(__xludf.DUMMYFUNCTION("""COMPUTED_VALUE"""),4.0) -> 4 | T14: =IFERROR(__xludf.DUMMYFUNCTION("""COMPUTED_VALUE"""),45142.0) -> 45142 | V14: =IFERROR(__xludf.DUMMYFUNCTION("""COMPUTED_VALUE"""),"Contrade Integrated Depot") -> Contrade Integrated Depot | W14: =IFERROR(__xludf.DUMMYFUNCTION("""COMPUTED_VALUE"""),4.583333333333333) -> 4.5833333 | X14: =IFERROR(__xludf.DUMMYFUNCTION("""COMPUTED_VALUE"""),45493.0) -> 45493 | Z14: =IFERROR(__xludf.DUMMYFUNCTION("""COMPUTED_VALUE"""),"Belview Co., Inc.") -> Belview Co., Inc. | AA14: =IFERROR(__xludf.DUMMYFUNCTION("""COMPUTED_VALUE"""),5.0) -> 5 | AC14: =IFERROR(__xludf.DUMMYFUNCTION("""COMPUTED_VALUE"""),"Atlas Superflags") -> Atlas Superflags | AD14: =IFERROR(__xludf.DUMMYFUNCTION("""COMPUTED_VALUE"""),4.0) -> 4 | AF14: =IFERROR(__xludf.DUMMYFUNCTION("""COMPUTED_VALUE"""),"Arkin Hardware") -> Arkin Hardware | AG14: =IFERROR(__xludf.DUMMYFUNCTION("""COMPUTED_VALUE"""),4.867222222222223) -> 4.8672222
A15: 8 | B15: Chemtrust Global Market | C15: 4.6458333 | E15: 8 | F15: Contrade Integrated Depot, Inc, | G15: 4.6089167 | I15: 7 | J15: Rex Bookstore | N15: =IFERROR(__xludf.DUMMYFUNCTION("""COMPUTED_VALUE"""),"Belview Co., Inc.") -> Belview Co., Inc. | O15: =IFERROR(__xludf.DUMMYFUNCTION("""COMPUTED_VALUE"""),5.0) -> 5 | P15: =IFERROR(__xludf.DUMMYFUNCTION("""COMPUTED_VALUE"""),44764.0) -> 44764 | R15: =IFERROR(__xludf.DUMMYFUNCTION("""COMPUTED_VALUE"""),"Rivchem Enterprises") -> Rivchem Enterprises | S15: =IFERROR(__xludf.DUMMYFUNCTION("""COMPUTED_VALUE"""),4.6) -> 4.6 | T15: =IFERROR(__xludf.DUMMYFUNCTION("""COMPUTED_VALUE"""),45145.0) -> 45145 | V15: =IFERROR(__xludf.DUMMYFUNCTION("""COMPUTED_VALUE"""),"Javammp Printing Services") -> Javammp Printing Services | W15: =IFERROR(__xludf.DUMMYFUNCTION("""COMPUTED_VALUE"""),3.9166666666666665) -> 3.9166667 | X15: =IFERROR(__xludf.DUMMYFUNCTION("""COMPUTED_VALUE"""),45495.0) -> 45495 | Z15: =IFERROR(__xludf.DUMMYFUNCTION("""COMPUTED_VALUE"""),"Brown Movement for Cultural Advancement, Inc.") -> Brown Movement for Cultural Advancement, Inc. | AA15: =IFERROR(__xludf.DUMMYFUNCTION("""COMPUTED_VALUE"""),5.0) -> 5 | AC15: =IFERROR(__xludf.DUMMYFUNCTION("""COMPUTED_VALUE"""),"Awardextremes, Inc.") -> Awardextremes, Inc. | AD15: =IFERROR(__xludf.DUMMYFUNCTION("""COMPUTED_VALUE"""),4.566666666666666) -> 4.5666667 | AF15: =IFERROR(__xludf.DUMMYFUNCTION("""COMPUTED_VALUE"""),"Asahl Design Centre Inc.") -> Asahl Design Centre Inc. | AG15: =IFERROR(__xludf.DUMMYFUNCTION("""COMPUTED_VALUE"""),4.858333333333333) -> 4.8583333
A16: School/Office Supplies | C16: =average(C17:C26) -> 4.7827932 | E16: 9 | F16: Times Trading Co., Inc. | G16: 4.6860417 | I16: 8 | J16: Phoenix Publishing House | N16: =IFERROR(__xludf.DUMMYFUNCTION("""COMPUTED_VALUE"""),"Amalgamated Specialties Corporation") -> Amalgamated Specialties Corporation | O16: =IFERROR(__xludf.DUMMYFUNCTION("""COMPUTED_VALUE"""),4.333333333333333) -> 4.3333333 | P16: =IFERROR(__xludf.DUMMYFUNCTION("""COMPUTED_VALUE"""),44767.0) -> 44767 | R16: =IFERROR(__xludf.DUMMYFUNCTION("""COMPUTED_VALUE"""),"Rivchem Enterprises") -> Rivchem Enterprises | S16: =IFERROR(__xludf.DUMMYFUNCTION("""COMPUTED_VALUE"""),4.6) -> 4.6 | T16: =IFERROR(__xludf.DUMMYFUNCTION("""COMPUTED_VALUE"""),45146.0) -> 45146 | V16: =IFERROR(__xludf.DUMMYFUNCTION("""COMPUTED_VALUE"""),"BIG LEAGUE SPORTS WEAR SHOP. INC.") -> BIG LEAGUE SPORTS WEAR SHOP. INC. | W16: =IFERROR(__xludf.DUMMYFUNCTION("""COMPUTED_VALUE"""),4.0) -> 4 | X16: =IFERROR(__xludf.DUMMYFUNCTION("""COMPUTED_VALUE"""),45503.0) -> 45503 | Z16: =IFERROR(__xludf.DUMMYFUNCTION("""COMPUTED_VALUE"""),"Chemtrust Global Market, Inc.") -> Chemtrust Global Market, Inc. | AA16: =IFERROR(__xludf.DUMMYFUNCTION("""COMPUTED_VALUE"""),4.066666666666666) -> 4.0666667 | AC16: =IFERROR(__xludf.DUMMYFUNCTION("""COMPUTED_VALUE"""),"Belview Co., Inc.") -> Belview Co., Inc. | AD16: =IFERROR(__xludf.DUMMYFUNCTION("""COMPUTED_VALUE"""),4.753333333333333) -> 4.7533333 | AF16: =IFERROR(__xludf.DUMMYFUNCTION("""COMPUTED_VALUE"""),"Atlas Superflags") -> Atlas Superflags | AG16: =IFERROR(__xludf.DUMMYFUNCTION("""COMPUTED_VALUE"""),4.7444444444444445) -> 4.7444444
A17: 9 | B17: Abacus Book and Card Corporation | C17: 4.7222222 | E17: 10 | F17: Paper Tree Marketing Group, Inc. | I17: 9 | J17: F & J De Jesus, Inc | N17: =IFERROR(__xludf.DUMMYFUNCTION("""COMPUTED_VALUE"""),"Contrade Integrated Depot") -> Contrade Integrated Depot | O17: =IFERROR(__xludf.DUMMYFUNCTION("""COMPUTED_VALUE"""),3.6) -> 3.6 | P17: =IFERROR(__xludf.DUMMYFUNCTION("""COMPUTED_VALUE"""),44767.0) -> 44767 | R17: =IFERROR(__xludf.DUMMYFUNCTION("""COMPUTED_VALUE"""),"Lordfel Marketing") -> Lordfel Marketing | S17: =IFERROR(__xludf.DUMMYFUNCTION("""COMPUTED_VALUE"""),5.0) -> 5 | T17: =IFERROR(__xludf.DUMMYFUNCTION("""COMPUTED_VALUE"""),45149.0) -> 45149 | V17: =IFERROR(__xludf.DUMMYFUNCTION("""COMPUTED_VALUE"""),"Printing Shop PrintPilipinas.com") -> Printing Shop PrintPilipinas.com | W17: =IFERROR(__xludf.DUMMYFUNCTION("""COMPUTED_VALUE"""),4.833333333333333) -> 4.8333333 | X17: =IFERROR(__xludf.DUMMYFUNCTION("""COMPUTED_VALUE"""),45505.0) -> 45505 | Z17: =IFERROR(__xludf.DUMMYFUNCTION("""COMPUTED_VALUE"""),"Columbia Technologies, Inc.") -> Columbia Technologies, Inc. | AA17: =IFERROR(__xludf.DUMMYFUNCTION("""COMPUTED_VALUE"""),4.958333333333333) -> 4.9583333 | AC17: =IFERROR(__xludf.DUMMYFUNCTION("""COMPUTED_VALUE"""),"Beyond Global Multiales Corp.") -> Beyond Global Multiales Corp. | AD17: =IFERROR(__xludf.DUMMYFUNCTION("""COMPUTED_VALUE"""),4.833333333333333) -> 4.8333333 | AF17: =IFERROR(__xludf.DUMMYFUNCTION("""COMPUTED_VALUE"""),"BIG LEAGUE SPORTS WEAR SHOP. INC.") -> BIG LEAGUE SPORTS WEAR SHOP. INC. | AG17: =IFERROR(__xludf.DUMMYFUNCTION("""COMPUTED_VALUE"""),4.0) -> 4
A18: 10 | B18: Contrade Integrated Depot, Inc, | C18: 4.7083333 | E18: 11 | F18: EA Intertrade General Merchandising, Inc. | G18: 5 | I18: 10 | J18: BOOK TRENDS ENTERPRISES | N18: =IFERROR(__xludf.DUMMYFUNCTION("""COMPUTED_VALUE"""),"Gift Republic, Inc.") -> Gift Republic, Inc. | O18: =IFERROR(__xludf.DUMMYFUNCTION("""COMPUTED_VALUE"""),2.0) -> 2 | P18: =IFERROR(__xludf.DUMMYFUNCTION("""COMPUTED_VALUE"""),44774.0) -> 44774 | R18: =IFERROR(__xludf.DUMMYFUNCTION("""COMPUTED_VALUE"""),"Lordfel Marketing") -> Lordfel Marketing | S18: =IFERROR(__xludf.DUMMYFUNCTION("""COMPUTED_VALUE"""),4.0) -> 4 | T18: =IFERROR(__xludf.DUMMYFUNCTION("""COMPUTED_VALUE"""),45149.0) -> 45149 | V18: =IFERROR(__xludf.DUMMYFUNCTION("""COMPUTED_VALUE"""),"Mostaco Printing") -> Mostaco Printing | W18: =IFERROR(__xludf.DUMMYFUNCTION("""COMPUTED_VALUE"""),4.75) -> 4.75 | X18: =IFERROR(__xludf.DUMMYFUNCTION("""COMPUTED_VALUE"""),45509.0) -> 45509 | Z18: =IFERROR(__xludf.DUMMYFUNCTION("""COMPUTED_VALUE"""),"Contrade Integrated Depot") -> Contrade Integrated Depot | AA18: =IFERROR(__xludf.DUMMYFUNCTION("""COMPUTED_VALUE"""),4.325444444444444) -> 4.3254444 | AC18: =IFERROR(__xludf.DUMMYFUNCTION("""COMPUTED_VALUE"""),"Booktrens Enterprises") -> Booktrens Enterprises | AD18: =IFERROR(__xludf.DUMMYFUNCTION("""COMPUTED_VALUE"""),5.0) -> 5 | AF18: =IFERROR(__xludf.DUMMYFUNCTION("""COMPUTED_VALUE"""),"Barcaman Couture Corporation") -> Barcaman Couture Corporation | AG18: =IFERROR(__xludf.DUMMYFUNCTION("""COMPUTED_VALUE"""),3.5666666666666664) -> 3.5666667
A19: 11 | B19: Times Trading Co., Inc. | C19: 4.8333333 | E19: 12 | F19: One Supply | I19: 11 | J19: CD Books International, Inc | N19: =IFERROR(__xludf.DUMMYFUNCTION("""COMPUTED_VALUE"""),"Gift Republic, Inc.") -> Gift Republic, Inc. | O19: =IFERROR(__xludf.DUMMYFUNCTION("""COMPUTED_VALUE"""),2.066666666666667) -> 2.0666667 | P19: =IFERROR(__xludf.DUMMYFUNCTION("""COMPUTED_VALUE"""),44774.0) -> 44774 | R19: =IFERROR(__xludf.DUMMYFUNCTION("""COMPUTED_VALUE"""),"Lordfel Marketing") -> Lordfel Marketing | S19: =IFERROR(__xludf.DUMMYFUNCTION("""COMPUTED_VALUE"""),4.0) -> 4 | T19: =IFERROR(__xludf.DUMMYFUNCTION("""COMPUTED_VALUE"""),45149.0) -> 45149 | V19: =IFERROR(__xludf.DUMMYFUNCTION("""COMPUTED_VALUE"""),"Contrade Integrated Depot") -> Contrade Integrated Depot | W19: =IFERROR(__xludf.DUMMYFUNCTION("""COMPUTED_VALUE"""),4.833333333333333) -> 4.8333333 | X19: =IFERROR(__xludf.DUMMYFUNCTION("""COMPUTED_VALUE"""),45510.0) -> 45510 | Z19: =IFERROR(__xludf.DUMMYFUNCTION("""COMPUTED_VALUE"""),"Creative Juice Digital Printing") -> Creative Juice Digital Printing | AA19: =IFERROR(__xludf.DUMMYFUNCTION("""COMPUTED_VALUE"""),4.775192307692308) -> 4.7751923 | AC19: =IFERROR(__xludf.DUMMYFUNCTION("""COMPUTED_VALUE"""),"Chemtrust Global Market, Inc.") -> Chemtrust Global Market, Inc. | AD19: =IFERROR(__xludf.DUMMYFUNCTION("""COMPUTED_VALUE"""),4.794444444444444) -> 4.7944444 | AF19: =IFERROR(__xludf.DUMMYFUNCTION("""COMPUTED_VALUE"""),"Belview Co., Inc.") -> Belview Co., Inc. | AG19: =IFERROR(__xludf.DUMMYFUNCTION("""COMPUTED_VALUE"""),4.986706349206351) -> 4.9867063
A20: 12 | B20: Paper Tree Marketing Group, Inc. | C20: 4.9166667 | E20: 13 | F20: Commerce Asia Inc. | G20: 4.7483333 | I20: 12 | J20: CREATIVE MIND BOOKS CENTER | N20: =IFERROR(__xludf.DUMMYFUNCTION("""COMPUTED_VALUE"""),"Awardextremes, Inc.") -> Awardextremes, Inc. | O20: =IFERROR(__xludf.DUMMYFUNCTION("""COMPUTED_VALUE"""),4.666666666666667) -> 4.6666667 | P20: =IFERROR(__xludf.DUMMYFUNCTION("""COMPUTED_VALUE"""),44778.0) -> 44778 | R20: =IFERROR(__xludf.DUMMYFUNCTION("""COMPUTED_VALUE"""),"Lordfel Marketing") -> Lordfel Marketing | S20: =IFERROR(__xludf.DUMMYFUNCTION("""COMPUTED_VALUE"""),4.0) -> 4 | T20: =IFERROR(__xludf.DUMMYFUNCTION("""COMPUTED_VALUE"""),45149.0) -> 45149 | V20: =IFERROR(__xludf.DUMMYFUNCTION("""COMPUTED_VALUE"""),"Belview Co., Inc.") -> Belview Co., Inc. | W20: =IFERROR(__xludf.DUMMYFUNCTION("""COMPUTED_VALUE"""),4.833333333333333) -> 4.8333333 | X20: =IFERROR(__xludf.DUMMYFUNCTION("""COMPUTED_VALUE"""),45510.0) -> 45510 | Z20: =IFERROR(__xludf.DUMMYFUNCTION("""COMPUTED_VALUE"""),"DKL Laboratory Supplies") -> DKL Laboratory Supplies | AA20: =IFERROR(__xludf.DUMMYFUNCTION("""COMPUTED_VALUE"""),3.8333333333333335) -> 3.8333333 | AC20: =IFERROR(__xludf.DUMMYFUNCTION("""COMPUTED_VALUE"""),"Chronos Athletics Shop") -> Chronos Athletics Shop | AD20: =IFERROR(__xludf.DUMMYFUNCTION("""COMPUTED_VALUE"""),4.519444444444445) -> 4.5194444 | AF20: =IFERROR(__xludf.DUMMYFUNCTION("""COMPUTED_VALUE"""),"Bobman Trading") -> Bobman Trading | AG20: =IFERROR(__xludf.DUMMYFUNCTION("""COMPUTED_VALUE"""),4.89074074074074) -> 4.8907407
A21: 13 | B21: EA Intertrade General Merchandising, Inc. | E21: 14 | F21: EXPRESS CARDS ENTERPRISES, CO. | I21: 13 | J21: Forefront Book Co., Inc. | N21: =IFERROR(__xludf.DUMMYFUNCTION("""COMPUTED_VALUE"""),"Gift Republic, Inc.") -> Gift Republic, Inc. | O21: =IFERROR(__xludf.DUMMYFUNCTION("""COMPUTED_VALUE"""),4.713333333333334) -> 4.7133333 | P21: =IFERROR(__xludf.DUMMYFUNCTION("""COMPUTED_VALUE"""),44778.0) -> 44778 | R21: =IFERROR(__xludf.DUMMYFUNCTION("""COMPUTED_VALUE"""),"Lordfel Marketing") -> Lordfel Marketing | S21: =IFERROR(__xludf.DUMMYFUNCTION("""COMPUTED_VALUE"""),4.0) -> 4 | T21: =IFERROR(__xludf.DUMMYFUNCTION("""COMPUTED_VALUE"""),45149.0) -> 45149 | V21: =IFERROR(__xludf.DUMMYFUNCTION("""COMPUTED_VALUE"""),"Abacus Book & Card Corp.") -> Abacus Book & Card Corp. | W21: =IFERROR(__xludf.DUMMYFUNCTION("""COMPUTED_VALUE"""),4.75) -> 4.75 | X21: =IFERROR(__xludf.DUMMYFUNCTION("""COMPUTED_VALUE"""),45512.0) -> 45512 | Z21: =IFERROR(__xludf.DUMMYFUNCTION("""COMPUTED_VALUE"""),"Data Computer Forms, Inc.") -> Data Computer Forms, Inc. | AA21: =IFERROR(__xludf.DUMMYFUNCTION("""COMPUTED_VALUE"""),4.966666666666667) -> 4.9666667 | AC21: =IFERROR(__xludf.DUMMYFUNCTION("""COMPUTED_VALUE"""),"Circuitrocks Electronic Store") -> Circuitrocks Electronic Store | AD21: =IFERROR(__xludf.DUMMYFUNCTION("""COMPUTED_VALUE"""),4.908333333333333) -> 4.9083333 | AF21: =IFERROR(__xludf.DUMMYFUNCTION("""COMPUTED_VALUE"""),"CD Books International, Inc.") -> CD Books International, Inc. | AG21: =IFERROR(__xludf.DUMMYFUNCTION("""COMPUTED_VALUE"""),4.866666666666666) -> 4.8666667
A22: 14 | B22: One Supply | E22: Computer/Peripherals/Software | G22: =average(G23:G27) -> 4.6472222 | I22: Computer/Peripherals/Software | K22: =average(K23:K30) -> 4.9320833 | N22: =IFERROR(__xludf.DUMMYFUNCTION("""COMPUTED_VALUE"""),"Leonard Prints Inc.") -> Leonard Prints Inc. | O22: =IFERROR(__xludf.DUMMYFUNCTION("""COMPUTED_VALUE"""),4.8) -> 4.8 | P22: =IFERROR(__xludf.DUMMYFUNCTION("""COMPUTED_VALUE"""),44789.0) -> 44789 | R22: =IFERROR(__xludf.DUMMYFUNCTION("""COMPUTED_VALUE"""),"Contrade Integrated Depot") -> Contrade Integrated Depot | S22: =IFERROR(__xludf.DUMMYFUNCTION("""COMPUTED_VALUE"""),4.690833333333334) -> 4.6908333 | T22: =IFERROR(__xludf.DUMMYFUNCTION("""COMPUTED_VALUE"""),45152.0) -> 45152 | V22: =IFERROR(__xludf.DUMMYFUNCTION("""COMPUTED_VALUE"""),"Mostaco Printing") -> Mostaco Printing | W22: =IFERROR(__xludf.DUMMYFUNCTION("""COMPUTED_VALUE"""),4.75) -> 4.75 | X22: =IFERROR(__xludf.DUMMYFUNCTION("""COMPUTED_VALUE"""),45513.0) -> 45513 | Z22: =IFERROR(__xludf.DUMMYFUNCTION("""COMPUTED_VALUE"""),"EIG Metal Engravers") -> EIG Metal Engravers | AA22: =IFERROR(__xludf.DUMMYFUNCTION("""COMPUTED_VALUE"""),4.5) -> 4.5 | AC22: =IFERROR(__xludf.DUMMYFUNCTION("""COMPUTED_VALUE"""),"Colent Marketing Philippines, Inc.") -> Colent Marketing Philippines, Inc. | AD22: =IFERROR(__xludf.DUMMYFUNCTION("""COMPUTED_VALUE"""),5.0) -> 5 | AF22: =IFERROR(__xludf.DUMMYFUNCTION("""COMPUTED_VALUE"""),"COMPUTECHNOLOGIES CORP.") -> COMPUTECHNOLOGIES CORP. | AG22: =IFERROR(__xludf.DUMMYFUNCTION("""COMPUTED_VALUE"""),4.858333333333333) -> 4.8583333
A23: 15 | B23: Commerce Asia Inc. | C23: 4.8125 | E23: 15 | F23: NetAd IT Solutions | G23: 4.7472222 | I23: 14 | J23: Commerce Asia Inc | N23: =IFERROR(__xludf.DUMMYFUNCTION("""COMPUTED_VALUE"""),"Contrade Integrated Depot") -> Contrade Integrated Depot | O23: =IFERROR(__xludf.DUMMYFUNCTION("""COMPUTED_VALUE"""),4.0) -> 4 | P23: =IFERROR(__xludf.DUMMYFUNCTION("""COMPUTED_VALUE"""),44791.0) -> 44791 | R23: =IFERROR(__xludf.DUMMYFUNCTION("""COMPUTED_VALUE"""),"Polaris Prime Air Tech Corporation") -> Polaris Prime Air Tech Corporation | S23: =IFERROR(__xludf.DUMMYFUNCTION("""COMPUTED_VALUE"""),4.0) -> 4 | T23: =IFERROR(__xludf.DUMMYFUNCTION("""COMPUTED_VALUE"""),45152.0) -> 45152 | V23: =IFERROR(__xludf.DUMMYFUNCTION("""COMPUTED_VALUE"""),"Print Depot Inc.") -> Print Depot Inc. | W23: =IFERROR(__xludf.DUMMYFUNCTION("""COMPUTED_VALUE"""),4.833333333333333) -> 4.8333333 | X23: =IFERROR(__xludf.DUMMYFUNCTION("""COMPUTED_VALUE"""),45514.0) -> 45514 | Z23: =IFERROR(__xludf.DUMMYFUNCTION("""COMPUTED_VALUE"""),"Ergo Contracts Phil., Inc.") -> Ergo Contracts Phil., Inc. | AA23: =IFERROR(__xludf.DUMMYFUNCTION("""COMPUTED_VALUE"""),4.766666666666667) -> 4.7666667 | AC23: =IFERROR(__xludf.DUMMYFUNCTION("""COMPUTED_VALUE"""),"Columbia Technologies, Inc.") -> Columbia Technologies, Inc. | AD23: =IFERROR(__xludf.DUMMYFUNCTION("""COMPUTED_VALUE"""),4.0) -> 4 | AF23: =IFERROR(__xludf.DUMMYFUNCTION("""COMPUTED_VALUE"""),"Chemtrust Global Market, Inc.") -> Chemtrust Global Market, Inc. | AG23: =IFERROR(__xludf.DUMMYFUNCTION("""COMPUTED_VALUE"""),4.775277777777777) -> 4.7752778
A24: 16 | B24: EXPRESS CARDS ENTERPRISES, CO. | E24: 16 | F24: Alpha-Cored Technology Systems, Inc. | G24: 5 | I24: 15 | J24: IEquity Technologies Corporation | N24: =IFERROR(__xludf.DUMMYFUNCTION("""COMPUTED_VALUE"""),"Amazon") -> Amazon | O24: =IFERROR(__xludf.DUMMYFUNCTION("""COMPUTED_VALUE"""),4.2283333333333335) -> 4.2283333 | P24: =IFERROR(__xludf.DUMMYFUNCTION("""COMPUTED_VALUE"""),44793.0) -> 44793 | R24: =IFERROR(__xludf.DUMMYFUNCTION("""COMPUTED_VALUE"""),"Abacus Book & Card Corp.") -> Abacus Book & Card Corp. | S24: =IFERROR(__xludf.DUMMYFUNCTION("""COMPUTED_VALUE"""),4.666666666666667) -> 4.6666667 | T24: =IFERROR(__xludf.DUMMYFUNCTION("""COMPUTED_VALUE"""),45153.0) -> 45153 | V24: =IFERROR(__xludf.DUMMYFUNCTION("""COMPUTED_VALUE"""),"Crosspoint Paper, Inc.") -> Crosspoint Paper, Inc. | W24: =IFERROR(__xludf.DUMMYFUNCTION("""COMPUTED_VALUE"""),4.833333333333333) -> 4.8333333 | X24: =IFERROR(__xludf.DUMMYFUNCTION("""COMPUTED_VALUE"""),45514.0) -> 45514 | Z24: =IFERROR(__xludf.DUMMYFUNCTION("""COMPUTED_VALUE"""),"Falcon Waterfree Philippines, Inc.") -> Falcon Waterfree Philippines, Inc. | AA24: =IFERROR(__xludf.DUMMYFUNCTION("""COMPUTED_VALUE"""),5.0) -> 5 | AC24: =IFERROR(__xludf.DUMMYFUNCTION("""COMPUTED_VALUE"""),"Commerce Asia, Inc.") -> Commerce Asia, Inc. | AD24: =IFERROR(__xludf.DUMMYFUNCTION("""COMPUTED_VALUE"""),4.748333333333333) -> 4.7483333 | AF24: =IFERROR(__xludf.DUMMYFUNCTION("""COMPUTED_VALUE"""),"Colent Marketing Philippines, Inc.") -> Colent Marketing Philippines, Inc. | AG24: =IFERROR(__xludf.DUMMYFUNCTION("""COMPUTED_VALUE"""),4.5) -> 4.5
A25: 17 | B25: Amalgamated Specialties Corp | E25: 8 | F25: Microsmith Technology Systems, Inc. | G25: 4.8416667 | I25: 16 | J25: Columbia Technologies ,Inc | K25: 4.9583333 | N25: =IFERROR(__xludf.DUMMYFUNCTION("""COMPUTED_VALUE"""),"Rivchem Enterprises") -> Rivchem Enterprises | O25: =IFERROR(__xludf.DUMMYFUNCTION("""COMPUTED_VALUE"""),4.766666666666667) -> 4.7666667 | P25: =IFERROR(__xludf.DUMMYFUNCTION("""COMPUTED_VALUE"""),44798.0) -> 44798 | R25: =IFERROR(__xludf.DUMMYFUNCTION("""COMPUTED_VALUE"""),"Net Ad IT Solutions") -> Net Ad IT Solutions | S25: =IFERROR(__xludf.DUMMYFUNCTION("""COMPUTED_VALUE"""),4.875) -> 4.875 | T25: =IFERROR(__xludf.DUMMYFUNCTION("""COMPUTED_VALUE"""),45157.0) -> 45157 | V25: =IFERROR(__xludf.DUMMYFUNCTION("""COMPUTED_VALUE"""),"Mostaco Printing") -> Mostaco Printing | W25: =IFERROR(__xludf.DUMMYFUNCTION("""COMPUTED_VALUE"""),4.75) -> 4.75 | X25: =IFERROR(__xludf.DUMMYFUNCTION("""COMPUTED_VALUE"""),45516.0) -> 45516 | Z25: =IFERROR(__xludf.DUMMYFUNCTION("""COMPUTED_VALUE"""),"Gift Republic, Inc.") -> Gift Republic, Inc. | AA25: =IFERROR(__xludf.DUMMYFUNCTION("""COMPUTED_VALUE"""),2.926666666666667) -> 2.9266667 | AC25: =IFERROR(__xludf.DUMMYFUNCTION("""COMPUTED_VALUE"""),"Contrade Integrated Depot") -> Contrade Integrated Depot | AD25: =IFERROR(__xludf.DUMMYFUNCTION("""COMPUTED_VALUE"""),4.6089166666666666) -> 4.6089167 | AF25: =IFERROR(__xludf.DUMMYFUNCTION("""COMPUTED_VALUE"""),"Columbia Technologies, Inc.") -> Columbia Technologies, Inc. | AG25: =IFERROR(__xludf.DUMMYFUNCTION("""COMPUTED_VALUE"""),4.941666666666666) -> 4.9416667
A26: 18 | B26: MOSTACO | C26: 4.7037037 | E26: 18 | F26: Columbia Technologies, Inc. | G26: 4 | I26: 17 | J26: Microsmith Technologies | K26: 4.9416667 | N26: =IFERROR(__xludf.DUMMYFUNCTION("""COMPUTED_VALUE"""),"Contrade Integrated Depot") -> Contrade Integrated Depot | O26: =IFERROR(__xludf.DUMMYFUNCTION("""COMPUTED_VALUE"""),3.8166666666666664) -> 3.8166667 | P26: =IFERROR(__xludf.DUMMYFUNCTION("""COMPUTED_VALUE"""),44799.0) -> 44799 | R26: =IFERROR(__xludf.DUMMYFUNCTION("""COMPUTED_VALUE"""),"Microsmith Technology System,Inc.") -> Microsmith Technology System,Inc. | S26: =IFERROR(__xludf.DUMMYFUNCTION("""COMPUTED_VALUE"""),4.833333333333333) -> 4.8333333 | T26: =IFERROR(__xludf.DUMMYFUNCTION("""COMPUTED_VALUE"""),45163.0) -> 45163 | V26: =IFERROR(__xludf.DUMMYFUNCTION("""COMPUTED_VALUE"""),"Abacus Book & Card Corp.") -> Abacus Book & Card Corp. | W26: =IFERROR(__xludf.DUMMYFUNCTION("""COMPUTED_VALUE"""),4.75) -> 4.75 | X26: =IFERROR(__xludf.DUMMYFUNCTION("""COMPUTED_VALUE"""),45516.0) -> 45516 | Z26: =IFERROR(__xludf.DUMMYFUNCTION("""COMPUTED_VALUE"""),"Hospeco Philippines, Inc.") -> Hospeco Philippines, Inc. | AA26: =IFERROR(__xludf.DUMMYFUNCTION("""COMPUTED_VALUE"""),4.683333333333334) -> 4.6833333 | AC26: =IFERROR(__xludf.DUMMYFUNCTION("""COMPUTED_VALUE"""),"Creative Juice Digital Printing") -> Creative Juice Digital Printing | AD26: =IFERROR(__xludf.DUMMYFUNCTION("""COMPUTED_VALUE"""),4.629938271604938) -> 4.6299383 | AF26: =IFERROR(__xludf.DUMMYFUNCTION("""COMPUTED_VALUE"""),"Commerce Asia, Inc.") -> Commerce Asia, Inc. | AG26: =IFERROR(__xludf.DUMMYFUNCTION("""COMPUTED_VALUE"""),4.8125) -> 4.8125
A27: Computer/Peripherals/Software | C27: =average(C28:C32) -> 4.8585438 | E27: 19 | F27: iEquity Technologies Corporation | I27: 18 | J27: EXPRESS CARDS ENTERPRISES, CO. | N27: =IFERROR(__xludf.DUMMYFUNCTION("""COMPUTED_VALUE"""),"Atlas Superflags") -> Atlas Superflags | O27: =IFERROR(__xludf.DUMMYFUNCTION("""COMPUTED_VALUE"""),5.0) -> 5 | P27: =IFERROR(__xludf.DUMMYFUNCTION("""COMPUTED_VALUE"""),44800.0) -> 44800 | R27: =IFERROR(__xludf.DUMMYFUNCTION("""COMPUTED_VALUE"""),"Atlas Superflags") -> Atlas Superflags | S27: =IFERROR(__xludf.DUMMYFUNCTION("""COMPUTED_VALUE"""),4.0) -> 4 | T27: =IFERROR(__xludf.DUMMYFUNCTION("""COMPUTED_VALUE"""),45165.0) -> 45165 | V27: =IFERROR(__xludf.DUMMYFUNCTION("""COMPUTED_VALUE"""),"Mostaco Printing") -> Mostaco Printing | W27: =IFERROR(__xludf.DUMMYFUNCTION("""COMPUTED_VALUE"""),4.75) -> 4.75 | X27: =IFERROR(__xludf.DUMMYFUNCTION("""COMPUTED_VALUE"""),45516.0) -> 45516 | Z27: =IFERROR(__xludf.DUMMYFUNCTION("""COMPUTED_VALUE"""),"Hytec Power, Inc.") -> Hytec Power, Inc. | AA27: =IFERROR(__xludf.DUMMYFUNCTION("""COMPUTED_VALUE"""),3.466666666666667) -> 3.4666667 | AC27: =IFERROR(__xludf.DUMMYFUNCTION("""COMPUTED_VALUE"""),"Crosspoint Paper, Inc.") -> Crosspoint Paper, Inc. | AD27: =IFERROR(__xludf.DUMMYFUNCTION("""COMPUTED_VALUE"""),5.0) -> 5 | AF27: =IFERROR(__xludf.DUMMYFUNCTION("""COMPUTED_VALUE"""),"Contrade Integrated Depot") -> Contrade Integrated Depot | AG27: =IFERROR(__xludf.DUMMYFUNCTION("""COMPUTED_VALUE"""),4.743253968253969) -> 4.743254
A28: 19 | B28: NetAd IT Solutions | C28: 4.8263889 | E28: Printing and Publication | G28: =average(G29:G40) -> 4.8047068 | I28: 19 | J28: Sert Technology Inc. | K28: 5 | N28: =IFERROR(__xludf.DUMMYFUNCTION("""COMPUTED_VALUE"""),"Leonard Prints Inc.") -> Leonard Prints Inc. | O28: =IFERROR(__xludf.DUMMYFUNCTION("""COMPUTED_VALUE"""),4.833333333333333) -> 4.8333333 | P28: =IFERROR(__xludf.DUMMYFUNCTION("""COMPUTED_VALUE"""),44803.0) -> 44803 | R28: =IFERROR(__xludf.DUMMYFUNCTION("""COMPUTED_VALUE"""),"Microsmith Technology System,Inc.") -> Microsmith Technology System,Inc. | S28: =IFERROR(__xludf.DUMMYFUNCTION("""COMPUTED_VALUE"""),5.0) -> 5 | T28: =IFERROR(__xludf.DUMMYFUNCTION("""COMPUTED_VALUE"""),45166.0) -> 45166 | V28: =IFERROR(__xludf.DUMMYFUNCTION("""COMPUTED_VALUE"""),"EIG Metal Engravers") -> EIG Metal Engravers | W28: =IFERROR(__xludf.DUMMYFUNCTION("""COMPUTED_VALUE"""),4.833333333333333) -> 4.8333333 | X28: =IFERROR(__xludf.DUMMYFUNCTION("""COMPUTED_VALUE"""),45517.0) -> 45517 | Z28: =IFERROR(__xludf.DUMMYFUNCTION("""COMPUTED_VALUE"""),"JC Campit And Michael Berza") -> JC Campit And Michael Berza | AA28: =IFERROR(__xludf.DUMMYFUNCTION("""COMPUTED_VALUE"""),5.0) -> 5 | AC28: =IFERROR(__xludf.DUMMYFUNCTION("""COMPUTED_VALUE"""),"DKL Laboratory Supplies") -> DKL Laboratory Supplies | AD28: =IFERROR(__xludf.DUMMYFUNCTION("""COMPUTED_VALUE"""),3.6666666666666665) -> 3.6666667 | AF28: =IFERROR(__xludf.DUMMYFUNCTION("""COMPUTED_VALUE"""),"Creative Juice Digital Printing") -> Creative Juice Digital Printing | AG28: =IFERROR(__xludf.DUMMYFUNCTION("""COMPUTED_VALUE"""),4.831249999999999) -> 4.83125
A29: 20 | B29: Alpha-Cored Technology Systems, Inc. | C29: 4.9166667 | E29: 20 | F29: Creative Juice Digital Printing | G29: 4.6299383 | I29: 20 | J29: NetAd IT Solutions | K29: 4.7604167 | N29: =IFERROR(__xludf.DUMMYFUNCTION("""COMPUTED_VALUE"""),"Microsmith Technology System,Inc.") -> Microsmith Technology System,Inc. | O29: =IFERROR(__xludf.DUMMYFUNCTION("""COMPUTED_VALUE"""),5.0) -> 5 | P29: =IFERROR(__xludf.DUMMYFUNCTION("""COMPUTED_VALUE"""),44805.0) -> 44805 | R29: =IFERROR(__xludf.DUMMYFUNCTION("""COMPUTED_VALUE"""),"Net Ad IT Solutions") -> Net Ad IT Solutions | S29: =IFERROR(__xludf.DUMMYFUNCTION("""COMPUTED_VALUE"""),5.0) -> 5 | T29: =IFERROR(__xludf.DUMMYFUNCTION("""COMPUTED_VALUE"""),45181.0) -> 45181 | V29: =IFERROR(__xludf.DUMMYFUNCTION("""COMPUTED_VALUE"""),"Commerce Asia, Inc.") -> Commerce Asia, Inc. | W29: =IFERROR(__xludf.DUMMYFUNCTION("""COMPUTED_VALUE"""),4.791666666666667) -> 4.7916667 | X29: =IFERROR(__xludf.DUMMYFUNCTION("""COMPUTED_VALUE"""),45517.0) -> 45517 | Z29: =IFERROR(__xludf.DUMMYFUNCTION("""COMPUTED_VALUE"""),"Jarm Printing Press") -> Jarm Printing Press | AA29: =IFERROR(__xludf.DUMMYFUNCTION("""COMPUTED_VALUE"""),4.75) -> 4.75 | AC29: =IFERROR(__xludf.DUMMYFUNCTION("""COMPUTED_VALUE"""),"DOOPLO ADVERTISING") -> DOOPLO ADVERTISING | AD29: =IFERROR(__xludf.DUMMYFUNCTION("""COMPUTED_VALUE"""),4.375) -> 4.375 | AF29: =IFERROR(__xludf.DUMMYFUNCTION("""COMPUTED_VALUE"""),"Crosspoint Paper, Inc.") -> Crosspoint Paper, Inc. | AG29: =IFERROR(__xludf.DUMMYFUNCTION("""COMPUTED_VALUE"""),4.944444444444444) -> 4.9444444
A30: 21 | B30: Microsmith Technology Systems, Inc. | C30: 4.8325758 | E30: 21 | F30: Velprint Corporation | I30: 21 | J30: Alpha-Cored Technology Systems Inc. | K30: 5 | N30: =IFERROR(__xludf.DUMMYFUNCTION("""COMPUTED_VALUE"""),"Amazon") -> Amazon | O30: =IFERROR(__xludf.DUMMYFUNCTION("""COMPUTED_VALUE"""),5.0) -> 5 | P30: =IFERROR(__xludf.DUMMYFUNCTION("""COMPUTED_VALUE"""),44810.0) -> 44810 | R30: =IFERROR(__xludf.DUMMYFUNCTION("""COMPUTED_VALUE"""),"Net Ad IT Solutions") -> Net Ad IT Solutions | S30: =IFERROR(__xludf.DUMMYFUNCTION("""COMPUTED_VALUE"""),4.875) -> 4.875 | T30: =IFERROR(__xludf.DUMMYFUNCTION("""COMPUTED_VALUE"""),45181.0) -> 45181 | V30: =IFERROR(__xludf.DUMMYFUNCTION("""COMPUTED_VALUE"""),"Shelves and Cups Book Store") -> Shelves and Cups Book Store | W30: =IFERROR(__xludf.DUMMYFUNCTION("""COMPUTED_VALUE"""),4.833333333333333) -> 4.8333333 | X30: =IFERROR(__xludf.DUMMYFUNCTION("""COMPUTED_VALUE"""),45517.0) -> 45517 | Z30: =IFERROR(__xludf.DUMMYFUNCTION("""COMPUTED_VALUE"""),"Leonard Prints Inc.") -> Leonard Prints Inc. | AA30: =IFERROR(__xludf.DUMMYFUNCTION("""COMPUTED_VALUE"""),4.816666666666666) -> 4.8166667 | AC30: =IFERROR(__xludf.DUMMYFUNCTION("""COMPUTED_VALUE"""),"Data Computer Forms, Inc.") -> Data Computer Forms, Inc. | AD30: =IFERROR(__xludf.DUMMYFUNCTION("""COMPUTED_VALUE"""),4.25) -> 4.25 | AF30: =IFERROR(__xludf.DUMMYFUNCTION("""COMPUTED_VALUE"""),"Data Computer Forms, Inc.") -> Data Computer Forms, Inc. | AG30: =IFERROR(__xludf.DUMMYFUNCTION("""COMPUTED_VALUE"""),4.952777777777778) -> 4.9527778
A31: 22 | B31: Columbia Technologies, Inc. | E31: 22 | F31: Luminaire Printing and Publication Corp. | G31: 4.8666667 | I31: Cleaning Supplies & Equipment | K31: =average(K32:K39) -> 4.616369 | N31: =IFERROR(__xludf.DUMMYFUNCTION("""COMPUTED_VALUE"""),"PNB Credit Card") -> PNB Credit Card | O31: =IFERROR(__xludf.DUMMYFUNCTION("""COMPUTED_VALUE"""),3.9166666666666665) -> 3.9166667 | P31: =IFERROR(__xludf.DUMMYFUNCTION("""COMPUTED_VALUE"""),44810.0) -> 44810 | R31: =IFERROR(__xludf.DUMMYFUNCTION("""COMPUTED_VALUE"""),"Abacus Book & Card Corp.") -> Abacus Book & Card Corp. | S31: =IFERROR(__xludf.DUMMYFUNCTION("""COMPUTED_VALUE"""),4.833333333333333) -> 4.8333333 | T31: =IFERROR(__xludf.DUMMYFUNCTION("""COMPUTED_VALUE"""),45181.0) -> 45181 | V31: =IFERROR(__xludf.DUMMYFUNCTION("""COMPUTED_VALUE"""),"Contrade Integrated Depot") -> Contrade Integrated Depot | W31: =IFERROR(__xludf.DUMMYFUNCTION("""COMPUTED_VALUE"""),4.666666666666667) -> 4.6666667 | X31: =IFERROR(__xludf.DUMMYFUNCTION("""COMPUTED_VALUE"""),45521.0) -> 45521 | Z31: =IFERROR(__xludf.DUMMYFUNCTION("""COMPUTED_VALUE"""),"Lordfel Marketing") -> Lordfel Marketing | AA31: =IFERROR(__xludf.DUMMYFUNCTION("""COMPUTED_VALUE"""),5.0) -> 5 | AC31: =IFERROR(__xludf.DUMMYFUNCTION("""COMPUTED_VALUE"""),"Dynamics Electrical Supply and Hardware") -> Dynamics Electrical Supply and Hardware | AD31: =IFERROR(__xludf.DUMMYFUNCTION("""COMPUTED_VALUE"""),4.0) -> 4 | AF31: =IFERROR(__xludf.DUMMYFUNCTION("""COMPUTED_VALUE"""),"Dynamics Electrical Supply and Hardware") -> Dynamics Electrical Supply and Hardware | AG31: =IFERROR(__xludf.DUMMYFUNCTION("""COMPUTED_VALUE"""),4.333333333333333) -> 4.3333333
A32: 23 | B32: iEquity Technologies Corporation | E32: 23 | F32: JARM Printing Press | G32: 4.875 | I32: 22 | J32: Belvedere Cleanvironment Phils., Inc. | N32: =IFERROR(__xludf.DUMMYFUNCTION("""COMPUTED_VALUE"""),"Abenson Ventures, Inc.") -> Abenson Ventures, Inc. | O32: =IFERROR(__xludf.DUMMYFUNCTION("""COMPUTED_VALUE"""),4.833333333333333) -> 4.8333333 | P32: =IFERROR(__xludf.DUMMYFUNCTION("""COMPUTED_VALUE"""),44812.0) -> 44812 | R32: =IFERROR(__xludf.DUMMYFUNCTION("""COMPUTED_VALUE"""),"Chemtrust Global Market, Inc.") -> Chemtrust Global Market, Inc. | S32: =IFERROR(__xludf.DUMMYFUNCTION("""COMPUTED_VALUE"""),5.0) -> 5 | T32: =IFERROR(__xludf.DUMMYFUNCTION("""COMPUTED_VALUE"""),45182.0) -> 45182 | V32: =IFERROR(__xludf.DUMMYFUNCTION("""COMPUTED_VALUE"""),"Printing Shop PrintPilipinas.com") -> Printing Shop PrintPilipinas.com | W32: =IFERROR(__xludf.DUMMYFUNCTION("""COMPUTED_VALUE"""),4.833333333333333) -> 4.8333333 | X32: =IFERROR(__xludf.DUMMYFUNCTION("""COMPUTED_VALUE"""),45523.0) -> 45523 | Z32: =IFERROR(__xludf.DUMMYFUNCTION("""COMPUTED_VALUE"""),"Luminaire Printing And Publishing Corp.") -> Luminaire Printing And Publishing Corp. | AA32: =IFERROR(__xludf.DUMMYFUNCTION("""COMPUTED_VALUE"""),4.785714285714286) -> 4.7857143 | AC32: =IFERROR(__xludf.DUMMYFUNCTION("""COMPUTED_VALUE"""),"EA Intertrade General Merchandising, Inc.") -> EA Intertrade General Merchandising, Inc. | AD32: =IFERROR(__xludf.DUMMYFUNCTION("""COMPUTED_VALUE"""),5.0) -> 5 | AF32: =IFERROR(__xludf.DUMMYFUNCTION("""COMPUTED_VALUE"""),"ECOSHIFT CORPORATION") -> ECOSHIFT CORPORATION | AG32: =IFERROR(__xludf.DUMMYFUNCTION("""COMPUTED_VALUE"""),4.966666666666667) -> 4.9666667
A33: Printing and Publication | C33: =average(C34:C44) -> 4.6960648 | E33: 24 | F33: Sprintec Printing Press, Inc. | I33: 23 | J33: Goldlink Industrial Sales | N33: =IFERROR(__xludf.DUMMYFUNCTION("""COMPUTED_VALUE"""),"Contrade Integrated Depot") -> Contrade Integrated Depot | O33: =IFERROR(__xludf.DUMMYFUNCTION("""COMPUTED_VALUE"""),4.833333333333333) -> 4.8333333 | P33: =IFERROR(__xludf.DUMMYFUNCTION("""COMPUTED_VALUE"""),44813.0) -> 44813 | R33: =IFERROR(__xludf.DUMMYFUNCTION("""COMPUTED_VALUE"""),"Chemtrust Global Market, Inc.") -> Chemtrust Global Market, Inc. | S33: =IFERROR(__xludf.DUMMYFUNCTION("""COMPUTED_VALUE"""),5.0) -> 5 | T33: =IFERROR(__xludf.DUMMYFUNCTION("""COMPUTED_VALUE"""),45184.0) -> 45184 | V33: =IFERROR(__xludf.DUMMYFUNCTION("""COMPUTED_VALUE"""),"Leonard Prints Inc.") -> Leonard Prints Inc. | W33: =IFERROR(__xludf.DUMMYFUNCTION("""COMPUTED_VALUE"""),4.791666666666667) -> 4.7916667 | X33: =IFERROR(__xludf.DUMMYFUNCTION("""COMPUTED_VALUE"""),45523.0) -> 45523 | Z33: =IFERROR(__xludf.DUMMYFUNCTION("""COMPUTED_VALUE"""),"Marguerita Maria Nina I. Kanapi") -> Marguerita Maria Nina I. Kanapi | AA33: =IFERROR(__xludf.DUMMYFUNCTION("""COMPUTED_VALUE"""),5.0) -> 5 | AC33: =IFERROR(__xludf.DUMMYFUNCTION("""COMPUTED_VALUE"""),"EESM Bookstore") -> EESM Bookstore | AD33: =IFERROR(__xludf.DUMMYFUNCTION("""COMPUTED_VALUE"""),4.808333333333333) -> 4.8083333 | AF33: =IFERROR(__xludf.DUMMYFUNCTION("""COMPUTED_VALUE"""),"EIG Metal Engravers") -> EIG Metal Engravers | AG33: =IFERROR(__xludf.DUMMYFUNCTION("""COMPUTED_VALUE"""),4.944444444444444) -> 4.9444444
